Workbook
Name __xlnm._FilterDatabase: #REF!
Name __xlnm._FilterDatabase_1: #REF!
Name aa: #REF!
Name ddd: #REF!
Name ee: #REF!
Name Goggleplay: #REF!
Name ww: #REF!
Name 내수사양상세기준: #REF!

Sheet Control
B1: ㅌ | C1: TC 추가 NO : | D1: =IFERROR(__xludf.DUMMYFUNCTION("""TC_""&""CT""&""_""&TEXT(ARRAYFORMULA(MAX(IFERROR(VALUE(REGEXEXTRACT(B34:B2095, ""\d+"")))))+1,""0000"")"),"TC_CT_2072")
B2: CCI One App | E2: EU FullTC | L2: 0.166.0 버전 이전 | M2: =IF(COUNTIF(N2:O2,"F")>=1,"FAIL",(IF(COUNTIF(N2:O2,"P")>=1,"PASS",(IF(COUNTIF(N2:O2,"N/T")>=1,"N/T",(IF(COUNTIF(N2:O2,"N/A")>=1,"N/A","-"))))))) | O2: 추가 | P2: 수정 | Q2: 삭제
E3: Project | H3: UID ver. | L3: 0.166.0, 0.167.0, 0.168.0 | M3: =IF(COUNTIF(N3:O3,"F")>=1,"FAIL",(IF(COUNTIF(N3:O3,"P")>=1,"PASS",(IF(COUNTIF(N3:O3,"N/T")>=1,"N/T",(IF(COUNTIF(N3:O3,"N/A")>=1,"N/A","-"))))))) | O3: =COUNTIFS($AB:$AB,"*"&O2&"*") | P3: =COUNTIFS($AB:$AB,"*"&P2&"*") | Q3: =COUNTIFS($AB:$AB,"*"&Q2&"*")
E4: 담당자 | H4: 작성일자 | L4: 0.169.0, 0.170.0, 0.171.0 | M4: =IF(COUNTIF(N4:O4,"F")>=1,"FAIL",(IF(COUNTIF(N4:O4,"P")>=1,"PASS",(IF(COUNTIF(N4:O4,"N/T")>=1,"N/T",(IF(COUNTIF(N4:O4,"N/A")>=1,"N/A","-")))))))
L5: 0.172.0 | M5: =IF(COUNTIF(N5:O5,"F")>=1,"FAIL",(IF(COUNTIF(N5:O5,"P")>=1,"PASS",(IF(COUNTIF(N5:O5,"N/T")>=1,"N/T",(IF(COUNTIF(N5:O5,"N/A")>=1,"N/A","-"))))))) | N5: ← 색깔 업뎃 시 직접 색 지정하지 말고, 이거 복붙해 주세요(누가 처리 했는지 히스토리 보관용)
B6: 테스트 환경
B7: Tester
B9: Test Target | D9: Total TC | E9: RunRate | F9: PassRate | G9: PASS | H9: FAIL | I9: N/A | J9: N/T | N9: Brand | O9: KOA | R9: HOA | U9: GOA
B10: Total | D10: =SUM(D11:D17) | E10: =IFERROR(SUM($G10:J10)/$D10,"-") | F10: =IFERROR($G10/(SUM(G10:H10)),"-") | G10: =SUM(G11:G17) | H10: =SUM(H11:H17) | I10: =SUM(I11:I17) | J10: =SUM(J11:J17) | N10: OS 별 결과 | O10: Total | P10: Android | Q10: iOS | R10: Total | S10: Android | T10: iOS | U10: Total
B11: Control | C11: Common | D11: =COUNTIF($D$21:$D$8853,$C11) | E11: =IFERROR(SUM($G11:J11)/$D11,"-") | F11: =IFERROR($G11/(SUM(G11:H11)),"-") | G11: =COUNTIFS($D:$D,$C11,$N:$N,G$9) | H11: =COUNTIFS($D:$D,$C11,$N:$N,H$9) | I11: =COUNTIFS($D:$D,$C11,$N:$N,I$9) | J11: =COUNTIFS($D:$D,$C11,$N:$N,J$9) | N11: Total | O11: =SUM(O12:O15) | P11: =SUM(P12:P15) | Q11: =SUM(Q12:Q15) | R11: =SUM(R12:R15) | S11: =SUM(S12:S15) | T11: =SUM(T12:T15) | U11: =SUM(U12:U15)
C12: Intro | D12: =COUNTIF($D$21:$D$8853,$C12) | E12: =IFERROR(SUM($G12:J12)/$D12,"-") | F12: =IFERROR($G12/(SUM(G12:H12)),"-") | G12: =COUNTIFS($D:$D,$C12,$N:$N,G$9) | H12: =COUNTIFS($D:$D,$C12,$N:$N,H$9) | I12: =COUNTIFS($D:$D,$C12,$N:$N,I$9) | J12: =COUNTIFS($D:$D,$C12,$N:$N,J$9) | N12: PASS | O12: =COUNTIFS(O$21:O$10779,$N12) | P12: =COUNTIFS(P$21:P$10779,"P") | Q12: =COUNTIFS(Q$21:Q$10779,"P") | R12: =COUNTIFS(R$21:R$10779,$N12) | S12: =COUNTIFS(S$21:S$10779,"P") | T12: =COUNTIFS(T$21:T$10779,"P") | U12: =COUNTIFS(U$21:U$10779,$N12)
C13: 제어 | D13: =COUNTIF($D$21:$D$8853,$C13) | E13: =IFERROR(SUM($G13:J13)/$D13,"-") | F13: =IFERROR($G13/(SUM(G13:H13)),"-") | G13: =COUNTIFS($D:$D,$C13,$N:$N,G$9) | H13: =COUNTIFS($D:$D,$C13,$N:$N,H$9) | I13: =COUNTIFS($D:$D,$C13,$N:$N,I$9) | J13: =COUNTIFS($D:$D,$C13,$N:$N,J$9) | N13: FAIL | O13: =COUNTIFS(O$21:O$10779,$N13) | P13: =COUNTIFS(P$21:P$10779,"F") | Q13: =COUNTIFS(Q$21:Q$10779,"F") | R13: =COUNTIFS(R$21:R$10779,$N13) | S13: =COUNTIFS(S$21:S$10779,"F") | T13: =COUNTIFS(T$21:T$10779,"F") | U13: =COUNTIFS(U$21:U$10779,$N13)
C14: EV | D14: =COUNTIF($D$21:$D$8853,$C14) | E14: =IFERROR(SUM($G14:J14)/$D14,"-") | F14: =IFERROR($G14/(SUM(G14:H14)),"-") | G14: =COUNTIFS($D:$D,$C14,$N:$N,G$9) | H14: =COUNTIFS($D:$D,$C14,$N:$N,H$9) | I14: =COUNTIFS($D:$D,$C14,$N:$N,I$9) | J14: =COUNTIFS($D:$D,$C14,$N:$N,J$9) | N14: N/A | O14: =COUNTIFS(O$21:O$10779,$N14) | P14: =COUNTIFS(P$21:P$10779,$N14) | Q14: =COUNTIFS(Q$21:Q$10779,$N14) | R14: =COUNTIFS(R$21:R$10779,$N14) | S14: =COUNTIFS(S$21:S$10779,$N14) | T14: =COUNTIFS(T$21:T$10779,$N14) | U14: =COUNTIFS(U$21:U$10779,$N14)
C15: 비디오 | D15: =COUNTIF($D$21:$D$8853,$C15) | E15: =IFERROR(SUM($G15:J15)/$D15,"-") | F15: =IFERROR($G15/(SUM(G15:H15)),"-") | G15: =COUNTIFS($D:$D,$C15,$N:$N,G$9) | H15: =COUNTIFS($D:$D,$C15,$N:$N,H$9) | I15: =COUNTIFS($D:$D,$C15,$N:$N,I$9) | J15: =COUNTIFS($D:$D,$C15,$N:$N,J$9) | N15: N/T | O15: =COUNTIFS(O$21:O$10779,$N15) | P15: =COUNTIFS(P$21:P$10779,$N15) | Q15: =COUNTIFS(Q$21:Q$10779,$N15) | R15: =COUNTIFS(R$21:R$10779,$N15) | S15: =COUNTIFS(S$21:S$10779,$N15) | T15: =COUNTIFS(T$21:T$10779,$N15) | U15: =COUNTIFS(U$21:U$10779,$N15)
C16: 능동형 알림 | D16: =COUNTIF($D$21:$D$8853,$C16) | E16: =IFERROR(SUM($G16:J16)/$D16,"-") | F16: =IFERROR($G16/(SUM(G16:H16)),"-") | G16: =COUNTIFS($D:$D,$C16,$N:$N,G$9) | H16: =COUNTIFS($D:$D,$C16,$N:$N,H$9) | I16: =COUNTIFS($D:$D,$C16,$N:$N,I$9) | J16: =COUNTIFS($D:$D,$C16,$N:$N,J$9)
C17: 특화 차종 | D17: =COUNTIF($D$21:$D$8853,$C17) | E17: =IFERROR(SUM($G17:J17)/$D17,"-") | F17: =IFERROR($G17/(SUM(G17:H17)),"-") | G17: =COUNTIFS($D:$D,$C17,$N:$N,G$9) | H17: =COUNTIFS($D:$D,$C17,$N:$N,H$9) | I17: =COUNTIFS($D:$D,$C17,$N:$N,I$9) | J17: =COUNTIFS($D:$D,$C17,$N:$N,J$9)
B19: TC ID | C19: 카테고리 | D19: 대분류 | E19: 중분류 | F19: 소분류 | G19: 향지 | H19: 브랜드 | I19: 우선순위 | J19: Pre-condition | L19: TC procedure | M19: Expected result | N19: Result | O19: KOA Result | P19: KOA | R19: HOA Result | S19: HOA | U19: GOA Result | V19: GOA | X19: Closed 지라 NO | Y19: 지라 NO. | Z19: NT/NA 상세 사유 | AA19: N/A N/T 필터 | AB19: LABEL
J20: App 동작 조건 | K20: 차량 동작 조건 | P20: Android | Q20: iOS | R20: Android Reason | S20: Android | T20: iOS | W20: iOS
B21: TC_CT_0001 | C21: Control | D21: Common | E21: Screen & interaction | F21: 고객 서비스 분기 별 화면 구성 | G21: KR, EU | I21: 4 | J21: 1. CCS 미가입 | L21: 1. Control 진입 | M21: 1. 기본 모드 + 가입 버튼 표출 {CCS_SERVICE_NAME}에 가입하면 더욱 다양한 서비스를 이용하실 수 있어요. 서비스 둘러보기 > {CCS_SERVICE_NAME} 가입 2. 빌트인 캠(기본 기능) 빌트인 캠 (i) 차량에서 빌트인 캠 연결 > 빌트인 캠 저장 영상 > | N21: =IF(COUNTIF(P21:W21,"F")>=1,"FAIL",(IF(COUNTIF(P21:W21,"P")>=1,"PASS",(IF(COUNTIF(P21:W21,"N/T")>=1,"N/T",(IF(COUNTIF(P21:W21,"N/A")>=1,"N/A","-"))))))) | O21: N/T | P21: N/T | T21: P | U21: =IF(COUNTIF(V21:W21,"F")>=1,"FAIL",(IF(COUNTIF(V21:W21,"P")>=1,"PASS",(IF(COUNTIF(V21:W21,"N/T")>=1,"N/T",(IF(COUNTIF(V21:W21,"N/A")>=1,"N/A","-"))))))) | V21: P | W21: P | X21: SPAQA-8491 SPAQA-10188 SPAQA-12476 SPAQA-15943 SPAQA-15677 SPAQA-15632 SPAQA-16255 SPAQA-16256 SPAQA-16861 SPAQA-15905 SPAQA-17072 SPAQA-17083 SPAQA-17666 SPAQA-18975 SPAQA-21550 SPAQA-22842 SPAQA-17666 SPAQA-22999 SPAQA-23000 SPAQA-23001 SPAQA-23433 SPAQA-25008 SPAQA-25803 SPAQA-25804 SPAQA-26284 SPAQA-26282
B22: TC_CT_1559 | C22: Control | D22: Common | E22: Screen & interaction | F22: 고객 서비스 분기 별 화면 구성 | I22: 4 | J22: 1. CCS 미가입 2. 피공유자 계정 | L22: 1. 하단 GNB 영역 확인 | M22: 1. Control 탭 미노출 | N22: =IF(COUNTIF(P22:W22,"F")>=1,"FAIL",(IF(COUNTIF(P22:W22,"P")>=1,"PASS",(IF(COUNTIF(P22:W22,"N/T")>=1,"N/T",(IF(COUNTIF(P22:W22,"N/A")>=1,"N/A","-"))))))) | O22: N/T | P22: N/T | T22: P | U22: =IF(COUNTIF(V22:W22,"F")>=1,"FAIL",(IF(COUNTIF(V22:W22,"P")>=1,"PASS",(IF(COUNTIF(V22:W22,"N/T")>=1,"N/T",(IF(COUNTIF(V22:W22,"N/A")>=1,"N/A","-"))))))) | V22: P | W22: P
B23: TC_CT_1560 | C23: Control | D23: Common | E23: Screen & interaction | F23: 고객 서비스 분기 별 화면 구성 | I23: 5 | J23: 1. 차량 미점유 | L23: 1. Control 진입 | M23: 1. 미점유, 차량 미보유 화면 표출 - CCS 소개, 차량 등록 가이드 문구 표출 {CCS_SERVICE_NAME}에 가입하면 더욱 다양한 서비스를 이용하실 수 있어요. 서비스 둘러보기 > 아이콘 "차량을 등록해 주세요." "빌트인 캠, 차량 제어 서비스를 이용할 수 있습니다." | N23: =IF(COUNTIF(P23:W23,"F")>=1,"FAIL",(IF(COUNTIF(P23:W23,"P")>=1,"PASS",(IF(COUNTIF(P23:W23,"N/T")>=1,"N/T",(IF(COUNTIF(P23:W23,"N/A")>=1,"N/A","-"))))))) | O23: N/T | P23: N/T | T23: N/T | U23: =IF(COUNTIF(V23:W23,"F")>=1,"FAIL",(IF(COUNTIF(V23:W23,"P")>=1,"PASS",(IF(COUNTIF(V23:W23,"N/T")>=1,"N/T",(IF(COUNTIF(V23:W23,"N/A")>=1,"N/A","-"))))))) | V23: N/T | W23: N/T | Z23: 미점유: 신규 계정 생성 후, 차량 한 번도 등록하지 않은 상태의 계정 K : geunhee@poliot.co.kr | AA23: N/T : 특수상황/실패 조건 필요(조건)
B24: TC_CT_1561 | C24: Control | D24: Common | E24: Screen & interaction | F24: 고객 서비스 분기 별 화면 구성 | I24: 5 | J24: 1. CCS 미지원 | L24: 1. Control 진입 | M24: 1. 기본 모드 표출 {CCS_SERVICE_NAME}에 가입하면 더욱 다양한 서비스를 이용하실 수 있어요. 서비스 둘러보기 > 2. 빌트인 캠(기본 기능) 빌트인 캠 (i) 차량에서 빌트인 캠 연결 > 빌트인 캠 저장 영상 > | N24: =IF(COUNTIF(P24:W24,"F")>=1,"FAIL",(IF(COUNTIF(P24:W24,"P")>=1,"PASS",(IF(COUNTIF(P24:W24,"N/T")>=1,"N/T",(IF(COUNTIF(P24:W24,"N/A")>=1,"N/A","-"))))))) | O24: N/T | P24: N/T | T24: N/T | U24: =IF(COUNTIF(V24:W24,"F")>=1,"FAIL",(IF(COUNTIF(V24:W24,"P")>=1,"PASS",(IF(COUNTIF(V24:W24,"N/T")>=1,"N/T",(IF(COUNTIF(V24:W24,"N/A")>=1,"N/A","-"))))))) | V24: N/T | W24: N/T | Z24: H/G : CCS 가입이 불가능한 차량 필요(N/T) K : koa.eu07.gmail.com STONIC | AA24: N/T : 차량/디바이스 필요(조건)
B25: TC_CT_0002 | C25: Control | D25: Common | E25: Screen & interaction | F25: 고객 서비스 분기 별 화면 구성 | G25: KR, EU | I25: 1 | J25: 1. 미로그인 | L25: 1. Control 진입 | M25: 1. 미로그인 모드 표출 2. CCS 소개(닷컴 국가별 URL 적용 필요) +로그인 버튼 title iC IC "{CCS_SERVICE_NAME}에 가입하시면 더 다양한 서비스를 이용하실 수 있어요." 서비스 둘러보기 > "기아차 오너라면 로그인해서 이용해보세요" 로그인 | N25: =IF(COUNTIF(P25:W25,"F")>=1,"FAIL",(IF(COUNTIF(P25:W25,"P")>=1,"PASS",(IF(COUNTIF(P25:W25,"N/T")>=1,"N/T",(IF(COUNTIF(P25:W25,"N/A")>=1,"N/A","-"))))))) | O25: N/T | P25: N/T | T25: P | U25: =IF(COUNTIF(V25:W25,"F")>=1,"FAIL",(IF(COUNTIF(V25:W25,"P")>=1,"PASS",(IF(COUNTIF(V25:W25,"N/T")>=1,"N/T",(IF(COUNTIF(V25:W25,"N/A")>=1,"N/A","-"))))))) | V25: N/A | W25: N/A | X25: SPAQA-8491 SPAQA-10188 SPAQA-12476 SPAQA-13511 SPAQA-14601 SPAQA-15008 SPAQA-22836 SPAQA-25497 SPAQA-25930 | Z25: G : 미로그인 상태로 Control 진입 불가(N/A) | AB25: CheckList
B26: TC_CT_0003 | C26: Control | D26: Common | E26: Screen & interaction | F26: 고객 서비스 분기 별 화면 구성 | G26: KR, EU | I26: 5 | J26: 1. 차량 미보유 | L26: 1. Control 진입 | M26: 1. 미점유, 차량 미보유 화면 2. CCS 소개(닷컴 국가별 URL 적용 필요) +차량 등록 가이드 문구 Title iC IC "{CCS_SERVICE_NAME}에 가입하시면 더 다양한 서비스를 이용하실 수 있어요." 서비스 둘러보기 > 아이콘 "차량을 등록해 주세요." "Dash Cam 차량 제어 서비스를 이용할 수 있습니다." | N26: =IF(COUNTIF(P26:W26,"F")>=1,"FAIL",(IF(COUNTIF(P26:W26,"P")>=1,"PASS",(IF(COUNTIF(P26:W26,"N/T")>=1,"N/T",(IF(COUNTIF(P26:W26,"N/A")>=1,"N/A","-"))))))) | O26: N/T | P26: N/T | T26: P | U26: =IF(COUNTIF(V26:W26,"F")>=1,"FAIL",(IF(COUNTIF(V26:W26,"P")>=1,"PASS",(IF(COUNTIF(V26:W26,"N/T")>=1,"N/T",(IF(COUNTIF(V26:W26,"N/A")>=1,"N/A","-"))))))) | V26: P | W26: P | X26: SPAQA-8491 SPAQA-10188 SPAQA-12476 (ICT) SPAQA-16405 SPAQA-21548 SPAQA-25220 SPAQA-25685 | Z26: 미보유: 차량 등록 후, 삭제한 상태의 계정 K: wbkong@poliot.co.kr H : juwon29@poliot.co.kr G : hmcqa.ccs01@gmail.com | AB26: 실차
B27: TC_CT_0004 | C27: Control | D27: Common | E27: Screen & interaction | F27: 고객 서비스 분기 별 화면 구성 | G27: KR, EU | I27: 5 | J27: 1. CCS 이용불가 - 장애상황 | L27: 1. Control 진입 | M27: 1. 안전모드 (CCS 서버 장애) ※ 예외 : CCS 서버 장애 상태 Control 탭 진입 시 안전모드 제공 2. 안내문구 : 제한사유 3. 문 잠금 해제 / 문 잠금 | N27: =IF(COUNTIF(P27:W27,"F")>=1,"FAIL",(IF(COUNTIF(P27:W27,"P")>=1,"PASS",(IF(COUNTIF(P27:W27,"N/T")>=1,"N/T",(IF(COUNTIF(P27:W27,"N/A")>=1,"N/A","-"))))))) | O27: N/T | P27: N/T | T27: P | U27: =IF(COUNTIF(V27:W27,"F")>=1,"FAIL",(IF(COUNTIF(V27:W27,"P")>=1,"PASS",(IF(COUNTIF(V27:W27,"N/T")>=1,"N/T",(IF(COUNTIF(V27:W27,"N/A")>=1,"N/A","-"))))))) | V27: P | W27: P | X27: SPAQA-15249 SPAQA-15746 SPAQA-15747 SPAQA-15749 SPAQA-15742 SPAQA-17676 SPAQA-17046 SPAQA-17552 SPAQA-18124 SPAQA-19585 SPAQA-19847 SPAQA-20863 SPAQA-21972 SPAQA-20864 | Z27: ※안전모드 개발자 모드로 확인 가능 CCS 이용 불가 상황 필요
B28: TC_CT_1562 | C28: Control | D28: Intro | E28: 미가입 / 미로그인 / 신약관 | F28: 미가입 | G28: KR, EU | I28: 4 | J28: 1. 피공유자 상태 2. CCS 권한 없는 상태 | L28: 1. 주사용자 가 CCS 권한 X 1. 주사용자가 피공유자에게 CCS 권한없이 차량 공유 2. 피공유자 앱 확인 | M28: 1. Control 탭 미노출 되어야 함. | N28: =IF(COUNTIF(P28:W28,"F")>=1,"FAIL",(IF(COUNTIF(P28:W28,"P")>=1,"PASS",(IF(COUNTIF(P28:W28,"N/T")>=1,"N/T",(IF(COUNTIF(P28:W28,"N/A")>=1,"N/A","-"))))))) | O28: N/T | P28: N/T | T28: P | U28: =IF(COUNTIF(V28:W28,"F")>=1,"FAIL",(IF(COUNTIF(V28:W28,"P")>=1,"PASS",(IF(COUNTIF(V28:W28,"N/T")>=1,"N/T",(IF(COUNTIF(V28:W28,"N/A")>=1,"N/A","-"))))))) | V28: P | W28: P | X28: SPAQA-24596 | Y28: SPAQA-25635 | AB28: 수정
B29: TC_CT_1563 | C29: Control | D29: Intro | E29: 미가입 / 미로그인 / 신약관 | F29: 미가입 | G29: KR, EU | I29: 4 | J29: 1. 피공유자 상태 2. CCS 권한 있는 상태 3. 피 공유자 약관 동의 받은 상태 | L29: 1. 주사용자가 피공유자에게 CCS 권한 부여 2. 피공유자 계정으로 로그인 후 앱 확인 | M29: 1. Control 탭 노출 | N29: =IF(COUNTIF(P29:W29,"F")>=1,"FAIL",(IF(COUNTIF(P29:W29,"P")>=1,"PASS",(IF(COUNTIF(P29:W29,"N/T")>=1,"N/T",(IF(COUNTIF(P29:W29,"N/A")>=1,"N/A","-"))))))) | O29: N/T | P29: N/T | T29: P | U29: =IF(COUNTIF(V29:W29,"F")>=1,"FAIL",(IF(COUNTIF(V29:W29,"P")>=1,"PASS",(IF(COUNTIF(V29:W29,"N/T")>=1,"N/T",(IF(COUNTIF(V29:W29,"N/A")>=1,"N/A","-"))))))) | V29: P | W29: P | X29: SPAQA-24596 | AB29: 수정
B30: TC_CT_0005 | C30: Control | D30: Common | E30: Screen & interaction | F30: 제어 버튼 노출 방식 | G30: KR, EU | I30: 4 | K30: 1. MQTT 지원 | L30: 1. Control 진입 2. 메인 제어 버튼 확인 | M30: 1. 제어 버튼을 토글 형태로 제공(양방향) ex) ‘문 잠금 해제’ 제어 성공 시 '문 잠금 해제' 상태로 버튼 상태 변경 | N30: =IF(COUNTIF(P30:W30,"F")>=1,"FAIL",(IF(COUNTIF(P30:W30,"P")>=1,"PASS",(IF(COUNTIF(P30:W30,"N/T")>=1,"N/T",(IF(COUNTIF(P30:W30,"N/A")>=1,"N/A","-"))))))) | O30: N/T | P30: N/T | T30: P | U30: =IF(COUNTIF(V30:W30,"F")>=1,"FAIL",(IF(COUNTIF(V30:W30,"P")>=1,"PASS",(IF(COUNTIF(V30:W30,"N/T")>=1,"N/T",(IF(COUNTIF(V30:W30,"N/A")>=1,"N/A","-"))))))) | V30: P | W30: P | Z30: K : MV원격사용불가(방전)
B31: TC_CT_0006 | C31: Control | D31: Common | E31: Screen & interaction | F31: 제어 버튼 노출 방식 | G31: KR, EU | I31: 4 | K31: 1. MQTT 이전 | L31: 1. Control 진입 2. 메인 제어 버튼 확인 | M31: 1. 제어 버튼을 팝업 형태로 제공(단방향) - 차량 현재 상태값을 알 수 없기 때문에 모두 제공) | N31: =IF(COUNTIF(P31:W31,"F")>=1,"FAIL",(IF(COUNTIF(P31:W31,"P")>=1,"PASS",(IF(COUNTIF(P31:W31,"N/T")>=1,"N/T",(IF(COUNTIF(P31:W31,"N/A")>=1,"N/A","-"))))))) | O31: N/T | P31: N/T | T31: P | U31: =IF(COUNTIF(V31:W31,"F")>=1,"FAIL",(IF(COUNTIF(V31:W31,"P")>=1,"PASS",(IF(COUNTIF(V31:W31,"N/T")>=1,"N/T",(IF(COUNTIF(V31:W31,"N/A")>=1,"N/A","-"))))))) | V31: P | W31: P
B32: TC_CT_0007 | C32: Control | D32: Common | E32: Screen & interaction | F32: 서브 제어 동작 사양 | G32: KR, EU | I32: 4 | L32: 1. Control 진입 2. 제어 진입 3. 서브 제어 버튼 선택 4. 차량 이미지 선택 | M32: 1. sub tab 닫힘 | N32: =IF(COUNTIF(P32:W32,"F")>=1,"FAIL",(IF(COUNTIF(P32:W32,"P")>=1,"PASS",(IF(COUNTIF(P32:W32,"N/T")>=1,"N/T",(IF(COUNTIF(P32:W32,"N/A")>=1,"N/A","-"))))))) | O32: N/T | P32: N/T | T32: P | U32: =IF(COUNTIF(V32:W32,"F")>=1,"FAIL",(IF(COUNTIF(V32:W32,"P")>=1,"PASS",(IF(COUNTIF(V32:W32,"N/T")>=1,"N/T",(IF(COUNTIF(V32:W32,"N/A")>=1,"N/A","-"))))))) | V32: P | W32: P
B33: TC_CT_0008 | C33: Control | D33: Common | E33: Screen & interaction | F33: 서브 제어 동작 사양 | G33: KR, EU | I33: 4 | L33: 1. Control 진입 2. 제어 진입 3. 서브 제어 버튼 선택 4. 서브 제어 영역 swipe to right | M33: 1. sub tab 닫힘 | N33: =IF(COUNTIF(P33:W33,"F")>=1,"FAIL",(IF(COUNTIF(P33:W33,"P")>=1,"PASS",(IF(COUNTIF(P33:W33,"N/T")>=1,"N/T",(IF(COUNTIF(P33:W33,"N/A")>=1,"N/A","-"))))))) | O33: N/T | P33: N/T | T33: P | U33: =IF(COUNTIF(V33:W33,"F")>=1,"FAIL",(IF(COUNTIF(V33:W33,"P")>=1,"PASS",(IF(COUNTIF(V33:W33,"N/T")>=1,"N/T",(IF(COUNTIF(V33:W33,"N/A")>=1,"N/A","-"))))))) | V33: P | W33: P
B34: TC_CT_0009 | C34: Control | D34: Common | E34: Screen & interaction | F34: 서브 제어 동작 사양 | G34: KR, EU | I34: 4 | L34: 1. Control 진입 2. 제어 진입 3. 서브 제어 버튼 선택 4. 선택한 서브 제어 버튼 재선택 | M34: 1. sub tab 닫힘 | N34: =IF(COUNTIF(P34:W34,"F")>=1,"FAIL",(IF(COUNTIF(P34:W34,"P")>=1,"PASS",(IF(COUNTIF(P34:W34,"N/T")>=1,"N/T",(IF(COUNTIF(P34:W34,"N/A")>=1,"N/A","-"))))))) | O34: N/T | P34: N/T | T34: P | U34: =IF(COUNTIF(V34:W34,"F")>=1,"FAIL",(IF(COUNTIF(V34:W34,"P")>=1,"PASS",(IF(COUNTIF(V34:W34,"N/T")>=1,"N/T",(IF(COUNTIF(V34:W34,"N/A")>=1,"N/A","-"))))))) | V34: P | W34: P
B35: TC_CT_0010 | C35: Control | D35: Common | E35: Screen & interaction | F35: 서브 제어 동작 사양 | G35: KR, EU | I35: 4 | J35: 1. iOS Only | L35: 1. Control 진입 2. 제어 진입 3. 서브 제어 버튼 선택 4. 빈 영역 선택 | M35: 1. sub tab 닫힘 | N35: =IF(COUNTIF(P35:W35,"F")>=1,"FAIL",(IF(COUNTIF(P35:W35,"P")>=1,"PASS",(IF(COUNTIF(P35:W35,"N/T")>=1,"N/T",(IF(COUNTIF(P35:W35,"N/A")>=1,"N/A","-"))))))) | O35: N/T | P35: N/T | T35: P | U35: =IF(COUNTIF(V35:W35,"F")>=1,"FAIL",(IF(COUNTIF(V35:W35,"P")>=1,"PASS",(IF(COUNTIF(V35:W35,"N/T")>=1,"N/T",(IF(COUNTIF(V35:W35,"N/A")>=1,"N/A","-"))))))) | V35: N/A | W35: P
B36: TC_CT_0011 | C36: Control | D36: Common | E36: Screen & interaction | F36: 서브 제어 동작 사양 | G36: KR, EU | I36: 4 | J36: 1. 예외 Case - Z Fold 1. 대화면 폼팩터 단말(Android) ex) Z Fold 단말 | L36: 1. Control 진입 2. 제어 진입 3. 서브 제어 버튼 선택 4. 차량 이미지 선택 | M36: 1. 차량 상태 상세로 이동 | N36: =IF(COUNTIF(P36:W36,"F")>=1,"FAIL",(IF(COUNTIF(P36:W36,"P")>=1,"PASS",(IF(COUNTIF(P36:W36,"N/T")>=1,"N/T",(IF(COUNTIF(P36:W36,"N/A")>=1,"N/A","-"))))))) | O36: N/T | P36: N/T | T36: N/A | U36: =IF(COUNTIF(V36:W36,"F")>=1,"FAIL",(IF(COUNTIF(V36:W36,"P")>=1,"PASS",(IF(COUNTIF(V36:W36,"N/T")>=1,"N/T",(IF(COUNTIF(V36:W36,"N/A")>=1,"N/A","-"))))))) | V36: P | W36: N/A | AB36: 수정
B37: TC_CT_1564 | C37: Control | D37: Common | E37: Screen & interaction | F37: 서브 제어 동작 사양 | G37: KR, EU | I37: 4 | J37: 1. 예외 Case - Z Fold 1. 대화면 폼팩터 단말(Android) ex) Z Fold 단말 | L37: 1. Control 진입 2. 제어 진입 3. 서브 제어 버튼 선택 4. 서브 제어 영역 내에서 Swipe to right 동작 | M37: 1. Sub tab 닫힘 | N37: =IF(COUNTIF(P37:W37,"F")>=1,"FAIL",(IF(COUNTIF(P37:W37,"P")>=1,"PASS",(IF(COUNTIF(P37:W37,"N/T")>=1,"N/T",(IF(COUNTIF(P37:W37,"N/A")>=1,"N/A","-"))))))) | O37: N/T | P37: N/T | T37: N/A | U37: =IF(COUNTIF(V37:W37,"F")>=1,"FAIL",(IF(COUNTIF(V37:W37,"P")>=1,"PASS",(IF(COUNTIF(V37:W37,"N/T")>=1,"N/T",(IF(COUNTIF(V37:W37,"N/A")>=1,"N/A","-"))))))) | V37: P | W37: N/A | AB37: 수정
B38: TC_CT_1565 | C38: Control | D38: Common | E38: Screen & interaction | F38: 서브 제어 동작 사양 | G38: KR, EU | I38: 4 | J38: 1. 예외 Case - Z Fold 1. 대화면 폼팩터 단말(Android) ex) Z Fold 단말 | L38: 1. Control 진입 2. 제어 진입 3. 서브 제어 버튼 선택 4. 선택한 서브 제어 버튼 재선택 | M38: 3. Sub tab 닫힘 | N38: =IF(COUNTIF(P38:W38,"F")>=1,"FAIL",(IF(COUNTIF(P38:W38,"P")>=1,"PASS",(IF(COUNTIF(P38:W38,"N/T")>=1,"N/T",(IF(COUNTIF(P38:W38,"N/A")>=1,"N/A","-"))))))) | O38: N/T | P38: N/T | T38: N/A | U38: =IF(COUNTIF(V38:W38,"F")>=1,"FAIL",(IF(COUNTIF(V38:W38,"P")>=1,"PASS",(IF(COUNTIF(V38:W38,"N/T")>=1,"N/T",(IF(COUNTIF(V38:W38,"N/A")>=1,"N/A","-"))))))) | V38: P | W38: N/A | AB38: 수정
B39: TC_CT_1558 | C39: Control | D39: Common | E39: Screen & interaction | F39: 서브 제어 동작 사양 | G39: KR, EU | I39: 4 | J39: 1. Android Only | L39: 1. Control 진입 2. 서브 제어 버튼 선택하여 Sub tab 열기 3. OS back key 선택 | M39: 1. Sub tab 닫힘 | N39: =IF(COUNTIF(P39:W39,"F")>=1,"FAIL",(IF(COUNTIF(P39:W39,"P")>=1,"PASS",(IF(COUNTIF(P39:W39,"N/T")>=1,"N/T",(IF(COUNTIF(P39:W39,"N/A")>=1,"N/A","-"))))))) | O39: N/T | P39: N/T | T39: N/A | U39: =IF(COUNTIF(V39:W39,"F")>=1,"FAIL",(IF(COUNTIF(V39:W39,"P")>=1,"PASS",(IF(COUNTIF(V39:W39,"N/T")>=1,"N/T",(IF(COUNTIF(V39:W39,"N/A")>=1,"N/A","-"))))))) | V39: P | W39: N/A
B40: TC_CT_0012 | C40: Control | D40: Common | E40: Screen & interaction | F40: 서브 제어 동작 사양 | G40: KR, EU | I40: 4 | L40: 1. Control 진입 2. 제어 진입 3. 서브 제어 버튼 선택하여 탭 표출 4. 화면 위,아래로 스크롤 동작 | M40: 1. 서브 제어 메뉴 포커스 유지 | N40: =IF(COUNTIF(P40:W40,"F")>=1,"FAIL",(IF(COUNTIF(P40:W40,"P")>=1,"PASS",(IF(COUNTIF(P40:W40,"N/T")>=1,"N/T",(IF(COUNTIF(P40:W40,"N/A")>=1,"N/A","-"))))))) | O40: N/T | P40: N/T | T40: P | U40: =IF(COUNTIF(V40:W40,"F")>=1,"FAIL",(IF(COUNTIF(V40:W40,"P")>=1,"PASS",(IF(COUNTIF(V40:W40,"N/T")>=1,"N/T",(IF(COUNTIF(V40:W40,"N/A")>=1,"N/A","-"))))))) | V40: P | W40: P | X40: SPAQA-12676
B41: TC_CT_1566 | C41: Control | D41: Common | E41: Screen & interaction | F41: 서브 제어 동작 사양 | G41: KR, EU | I41: 4 | L41: 1. Control 진입 2. 제어 진입 3. 서브 제어 버튼 선택하여 탭 표출 4. 다른 탭 이동 후 재진입(ex MyCar 이동 후, Control 재진입) | M41: 1. 서브 제어 메뉴 포커스 유지 | N41: =IF(COUNTIF(P41:W41,"F")>=1,"FAIL",(IF(COUNTIF(P41:W41,"P")>=1,"PASS",(IF(COUNTIF(P41:W41,"N/T")>=1,"N/T",(IF(COUNTIF(P41:W41,"N/A")>=1,"N/A","-"))))))) | O41: N/T | P41: N/T | T41: P | U41: =IF(COUNTIF(V41:W41,"F")>=1,"FAIL",(IF(COUNTIF(V41:W41,"P")>=1,"PASS",(IF(COUNTIF(V41:W41,"N/T")>=1,"N/T",(IF(COUNTIF(V41:W41,"N/A")>=1,"N/A","-"))))))) | V41: P | W41: P
B42: TC_CT_0013 | C42: Control | D42: Common | E42: Screen & interaction | F42: 서브 제어 동작 사양 | G42: KR, EU | I42: 4 | K42: 1. 서브 제어 탭 : 창문, 환기, 커튼 있는 차량 | L42: 1. Control 진입 2. 제어 진입 3. 창문/ 커튼 제어 버튼 선택 | M42: 1. “창문 열기” or “환기하기” 제어 성공 시, 창문 열림 상태로 전환 2. “창문 닫기” or “커튼 올림” 제어 성공 시, 창문 닫힘 상태로 전환 | N42: =IF(COUNTIF(P42:W42,"F")>=1,"FAIL",(IF(COUNTIF(P42:W42,"P")>=1,"PASS",(IF(COUNTIF(P42:W42,"N/T")>=1,"N/T",(IF(COUNTIF(P42:W42,"N/A")>=1,"N/A","-"))))))) | O42: N/T | P42: N/T | T42: N/A | U42: =IF(COUNTIF(V42:W42,"F")>=1,"FAIL",(IF(COUNTIF(V42:W42,"P")>=1,"PASS",(IF(COUNTIF(V42:W42,"N/T")>=1,"N/T",(IF(COUNTIF(V42:W42,"N/A")>=1,"N/A","-"))))))) | V42: N/A | W42: N/A | X42: SPAQA-13307 SPAQA-16661 | Z42: 내용 중복으로 TC 삭제 | AA42: 사양 아님(N/A) | AB42: 삭제
B43: TC_CT_0041 | C43: Control | D43: Common | E43: Screen & interaction | F43: Skeleton UI | G43: KR, EU | I43: 1 | L43: 1. Control 진입 2. EV 탭 선택 3. 충전 설정 화면 진입 | M43: 1. 스켈레톤 UI 표출 ※ 로딩이 완료되어도 최소"1초" 동안 유지 ※ 로딩 완료 시, 실제 데이터로 대체 | N43: =IF(COUNTIF(P43:W43,"F")>=1,"FAIL",(IF(COUNTIF(P43:W43,"P")>=1,"PASS",(IF(COUNTIF(P43:W43,"N/T")>=1,"N/T",(IF(COUNTIF(P43:W43,"N/A")>=1,"N/A","-"))))))) | O43: N/T | P43: N/T | T43: P | U43: =IF(COUNTIF(V43:W43,"F")>=1,"FAIL",(IF(COUNTIF(V43:W43,"P")>=1,"PASS",(IF(COUNTIF(V43:W43,"N/T")>=1,"N/T",(IF(COUNTIF(V43:W43,"N/A")>=1,"N/A","-"))))))) | V43: P | W43: P | X43: SPAQA-15224 | AB43: CheckList
B44: TC_CT_1567 | C44: Control | D44: Common | E44: Screen & interaction | F44: 영상 이미지 보기 동작 사양 | G44: KR, EU | H44: HOA, GOA | I44: 1 | L44: 1. Control 진입 2. 비디오 탭 선택 3. 저장된 영상/이미지 보기 화면 진입 4. Pinch In/Out 동작 확인 | M44: 1. 영상/이미지 확대,축소 미동작 | N44: =IF(COUNTIF(P44:W44,"F")>=1,"FAIL",(IF(COUNTIF(P44:W44,"P")>=1,"PASS",(IF(COUNTIF(P44:W44,"N/T")>=1,"N/T",(IF(COUNTIF(P44:W44,"N/A")>=1,"N/A","-"))))))) | O44: N/T | P44: N/T | T44: P | U44: =IF(COUNTIF(V44:W44,"F")>=1,"FAIL",(IF(COUNTIF(V44:W44,"P")>=1,"PASS",(IF(COUNTIF(V44:W44,"N/T")>=1,"N/T",(IF(COUNTIF(V44:W44,"N/A")>=1,"N/A","-"))))))) | V44: P | W44: P | Z44: K : 비디오 탭 미지원 G : 어떤 상태에서 Pinch IN.OUT 했을 때 확대/축소 불가한건지 TC 보완 필요 | AB44: CheckList
B45: TC_CT_1568 | C45: Control | D45: Common | E45: Screen & interaction | F45: 영상 이미지 보기 동작 사양 | G45: KR, EU | H45: HOA, GOA | I45: 1 | K45: 1. 내 차 주변 영상 보기 지원 | L45: 1. Control 진입 2. 비디오 탭 선택 3. 내 차 주변 영상 보기 화면 진입 4. 가로모드로 전환 5. Pinch In/Out 동작 확인 | M45: 1. 영상/이미지 확대,축소 동작 ※ 내 차 주변 영상 보기에선 가로모드에서만 Pinch In/Out 가능(탑뷰 제외) | N45: =IF(COUNTIF(P45:W45,"F")>=1,"FAIL",(IF(COUNTIF(P45:W45,"P")>=1,"PASS",(IF(COUNTIF(P45:W45,"N/T")>=1,"N/T",(IF(COUNTIF(P45:W45,"N/A")>=1,"N/A","-"))))))) | O45: N/T | P45: N/T | T45: P | U45: =IF(COUNTIF(V45:W45,"F")>=1,"FAIL",(IF(COUNTIF(V45:W45,"P")>=1,"PASS",(IF(COUNTIF(V45:W45,"N/T")>=1,"N/T",(IF(COUNTIF(V45:W45,"N/A")>=1,"N/A","-"))))))) | V45: P | W45: P | Z45: K : 비디오 탭 미지원
B46: TC_CT_1569 | C46: Control | D46: Common | E46: Screen & interaction | F46: 영상 이미지 보기 동작 사양 | G46: KR, EU | H46: HOA, GOA | I46: 1 | L46: 1. Control 진입 2. 비디오 탭 선택 3. 저장된 영상/이미지 보기 화면 진입 4. 영상/이미지 확대 5. Touch&Move 동작 확인 | M46: 1. 영상/이미지의 포커스가 동작하는 대로 이동 | N46: =IF(COUNTIF(P46:W46,"F")>=1,"FAIL",(IF(COUNTIF(P46:W46,"P")>=1,"PASS",(IF(COUNTIF(P46:W46,"N/T")>=1,"N/T",(IF(COUNTIF(P46:W46,"N/A")>=1,"N/A","-"))))))) | O46: N/T | P46: N/T | T46: P | U46: =IF(COUNTIF(V46:W46,"F")>=1,"FAIL",(IF(COUNTIF(V46:W46,"P")>=1,"PASS",(IF(COUNTIF(V46:W46,"N/T")>=1,"N/T",(IF(COUNTIF(V46:W46,"N/A")>=1,"N/A","-"))))))) | V46: P | W46: P | Z46: K : 비디오 탭 미지원
B47: TC_CT_1570 | C47: Control | D47: Common | E47: Screen & interaction | F47: 영상 이미지 보기 동작 사양 | G47: KR, EU | H47: HOA, GOA | I47: 1 | L47: 1. Control 진입 2. 비디오 탭 선택 3. 저장된 영상/이미지 보기 화면 진입 4. 컨트롤러 표출 상태에서 Pinch In/Out, Touch&Move 동작 확인 | M47: 1. 확대 축소, 드래그 동작 불가 | N47: =IF(COUNTIF(P47:W47,"F")>=1,"FAIL",(IF(COUNTIF(P47:W47,"P")>=1,"PASS",(IF(COUNTIF(P47:W47,"N/T")>=1,"N/T",(IF(COUNTIF(P47:W47,"N/A")>=1,"N/A","-"))))))) | O47: N/T | P47: N/T | T47: P | U47: =IF(COUNTIF(V47:W47,"F")>=1,"FAIL",(IF(COUNTIF(V47:W47,"P")>=1,"PASS",(IF(COUNTIF(V47:W47,"N/T")>=1,"N/T",(IF(COUNTIF(V47:W47,"N/A")>=1,"N/A","-"))))))) | V47: P | W47: P | Z47: K : 비디오 탭 미지원
B48: TC_CT_1571 | C48: Control | D48: Common | E48: Screen & interaction | F48: 영상 이미지 보기 동작 사양 | G48: KR, EU | H48: HOA, GOA | I48: 1 | L48: 1. Control 진입 2. 비디오 탭 선택 3. 저장된 영상/이미지 보기 화면 진입 4. 세로모드에서 Pinch In/Out 동작 5. 가로모드로 변경 | M48: 1. 확대,축소 배율이 유지됨 ※ iOS는 센터 포지셔닝 불가 | N48: =IF(COUNTIF(P48:W48,"F")>=1,"FAIL",(IF(COUNTIF(P48:W48,"P")>=1,"PASS",(IF(COUNTIF(P48:W48,"N/T")>=1,"N/T",(IF(COUNTIF(P48:W48,"N/A")>=1,"N/A","-"))))))) | O48: N/T | P48: N/T | T48: P | U48: =IF(COUNTIF(V48:W48,"F")>=1,"FAIL",(IF(COUNTIF(V48:W48,"P")>=1,"PASS",(IF(COUNTIF(V48:W48,"N/T")>=1,"N/T",(IF(COUNTIF(V48:W48,"N/A")>=1,"N/A","-"))))))) | V48: P | W48: P | Z48: K : 비디오 탭 미지원
B49: TC_CT_1572 | C49: Control | D49: Common | E49: Screen & interaction | F49: 영상 이미지 보기 동작 사양 | G49: KR, EU | H49: HOA, GOA | I49: 1 | L49: 1. Control 진입 2. 비디오 탭 선택 3. 저장된 영상/이미지 보기 화면 진입 4. Pinch In/Out 동작으로 배율 변경 5. 전,후방 영상 선택 | M49: 1. Pinch In/Out 설정 유지되지 않음 | N49: =IF(COUNTIF(P49:W49,"F")>=1,"FAIL",(IF(COUNTIF(P49:W49,"P")>=1,"PASS",(IF(COUNTIF(P49:W49,"N/T")>=1,"N/T",(IF(COUNTIF(P49:W49,"N/A")>=1,"N/A","-"))))))) | O49: N/T | P49: N/T | T49: P | U49: =IF(COUNTIF(V49:W49,"F")>=1,"FAIL",(IF(COUNTIF(V49:W49,"P")>=1,"PASS",(IF(COUNTIF(V49:W49,"N/T")>=1,"N/T",(IF(COUNTIF(V49:W49,"N/A")>=1,"N/A","-"))))))) | V49: P | W49: P | Z49: K : 비디오 탭 미지원
B50: TC_CT_1573 | C50: Control | D50: Common | E50: Screen & interaction | F50: 영상 이미지 보기 동작 사양 | G50: KR, EU | H50: HOA, GOA | I50: 1 | J50: 1. 이전/다음 파일로 이동 가능한 경우 | L50: 1. Control 진입 2. 비디오 탭 선택 3. 저장된 영상/이미지 보기 화면 진입 4. 좌/우 Flick 동작 | M50: 1. 이전/다음, 영상/이미지로 이동 | N50: =IF(COUNTIF(P50:W50,"F")>=1,"FAIL",(IF(COUNTIF(P50:W50,"P")>=1,"PASS",(IF(COUNTIF(P50:W50,"N/T")>=1,"N/T",(IF(COUNTIF(P50:W50,"N/A")>=1,"N/A","-"))))))) | O50: N/T | P50: N/T | T50: P | U50: =IF(COUNTIF(V50:W50,"F")>=1,"FAIL",(IF(COUNTIF(V50:W50,"P")>=1,"PASS",(IF(COUNTIF(V50:W50,"N/T")>=1,"N/T",(IF(COUNTIF(V50:W50,"N/A")>=1,"N/A","-"))))))) | V50: P | W50: P | Z50: K : 비디오 탭 미지원
B51: TC_CT_0014 | C51: Control | D51: Common | E51: 차량 제어 관련 UI | F51: 제어 연결 | G51: KR, EU | I51: 4 | K51: 1. EV5 앱모드 | L51: 1. Control 진입 2. 제어 진입 3. 모든 제어 버튼 누른 상태 0.5초 이내 Touch Up | M51: 1. 제어 요청 실패 토스트 팝업 표출 "Press and hold the button for 1 second to activate the control." | N51: =IF(COUNTIF(P51:W51,"F")>=1,"FAIL",(IF(COUNTIF(P51:W51,"P")>=1,"PASS",(IF(COUNTIF(P51:W51,"N/T")>=1,"N/T",(IF(COUNTIF(P51:W51,"N/A")>=1,"N/A","-"))))))) | O51: N/T | P51: N/T | T51: P | U51: =IF(COUNTIF(V51:W51,"F")>=1,"FAIL",(IF(COUNTIF(V51:W51,"P")>=1,"PASS",(IF(COUNTIF(V51:W51,"N/T")>=1,"N/T",(IF(COUNTIF(V51:W51,"N/A")>=1,"N/A","-"))))))) | V51: F | W51: P | Y51: SPAQA-22711
B52: TC_CT_1825 | C52: Control | D52: Common | E52: 차량 제어 관련 UI | F52: 제어 연결 | G52: KR, EU | I52: 4 | K52: 1. EV4 앱모드 | L52: 1. Control 진입 2. 제어 진입 3. 모든 제어 버튼 누른 상태 0.5초 이내 Touch Up | M52: 1. 제어 요청 실패 토스트 팝업 표출 "Press and hold the button for 1 second to activate the control." | N52: =IF(COUNTIF(P52:W52,"F")>=1,"FAIL",(IF(COUNTIF(P52:W52,"P")>=1,"PASS",(IF(COUNTIF(P52:W52,"N/T")>=1,"N/T",(IF(COUNTIF(P52:W52,"N/A")>=1,"N/A","-"))))))) | O52: N/T | P52: N/T | T52: P | U52: =IF(COUNTIF(V52:W52,"F")>=1,"FAIL",(IF(COUNTIF(V52:W52,"P")>=1,"PASS",(IF(COUNTIF(V52:W52,"N/T")>=1,"N/T",(IF(COUNTIF(V52:W52,"N/A")>=1,"N/A","-"))))))) | V52: P | W52: P | Z52: K : EV4 차량 필요 | AA52: N/T : 차량/디바이스 필요(조건)
B53: TC_CT_1826 | C53: Control | D53: Common | E53: 차량 제어 관련 UI | F53: 제어 연결 | G53: KR, EU | I53: 4 | K53: 1. PHEV4 앱모드 | L53: 1. Control 진입 2. 제어 진입 3. 모든 제어 버튼 누른 상태 0.5초 이내 Touch Up | M53: 1. 제어 요청 실패 토스트 팝업 표출 "Press and hold the button for 1 second to activate the control." | N53: =IF(COUNTIF(P53:W53,"F")>=1,"FAIL",(IF(COUNTIF(P53:W53,"P")>=1,"PASS",(IF(COUNTIF(P53:W53,"N/T")>=1,"N/T",(IF(COUNTIF(P53:W53,"N/A")>=1,"N/A","-"))))))) | O53: N/T | P53: N/T | T53: P | U53: =IF(COUNTIF(V53:W53,"F")>=1,"FAIL",(IF(COUNTIF(V53:W53,"P")>=1,"PASS",(IF(COUNTIF(V53:W53,"N/T")>=1,"N/T",(IF(COUNTIF(V53:W53,"N/A")>=1,"N/A","-"))))))) | V53: N/A | W53: N/A | Z53: G : PHEV 비대상 차종(N/A) | AA53: 비대상 차종(N/A)
B54: TC_CT_0015 | C54: Control | D54: Common | E54: 차량 제어 관련 UI | F54: 제어 연결 | G54: KR, EU | I54: 4 | K54: 1. EV5 앱모드 | L54: 1. Control 진입 2. 제어 진입 3. 모든 제어 버튼 누른 상태 0.5초 이상 유지 후 Touch up | M54: 1. 제어 명령 전송 프로세스 실행 ex) Pin 입력 > 로딩 애니메이션 > 블링킹 애니메이션 2. 터치 유지 0.5초 넘어가는 순간 햅틱 제공 | N54: =IF(COUNTIF(P54:W54,"F")>=1,"FAIL",(IF(COUNTIF(P54:W54,"P")>=1,"PASS",(IF(COUNTIF(P54:W54,"N/T")>=1,"N/T",(IF(COUNTIF(P54:W54,"N/A")>=1,"N/A","-"))))))) | O54: N/T | P54: N/T | T54: P | U54: =IF(COUNTIF(V54:W54,"F")>=1,"FAIL",(IF(COUNTIF(V54:W54,"P")>=1,"PASS",(IF(COUNTIF(V54:W54,"N/T")>=1,"N/T",(IF(COUNTIF(V54:W54,"N/A")>=1,"N/A","-"))))))) | V54: P | W54: P | X54: SPAQA-12896 SPAQA-18166 SPAQA-18416 SPAQA-19555 SPAQA-20771 SPAQA-25348
B55: TC_CT_1827 | C55: Control | D55: Common | E55: 차량 제어 관련 UI | F55: 제어 연결 | G55: KR, EU | I55: 4 | K55: 1. EV4 앱모드 | L55: 1. Control 진입 2. 제어 진입 3. 모든 제어 버튼 누른 상태 0.5초 이상 유지 후 Touch up | M55: 1. 제어 명령 전송 프로세스 실행 ex) Pin 입력 > 로딩 애니메이션 > 블링킹 애니메이션 2. 터치 유지 0.5초 넘어가는 순간 햅틱 제공 | N55: =IF(COUNTIF(P55:W55,"F")>=1,"FAIL",(IF(COUNTIF(P55:W55,"P")>=1,"PASS",(IF(COUNTIF(P55:W55,"N/T")>=1,"N/T",(IF(COUNTIF(P55:W55,"N/A")>=1,"N/A","-"))))))) | O55: N/T | P55: N/T | T55: P | U55: =IF(COUNTIF(V55:W55,"F")>=1,"FAIL",(IF(COUNTIF(V55:W55,"P")>=1,"PASS",(IF(COUNTIF(V55:W55,"N/T")>=1,"N/T",(IF(COUNTIF(V55:W55,"N/A")>=1,"N/A","-"))))))) | V55: P | W55: P | Z55: K : EV4 차량 필요 | AA55: N/T : 차량/디바이스 필요(조건)
B56: TC_CT_1828 | C56: Control | D56: Common | E56: 차량 제어 관련 UI | F56: 제어 연결 | G56: KR, EU | I56: 4 | K56: 1. PHEV4 앱모드 | L56: 1. Control 진입 2. 제어 진입 3. 모든 제어 버튼 누른 상태 0.5초 이상 유지 후 Touch up | M56: 1. 제어 명령 전송 프로세스 실행 ex) Pin 입력 > 로딩 애니메이션 > 블링킹 애니메이션 2. 터치 유지 0.5초 넘어가는 순간 햅틱 제공 | N56: =IF(COUNTIF(P56:W56,"F")>=1,"FAIL",(IF(COUNTIF(P56:W56,"P")>=1,"PASS",(IF(COUNTIF(P56:W56,"N/T")>=1,"N/T",(IF(COUNTIF(P56:W56,"N/A")>=1,"N/A","-"))))))) | O56: N/T | P56: N/T | T56: P | U56: =IF(COUNTIF(V56:W56,"F")>=1,"FAIL",(IF(COUNTIF(V56:W56,"P")>=1,"PASS",(IF(COUNTIF(V56:W56,"N/T")>=1,"N/T",(IF(COUNTIF(V56:W56,"N/A")>=1,"N/A","-"))))))) | V56: N/A | W56: N/A | Z56: G : PHEV 비대상 차종(N/A) | AA56: 비대상 차종(N/A)
B57: TC_CT_0016 | C57: Control | D57: Common | E57: 차량 제어 관련 UI | F57: 제어 연결 | G57: KR, EU | I57: 4 | K57: 1. EV5 앱모드 | L57: 1. Control 진입 2. 제어 진입 3. 모든 제어 버튼 누른 상태 0.5초 ~3초 유지 후 Touch up 4. 서버 통신 성공 시 제어 버튼 확인 | M57: 1. 블링킹 애니메이션 표출 | N57: =IF(COUNTIF(P57:W57,"F")>=1,"FAIL",(IF(COUNTIF(P57:W57,"P")>=1,"PASS",(IF(COUNTIF(P57:W57,"N/T")>=1,"N/T",(IF(COUNTIF(P57:W57,"N/A")>=1,"N/A","-"))))))) | O57: N/T | P57: N/T | T57: P | U57: =IF(COUNTIF(V57:W57,"F")>=1,"FAIL",(IF(COUNTIF(V57:W57,"P")>=1,"PASS",(IF(COUNTIF(V57:W57,"N/T")>=1,"N/T",(IF(COUNTIF(V57:W57,"N/A")>=1,"N/A","-"))))))) | V57: P | W57: P | X57: SPAQA-12888
B58: TC_CT_1829 | C58: Control | D58: Common | E58: 차량 제어 관련 UI | F58: 제어 연결 | G58: KR, EU | I58: 4 | K58: 1. EV4 앱모드 | L58: 1. Control 진입 2. 제어 진입 3. 모든 제어 버튼 누른 상태 0.5초 ~3초 유지 후 Touch up 4. 서버 통신 성공 시 제어 버튼 확인 | M58: 1. 블링킹 애니메이션 표출 | N58: =IF(COUNTIF(P58:W58,"F")>=1,"FAIL",(IF(COUNTIF(P58:W58,"P")>=1,"PASS",(IF(COUNTIF(P58:W58,"N/T")>=1,"N/T",(IF(COUNTIF(P58:W58,"N/A")>=1,"N/A","-"))))))) | O58: N/T | P58: N/T | T58: P | U58: =IF(COUNTIF(V58:W58,"F")>=1,"FAIL",(IF(COUNTIF(V58:W58,"P")>=1,"PASS",(IF(COUNTIF(V58:W58,"N/T")>=1,"N/T",(IF(COUNTIF(V58:W58,"N/A")>=1,"N/A","-"))))))) | V58: P | W58: P | Z58: K : EV4 차량 필요 | AA58: N/T : 차량/디바이스 필요(조건)
B59: TC_CT_1830 | C59: Control | D59: Common | E59: 차량 제어 관련 UI | F59: 제어 연결 | G59: KR, EU | I59: 4 | K59: 1. PHEV4 앱모드 | L59: 1. Control 진입 2. 제어 진입 3. 모든 제어 버튼 누른 상태 0.5초 ~3초 유지 후 Touch up 4. 서버 통신 성공 시 제어 버튼 확인 | M59: 1. 블링킹 애니메이션 표출 | N59: =IF(COUNTIF(P59:W59,"F")>=1,"FAIL",(IF(COUNTIF(P59:W59,"P")>=1,"PASS",(IF(COUNTIF(P59:W59,"N/T")>=1,"N/T",(IF(COUNTIF(P59:W59,"N/A")>=1,"N/A","-"))))))) | O59: N/T | P59: N/T | T59: P | U59: =IF(COUNTIF(V59:W59,"F")>=1,"FAIL",(IF(COUNTIF(V59:W59,"P")>=1,"PASS",(IF(COUNTIF(V59:W59,"N/T")>=1,"N/T",(IF(COUNTIF(V59:W59,"N/A")>=1,"N/A","-"))))))) | V59: N/A | W59: N/A | Z59: G : PHEV 비대상 차종(N/A) | AA59: 비대상 차종(N/A)
B60: TC_CT_0017 | C60: Control | D60: Common | E60: 차량 제어 관련 UI | F60: 제어 연결 | G60: KR, EU | I60: 4 | K60: 1. EV5 앱모드 | L60: 1. Control 진입 2. 제어 진입 3. 모든 제어 버튼 누른 상태 0.5초 ~3초 유지 후 Touch up 4. 서버 통신 성공 이후(블링킹 애니메이션 표출) 3초 내 제어 버튼 재선택 | M60: 1. 블링킹 애니메이션 시행되는 동안, 동일한 제어 버튼으로 제어 불가(=반응 없음) | N60: =IF(COUNTIF(P60:W60,"F")>=1,"FAIL",(IF(COUNTIF(P60:W60,"P")>=1,"PASS",(IF(COUNTIF(P60:W60,"N/T")>=1,"N/T",(IF(COUNTIF(P60:W60,"N/A")>=1,"N/A","-"))))))) | O60: N/T | P60: N/T | T60: P | U60: =IF(COUNTIF(V60:W60,"F")>=1,"FAIL",(IF(COUNTIF(V60:W60,"P")>=1,"PASS",(IF(COUNTIF(V60:W60,"N/T")>=1,"N/T",(IF(COUNTIF(V60:W60,"N/A")>=1,"N/A","-"))))))) | V60: P | W60: P | X60: SPAQA-21968 SPAQA-24552
B61: TC_CT_1831 | C61: Control | D61: Common | E61: 차량 제어 관련 UI | F61: 제어 연결 | G61: KR, EU | I61: 4 | K61: 1. EV4 앱모드 | L61: 1. Control 진입 2. 제어 진입 3. 모든 제어 버튼 누른 상태 0.5초 ~3초 유지 후 Touch up 4. 서버 통신 성공 이후(블링킹 애니메이션 표출) 3초 내 제어 버튼 재선택 | M61: 1. 블링킹 애니메이션 시행되는 동안, 동일한 제어 버튼으로 제어 불가(=반응 없음) | N61: =IF(COUNTIF(P61:W61,"F")>=1,"FAIL",(IF(COUNTIF(P61:W61,"P")>=1,"PASS",(IF(COUNTIF(P61:W61,"N/T")>=1,"N/T",(IF(COUNTIF(P61:W61,"N/A")>=1,"N/A","-"))))))) | O61: N/T | P61: N/T | T61: P | U61: =IF(COUNTIF(V61:W61,"F")>=1,"FAIL",(IF(COUNTIF(V61:W61,"P")>=1,"PASS",(IF(COUNTIF(V61:W61,"N/T")>=1,"N/T",(IF(COUNTIF(V61:W61,"N/A")>=1,"N/A","-"))))))) | V61: P | W61: P | Z61: K : EV4 차량 필요 | AA61: N/T : 차량/디바이스 필요(조건)
B62: TC_CT_1832 | C62: Control | D62: Common | E62: 차량 제어 관련 UI | F62: 제어 연결 | G62: KR, EU | I62: 4 | K62: 1. PHEV4 앱모드 | L62: 1. Control 진입 2. 제어 진입 3. 모든 제어 버튼 누른 상태 0.5초 ~3초 유지 후 Touch up 4. 서버 통신 성공 이후(블링킹 애니메이션 표출) 3초 내 제어 버튼 재선택 | M62: 1. 블링킹 애니메이션 시행되는 동안, 동일한 제어 버튼으로 제어 불가(=반응 없음) | N62: =IF(COUNTIF(P62:W62,"F")>=1,"FAIL",(IF(COUNTIF(P62:W62,"P")>=1,"PASS",(IF(COUNTIF(P62:W62,"N/T")>=1,"N/T",(IF(COUNTIF(P62:W62,"N/A")>=1,"N/A","-"))))))) | O62: N/T | P62: N/T | T62: P | U62: =IF(COUNTIF(V62:W62,"F")>=1,"FAIL",(IF(COUNTIF(V62:W62,"P")>=1,"PASS",(IF(COUNTIF(V62:W62,"N/T")>=1,"N/T",(IF(COUNTIF(V62:W62,"N/A")>=1,"N/A","-"))))))) | V62: N/A | W62: N/A | Z62: G : PHEV 비대상 차종(N/A) | AA62: 비대상 차종(N/A)
B63: TC_CT_0018 | C63: Control | D63: Common | E63: 차량 제어 관련 UI | F63: 제어 연결 | G63: KR, EU | I63: 4 | K63: 1. MQTT 지원 | L63: 1. Control 진입 2. 제어 진입 3. 모든 제어 버튼 누른 상태 3초 이상 유지 | M63: 1. 강제 제어 화면 표출 | N63: =IF(COUNTIF(P63:W63,"F")>=1,"FAIL",(IF(COUNTIF(P63:W63,"P")>=1,"PASS",(IF(COUNTIF(P63:W63,"N/T")>=1,"N/T",(IF(COUNTIF(P63:W63,"N/A")>=1,"N/A","-"))))))) | O63: N/T | P63: N/T | T63: P | U63: =IF(COUNTIF(V63:W63,"F")>=1,"FAIL",(IF(COUNTIF(V63:W63,"P")>=1,"PASS",(IF(COUNTIF(V63:W63,"N/T")>=1,"N/T",(IF(COUNTIF(V63:W63,"N/A")>=1,"N/A","-"))))))) | V63: P | W63: P
B64: TC_CT_1833 | C64: Control | D64: Common | E64: 차량 제어 관련 UI | F64: 제어 연결 | G64: KR, EU | I64: 4 | K64: 1. MQTT 이전 지원 | L64: 1. Control 진입 2. 제어 진입 3. 모든 제어 버튼 누른 상태 3초 이상 유지 | M64: 1. 강제 제어 화면 미 표출 | N64: =IF(COUNTIF(P64:W64,"F")>=1,"FAIL",(IF(COUNTIF(P64:W64,"P")>=1,"PASS",(IF(COUNTIF(P64:W64,"N/T")>=1,"N/T",(IF(COUNTIF(P64:W64,"N/A")>=1,"N/A","-"))))))) | O64: N/T | P64: N/T | T64: P | U64: =IF(COUNTIF(V64:W64,"F")>=1,"FAIL",(IF(COUNTIF(V64:W64,"P")>=1,"PASS",(IF(COUNTIF(V64:W64,"N/T")>=1,"N/T",(IF(COUNTIF(V64:W64,"N/A")>=1,"N/A","-"))))))) | V64: P | W64: P
B65: TC_CT_0019 | C65: Control | D65: Common | E65: 차량 제어 관련 UI | F65: 제어 연결 | G65: KR, EU | I65: 5 | J65: 1. 서버 통신 실패 or res 미응답 | L65: 1. Control 진입 2. 제어 진입 3. 모든의 제어 버튼 선택 4. Touch Up 0.5sec N | M65: 1. VSS를 통해 차량 상태 재확인 2. 마지막으로 가지고 있는 차량 상태 보여줌 | N65: =IF(COUNTIF(P65:W65,"F")>=1,"FAIL",(IF(COUNTIF(P65:W65,"P")>=1,"PASS",(IF(COUNTIF(P65:W65,"N/T")>=1,"N/T",(IF(COUNTIF(P65:W65,"N/A")>=1,"N/A","-"))))))) | O65: N/T | P65: N/T | T65: N/A | U65: =IF(COUNTIF(V65:W65,"F")>=1,"FAIL",(IF(COUNTIF(V65:W65,"P")>=1,"PASS",(IF(COUNTIF(V65:W65,"N/T")>=1,"N/T",(IF(COUNTIF(V65:W65,"N/A")>=1,"N/A","-"))))))) | V65: N/A | W65: N/A | Z65: 불필요 TC | AA65: 사양 아님(N/A) | AB65: 삭제
B66: TC_CT_0020 | C66: Control | D66: Common | E66: 차량 제어 관련 UI | F66: 제어 연결 | G66: KR, EU | I66: 4 | L66: 1. Control 진입 2. 제어 연결 상태 아이콘 확인 | M66: 1. Control 진입 시 제어 연결 상태의 아이콘 및 문구 제공 - iOS : 최초 1회만 표출 - Android : Control 진입 시 매번 표출 * MQTT 및 원격 불가능할 경우에는 미 제공 | N66: =IF(COUNTIF(P66:W66,"F")>=1,"FAIL",(IF(COUNTIF(P66:W66,"P")>=1,"PASS",(IF(COUNTIF(P66:W66,"N/T")>=1,"N/T",(IF(COUNTIF(P66:W66,"N/A")>=1,"N/A","-"))))))) | O66: N/T | P66: N/T | T66: P | U66: =IF(COUNTIF(V66:W66,"F")>=1,"FAIL",(IF(COUNTIF(V66:W66,"P")>=1,"PASS",(IF(COUNTIF(V66:W66,"N/T")>=1,"N/T",(IF(COUNTIF(V66:W66,"N/A")>=1,"N/A","-"))))))) | V66: P | W66: P
B67: TC_CT_0021 | C67: Control | D67: Common | E67: 차량 제어 관련 UI | F67: 제어 연결 | G67: KR, EU | I67: 4 | J67: 1. 폰-서버 연결된 상태 | L67: 1. Control 진입 2. 제어 연결 상태 아이콘 확인 | M67: 1. [연결됨] 아이콘 표출 | N67: =IF(COUNTIF(P67:W67,"F")>=1,"FAIL",(IF(COUNTIF(P67:W67,"P")>=1,"PASS",(IF(COUNTIF(P67:W67,"N/T")>=1,"N/T",(IF(COUNTIF(P67:W67,"N/A")>=1,"N/A","-"))))))) | O67: N/T | P67: N/T | T67: P | U67: =IF(COUNTIF(V67:W67,"F")>=1,"FAIL",(IF(COUNTIF(V67:W67,"P")>=1,"PASS",(IF(COUNTIF(V67:W67,"N/T")>=1,"N/T",(IF(COUNTIF(V67:W67,"N/A")>=1,"N/A","-"))))))) | V67: P | W67: P | X67: SPAQA-25480(TASK)
B68: TC_CT_0022 | C68: Control | D68: Common | E68: 차량 제어 관련 UI | F68: 제어 연결 | G68: KR, EU | I68: 4 | J68: 1. 폰-서버 연결된 상태 | L68: 1. Control 진입 2. 제어 연결 상태 아이콘 선택 | M68: 1. [연결됨] 문구 표출 2. 3초 후 문구 사라짐 | N68: =IF(COUNTIF(P68:W68,"F")>=1,"FAIL",(IF(COUNTIF(P68:W68,"P")>=1,"PASS",(IF(COUNTIF(P68:W68,"N/T")>=1,"N/T",(IF(COUNTIF(P68:W68,"N/A")>=1,"N/A","-"))))))) | O68: N/T | P68: N/T | T68: P | U68: =IF(COUNTIF(V68:W68,"F")>=1,"FAIL",(IF(COUNTIF(V68:W68,"P")>=1,"PASS",(IF(COUNTIF(V68:W68,"N/T")>=1,"N/T",(IF(COUNTIF(V68:W68,"N/A")>=1,"N/A","-"))))))) | V68: P | W68: P
B69: TC_CT_0023 | C69: Control | D69: Common | E69: 차량 제어 관련 UI | F69: 제어 연결 | G69: KR, EU | I69: 4 | J69: 1. 폰-서버 연결중 상태 | L69: 1. Control 진입 2. 제어 연결 상태 아이콘 확인 | M69: 1. [연결중] 아이콘 표출 | N69: =IF(COUNTIF(P69:W69,"F")>=1,"FAIL",(IF(COUNTIF(P69:W69,"P")>=1,"PASS",(IF(COUNTIF(P69:W69,"N/T")>=1,"N/T",(IF(COUNTIF(P69:W69,"N/A")>=1,"N/A","-"))))))) | O69: N/T | P69: N/T | T69: P | U69: =IF(COUNTIF(V69:W69,"F")>=1,"FAIL",(IF(COUNTIF(V69:W69,"P")>=1,"PASS",(IF(COUNTIF(V69:W69,"N/T")>=1,"N/T",(IF(COUNTIF(V69:W69,"N/A")>=1,"N/A","-"))))))) | V69: P | W69: P | Z69: 앱 종료 후 재시작 -> Control 탭 빠르게 진입시 확인 가능
B70: TC_CT_0024 | C70: Control | D70: Common | E70: 차량 제어 관련 UI | F70: 제어 연결 | G70: KR, EU | I70: 4 | J70: 1. 폰-서버 연결중 상태 | L70: 1. Control 진입 2. 제어 연결 상태 아이콘 선택 | M70: 1. [연결중] 문구 표출 2. 3초 후 문구 사라짐 | N70: =IF(COUNTIF(P70:W70,"F")>=1,"FAIL",(IF(COUNTIF(P70:W70,"P")>=1,"PASS",(IF(COUNTIF(P70:W70,"N/T")>=1,"N/T",(IF(COUNTIF(P70:W70,"N/A")>=1,"N/A","-"))))))) | O70: N/T | P70: N/T | T70: P | U70: =IF(COUNTIF(V70:W70,"F")>=1,"FAIL",(IF(COUNTIF(V70:W70,"P")>=1,"PASS",(IF(COUNTIF(V70:W70,"N/T")>=1,"N/T",(IF(COUNTIF(V70:W70,"N/A")>=1,"N/A","-"))))))) | V70: P | W70: P | X70: SPAQA-21139 | Z70: 앱 종료 후 재시작 -> Control 탭 빠르게 진입시 확인 가능
B71: TC_CT_1574 | C71: Control | D71: Common | E71: 차량 제어 관련 UI | F71: 제어 연결 | G71: KR, EU | I71: 5 | J71: 1. 폰-서버 미연결 상태 | L71: 1. Control 진입 2. 제어 연결 상태 아이콘 확인 | M71: 1. [미연결] 아이콘 표출 | N71: =IF(COUNTIF(P71:W71,"F")>=1,"FAIL",(IF(COUNTIF(P71:W71,"P")>=1,"PASS",(IF(COUNTIF(P71:W71,"N/T")>=1,"N/T",(IF(COUNTIF(P71:W71,"N/A")>=1,"N/A","-"))))))) | O71: N/T | P71: N/T | T71: P | U71: =IF(COUNTIF(V71:W71,"F")>=1,"FAIL",(IF(COUNTIF(V71:W71,"P")>=1,"PASS",(IF(COUNTIF(V71:W71,"N/T")>=1,"N/T",(IF(COUNTIF(V71:W71,"N/A")>=1,"N/A","-"))))))) | V71: P | W71: P | Z71: 단말 비행기모드 ON or 네트워크 OFF 후 확인
B72: TC_CT_0025 | C72: Control | D72: Common | E72: 차량 제어 관련 UI | F72: 제어 연결 | G72: KR, EU | I72: 5 | J72: 1. 폰-서버 미연결 상태 | L72: 1. Control 진입 2. 제어 연결 상태 아이콘 선택 | M72: 1. 별도 문구 표출 없음 | N72: =IF(COUNTIF(P72:W72,"F")>=1,"FAIL",(IF(COUNTIF(P72:W72,"P")>=1,"PASS",(IF(COUNTIF(P72:W72,"N/T")>=1,"N/T",(IF(COUNTIF(P72:W72,"N/A")>=1,"N/A","-"))))))) | O72: N/T | P72: N/T | T72: P | U72: =IF(COUNTIF(V72:W72,"F")>=1,"FAIL",(IF(COUNTIF(V72:W72,"P")>=1,"PASS",(IF(COUNTIF(V72:W72,"N/T")>=1,"N/T",(IF(COUNTIF(V72:W72,"N/A")>=1,"N/A","-"))))))) | V72: P | W72: P | Z72: 단말 비행기모드 ON or 네트워크 OFF 후 확인
B73: TC_CT_0026 | C73: Control | D73: Common | E73: 차량 제어 관련 UI | F73: 제어 연결 | G73: KR, EU | I73: 4 | L73: 1. Control 진입 2. 배터리 영역 아이콘 확인 | M73: 1. 0%~100%를 기준으로 선형적으로 표현 | N73: =IF(COUNTIF(P73:W73,"F")>=1,"FAIL",(IF(COUNTIF(P73:W73,"P")>=1,"PASS",(IF(COUNTIF(P73:W73,"N/T")>=1,"N/T",(IF(COUNTIF(P73:W73,"N/A")>=1,"N/A","-"))))))) | O73: N/T | P73: N/T | T73: P | U73: =IF(COUNTIF(V73:W73,"F")>=1,"FAIL",(IF(COUNTIF(V73:W73,"P")>=1,"PASS",(IF(COUNTIF(V73:W73,"N/T")>=1,"N/T",(IF(COUNTIF(V73:W73,"N/A")>=1,"N/A","-"))))))) | V73: P | W73: P | X73: SPAQA-18780
B74: TC_CT_0027 | C74: Control | D74: Common | E74: 차량 제어 관련 UI | F74: 제어 연결 | G74: KR, EU | I74: 4 | L74: 1. Control 진입 2. 배터리 영역 확인 | M74: 1. 아이콘 + N% (0 ~ 100%) | N74: =IF(COUNTIF(P74:W74,"F")>=1,"FAIL",(IF(COUNTIF(P74:W74,"P")>=1,"PASS",(IF(COUNTIF(P74:W74,"N/T")>=1,"N/T",(IF(COUNTIF(P74:W74,"N/A")>=1,"N/A","-"))))))) | O74: N/T | P74: N/T | T74: P | U74: =IF(COUNTIF(V74:W74,"F")>=1,"FAIL",(IF(COUNTIF(V74:W74,"P")>=1,"PASS",(IF(COUNTIF(V74:W74,"N/T")>=1,"N/T",(IF(COUNTIF(V74:W74,"N/A")>=1,"N/A","-"))))))) | V74: P | W74: P | X74: SPAQA-13650
B75: TC_CT_0028 | C75: Control | D75: Common | E75: 차량 제어 관련 UI | F75: 제어 연결 | G75: KR, EU | I75: 5 | J75: 1. 차량에서 배터리량 정보를 불러오지 못한 상태 | L75: 1. Control 진입 2. 배터리 영역 확인 | M75: 1. --% 표출 | N75: =IF(COUNTIF(P75:W75,"F")>=1,"FAIL",(IF(COUNTIF(P75:W75,"P")>=1,"PASS",(IF(COUNTIF(P75:W75,"N/T")>=1,"N/T",(IF(COUNTIF(P75:W75,"N/A")>=1,"N/A","-"))))))) | O75: N/T | P75: N/T | T75: P | U75: =IF(COUNTIF(V75:W75,"F")>=1,"FAIL",(IF(COUNTIF(V75:W75,"P")>=1,"PASS",(IF(COUNTIF(V75:W75,"N/T")>=1,"N/T",(IF(COUNTIF(V75:W75,"N/A")>=1,"N/A","-"))))))) | V75: P | W75: P | X75: SPAQA-15203 SPAQA-16403 | Z75: 충전 중 상태 > 일시적으로 미표출 시 확인 | AB75: 실차, Proxy
B76: TC_CT_0029 | C76: Control | D76: Common | E76: 차량 제어 관련 UI | F76: 제어 연결 | G76: KR, EU | I76: 3 | K76: 1. 충전 중 | L76: 1. Control 진입 2. 배터리 영역 확인 | M76: 1. 아이콘 + n% + NkW 표출 * 충전 전류(kW)는 값 받았을 시에만 표출 | N76: =IF(COUNTIF(P76:W76,"F")>=1,"FAIL",(IF(COUNTIF(P76:W76,"P")>=1,"PASS",(IF(COUNTIF(P76:W76,"N/T")>=1,"N/T",(IF(COUNTIF(P76:W76,"N/A")>=1,"N/A","-"))))))) | O76: N/T | P76: N/T | T76: P | U76: =IF(COUNTIF(V76:W76,"F")>=1,"FAIL",(IF(COUNTIF(V76:W76,"P")>=1,"PASS",(IF(COUNTIF(V76:W76,"N/T")>=1,"N/T",(IF(COUNTIF(V76:W76,"N/A")>=1,"N/A","-"))))))) | V76: P | W76: P | X76: SPAQA-14064 SPAQA-14506 | AB76: 실차, Proxy
B77: TC_CT_0030 | C77: Control | D77: Common | E77: 차량 제어 관련 UI | F77: 제어 연결 | G77: KR, EU | I77: 3 | K77: 1. 충전 중 | L77: 1. Control 진입 2. 배터리 영역 아이콘 확인 | M77: 1. [충전 중] GUI 사양에 맞는 아이콘 표출 | N77: =IF(COUNTIF(P77:W77,"F")>=1,"FAIL",(IF(COUNTIF(P77:W77,"P")>=1,"PASS",(IF(COUNTIF(P77:W77,"N/T")>=1,"N/T",(IF(COUNTIF(P77:W77,"N/A")>=1,"N/A","-"))))))) | O77: N/T | P77: N/T | T77: P | U77: =IF(COUNTIF(V77:W77,"F")>=1,"FAIL",(IF(COUNTIF(V77:W77,"P")>=1,"PASS",(IF(COUNTIF(V77:W77,"N/T")>=1,"N/T",(IF(COUNTIF(V77:W77,"N/A")>=1,"N/A","-"))))))) | V77: P | W77: P | X77: SPAQA-18919 | AB77: 실차, Proxy
B78: TC_CT_0031 | C78: Control | D78: Common | E78: 차량 제어 관련 UI | F78: 제어 연결 | G78: KR, EU | I78: 3 | K78: 1. V2L 실행 중 | L78: 1. Control 진입 2. 배터리 영역 아이콘 확인 | M78: 1. [V2L 실행 중] GUI 사양에 맞는 아이콘 표출 | N78: =IF(COUNTIF(P78:W78,"F")>=1,"FAIL",(IF(COUNTIF(P78:W78,"P")>=1,"PASS",(IF(COUNTIF(P78:W78,"N/T")>=1,"N/T",(IF(COUNTIF(P78:W78,"N/A")>=1,"N/A","-"))))))) | O78: N/T | P78: N/T | T78: P | U78: =IF(COUNTIF(V78:W78,"F")>=1,"FAIL",(IF(COUNTIF(V78:W78,"P")>=1,"PASS",(IF(COUNTIF(V78:W78,"N/T")>=1,"N/T",(IF(COUNTIF(V78:W78,"N/A")>=1,"N/A","-"))))))) | V78: P | W78: P | X78: SPAQA-13196 SPAQA-13442 SPAQA-13488 SPAQA-13512 SPAQA-24544 | Z78: K : MV원격사용불가(방전) (N/T) | AB78: 실차
B79: TC_CT_0032 | C79: Control | D79: Common | E79: 차량 제어 관련 UI | F79: 제어 연결 | G79: KR, EU | I79: 5 | K79: 1. 배터리 컨디셔닝 중 | L79: 1. Control 진입 2. 배터리 영역 아이콘 확인 | M79: 1. [배터리 컨디셔닝 중] GUI 사양에 맞는 아이콘 표출 | N79: =IF(COUNTIF(P79:W79,"F")>=1,"FAIL",(IF(COUNTIF(P79:W79,"P")>=1,"PASS",(IF(COUNTIF(P79:W79,"N/T")>=1,"N/T",(IF(COUNTIF(P79:W79,"N/A")>=1,"N/A","-"))))))) | O79: N/T | P79: N/T | T79: P | U79: =IF(COUNTIF(V79:W79,"F")>=1,"FAIL",(IF(COUNTIF(V79:W79,"P")>=1,"PASS",(IF(COUNTIF(V79:W79,"N/T")>=1,"N/T",(IF(COUNTIF(V79:W79,"N/A")>=1,"N/A","-"))))))) | V79: P | W79: P | X79: SPAQA-14461 SPAQA-18780 SPAQA-25461 | Z79: K : MV원격사용불가(방전) (N/T) | AB79: 실차, Proxy
B80: TC_CT_0033 | C80: Control | D80: Common | E80: 차량 제어 관련 UI | F80: 제어 연결 | G80: KR, EU | I80: 4 | J80: 1. 차량에서 주행 가능 거리 불러온 상태 | L80: 1. Control 진입 2. 배터리 영역 아이콘 확인 | M80: 1. 주행 가능 거리 있을때 아래와 같이 표출 - 999km 이하 : 아이콘 + Nkm - 1,000km 이상 : 999+km - 1,000mile 이상 : 999+mile | N80: =IF(COUNTIF(P80:W80,"F")>=1,"FAIL",(IF(COUNTIF(P80:W80,"P")>=1,"PASS",(IF(COUNTIF(P80:W80,"N/T")>=1,"N/T",(IF(COUNTIF(P80:W80,"N/A")>=1,"N/A","-"))))))) | O80: N/T | P80: N/T | T80: P | U80: =IF(COUNTIF(V80:W80,"F")>=1,"FAIL",(IF(COUNTIF(V80:W80,"P")>=1,"PASS",(IF(COUNTIF(V80:W80,"N/T")>=1,"N/T",(IF(COUNTIF(V80:W80,"N/A")>=1,"N/A","-"))))))) | V80: P | W80: P | X80: SPAQA-14380 SPAQA-23919 SPAQA-26292 | AB80: Proxy
B81: TC_CT_0034 | C81: Control | D81: Common | E81: 차량 제어 관련 UI | F81: 제어 연결 | G81: KR, EU | I81: 4 | J81: 1. 유효하지 않은 값 수신(0 포함) | L81: 1. Control 진입 2. 주행 가능 거리 영역 확인 | M81: 1. 단위에 따라 아래와 같이 표출 - km 단위일 경우 : --km - mile 단위일 경우 : --mile | N81: =IF(COUNTIF(P81:W81,"F")>=1,"FAIL",(IF(COUNTIF(P81:W81,"P")>=1,"PASS",(IF(COUNTIF(P81:W81,"N/T")>=1,"N/T",(IF(COUNTIF(P81:W81,"N/A")>=1,"N/A","-"))))))) | O81: N/T | P81: N/T | T81: P | U81: =IF(COUNTIF(V81:W81,"F")>=1,"FAIL",(IF(COUNTIF(V81:W81,"P")>=1,"PASS",(IF(COUNTIF(V81:W81,"N/T")>=1,"N/T",(IF(COUNTIF(V81:W81,"N/A")>=1,"N/A","-"))))))) | V81: P | W81: P | X81: SPAQA-16517 SPAQA-20199 | AB81: Proxy
B82: TC_CT_0035 | C82: Control | D82: Common | E82: 차량 제어 관련 UI | F82: 제어 연결 | G82: KR, EU | I82: 5 | K82: 1. 주행 가능 거리 미지원 차량 | L82: 1. Control 진입 2. 주행 가능 거리 영역 확인 | M82: 1. 주행 가능 거리 영역 미표출 | N82: =IF(COUNTIF(P82:W82,"F")>=1,"FAIL",(IF(COUNTIF(P82:W82,"P")>=1,"PASS",(IF(COUNTIF(P82:W82,"N/T")>=1,"N/T",(IF(COUNTIF(P82:W82,"N/A")>=1,"N/A","-"))))))) | O82: N/T | P82: N/T | T82: N/T | U82: =IF(COUNTIF(V82:W82,"F")>=1,"FAIL",(IF(COUNTIF(V82:W82,"P")>=1,"PASS",(IF(COUNTIF(V82:W82,"N/T")>=1,"N/T",(IF(COUNTIF(V82:W82,"N/A")>=1,"N/A","-"))))))) | V82: N/T | W82: N/T | Z82: (공통) 주행 가능 거리 미지원 차량 필요 (N/T) | AA82: N/T : 차량/디바이스 필요(조건)
B83: TC_CT_0036 | C83: Control | D83: Common | E83: 차량 제어 관련 UI | F83: 제어 연결 | G83: KR, EU | I83: 3 | K83: 1. CCS 가입 차량 | L83: 1. Control 진입 2. 제어 진입 | M83: 1. 단위 확인 2. 앱에서 설정된 단위를 따름 (km / mile) * 샘플앱의 경우 Default 단위(km) 사용 | N83: =IF(COUNTIF(P83:W83,"F")>=1,"FAIL",(IF(COUNTIF(P83:W83,"P")>=1,"PASS",(IF(COUNTIF(P83:W83,"N/T")>=1,"N/T",(IF(COUNTIF(P83:W83,"N/A")>=1,"N/A","-"))))))) | O83: N/T | P83: N/T | T83: P | U83: =IF(COUNTIF(V83:W83,"F")>=1,"FAIL",(IF(COUNTIF(V83:W83,"P")>=1,"PASS",(IF(COUNTIF(V83:W83,"N/T")>=1,"N/T",(IF(COUNTIF(V83:W83,"N/A")>=1,"N/A","-"))))))) | V83: P | W83: P | X83: SPAQA-13204 SPAQA-17360 SPAQA-21829
B84: TC_CT_0037 | C84: Control | D84: Common | E84: 차량 제어 관련 UI | F84: 제어 연결 | G84: KR, EU | I84: 5 | J84: 1. MQTT 통신 끊겨진 상태 | K84: 1 MQTT 2. EV | L84: 1. Control 진입 2. 제어 진입 3. 원격 제어 시도 | M84: 1. 서버 통신 오류 팝업 표출 "서버와의 통신이 원활하지 않습니다. 다시 시도해 주시기 바랍니다." 닫기 * 닫기: 팝업 소거 , 현재 화면 유지 | N84: =IF(COUNTIF(P84:W84,"F")>=1,"FAIL",(IF(COUNTIF(P84:W84,"P")>=1,"PASS",(IF(COUNTIF(P84:W84,"N/T")>=1,"N/T",(IF(COUNTIF(P84:W84,"N/A")>=1,"N/A","-"))))))) | O84: N/T | P84: N/T | T84: N/T | U84: =IF(COUNTIF(V84:W84,"F")>=1,"FAIL",(IF(COUNTIF(V84:W84,"P")>=1,"PASS",(IF(COUNTIF(V84:W84,"N/T")>=1,"N/T",(IF(COUNTIF(V84:W84,"N/A")>=1,"N/A","-"))))))) | V84: N/T | W84: N/T | Z84: (공통) MQTT 통신 끊긴 상태 필요 | AA84: N/T : 특수상황/실패 조건 필요(조건)
B85: TC_CT_0038 | C85: Control | D85: Common | E85: 차량 제어 관련 UI | F85: 제어 연결 | G85: KR, EU | I85: 5 | J85: 1. MQTT 통신 끊겨진 상태 | K85: 1 MQTT 2. EV | L85: 1. Control 진입 2. 제어 진입 3. 차량 점검 선택 | M85: 1. 페이지 이동 [<] Title "데이터가 수신되지 않았습니다." [다시 시도] * 다시 시도 : 차량 진단 데이터 재수신하며 버튼 내 로딩 애니메이션 제공 | N85: =IF(COUNTIF(P85:W85,"F")>=1,"FAIL",(IF(COUNTIF(P85:W85,"P")>=1,"PASS",(IF(COUNTIF(P85:W85,"N/T")>=1,"N/T",(IF(COUNTIF(P85:W85,"N/A")>=1,"N/A","-"))))))) | O85: N/T | P85: N/T | T85: N/T | U85: =IF(COUNTIF(V85:W85,"F")>=1,"FAIL",(IF(COUNTIF(V85:W85,"P")>=1,"PASS",(IF(COUNTIF(V85:W85,"N/T")>=1,"N/T",(IF(COUNTIF(V85:W85,"N/A")>=1,"N/A","-"))))))) | V85: N/T | W85: N/T | Z85: (공통) MQTT 통신 끊긴 상태 필요 (N/T) | AA85: N/T : 특수상황/실패 조건 필요(조건)
B86: TC_CT_0039 | C86: Control | D86: Common | E86: 차량 제어 관련 UI | F86: 컨트롤 title | G86: KR, EU | I86: 4 | L86: 1. Control 진입 2. Title 확인 | M86: 1. Control 타이틀 표출 | N86: =IF(COUNTIF(P86:W86,"F")>=1,"FAIL",(IF(COUNTIF(P86:W86,"P")>=1,"PASS",(IF(COUNTIF(P86:W86,"N/T")>=1,"N/T",(IF(COUNTIF(P86:W86,"N/A")>=1,"N/A","-"))))))) | O86: N/T | P86: N/T | T86: P | U86: =IF(COUNTIF(V86:W86,"F")>=1,"FAIL",(IF(COUNTIF(V86:W86,"P")>=1,"PASS",(IF(COUNTIF(V86:W86,"N/T")>=1,"N/T",(IF(COUNTIF(V86:W86,"N/A")>=1,"N/A","-"))))))) | V86: P | W86: P | X86: SPAQA-17334 SPAQA-20393
B87: TC_CT_0040 | C87: Control | D87: Common | E87: 차량 제어 관련 UI | F87: 컨트롤 title | G87: KR, EU | I87: 4 | L87: 1. Control 진입 2. 스크롤 후 탭 이동 | M87: 1. 스크롤은 상단에 고정되어 있으나, inline 형태는 유지 * 모든 탭 동일 | N87: =IF(COUNTIF(P87:W87,"F")>=1,"FAIL",(IF(COUNTIF(P87:W87,"P")>=1,"PASS",(IF(COUNTIF(P87:W87,"N/T")>=1,"N/T",(IF(COUNTIF(P87:W87,"N/A")>=1,"N/A","-"))))))) | O87: N/T | P87: N/T | T87: P | U87: =IF(COUNTIF(V87:W87,"F")>=1,"FAIL",(IF(COUNTIF(V87:W87,"P")>=1,"PASS",(IF(COUNTIF(V87:W87,"N/T")>=1,"N/T",(IF(COUNTIF(V87:W87,"N/A")>=1,"N/A","-"))))))) | V87: P | W87: P
B88: TC_CT_0042 | C88: Control | D88: Common | E88: 차량 제어 관련 UI | F88: 제어 연결 | G88: KR, EU | I88: 5 | J88: 1. 안전 모드 2. CCS SDK 자체 발생 | L88: 1. Control 진입 | M88: 1. 안전 모드 문구 Case1 "일시적으로 차량 연결이 불안정해 서비스 이용이 제한 됩니다. 잠시 후 앱을 다시 실행 해주세요. 현재 상태에서는 푸시 알림이 오지 않을 수 있습니다." | N88: =IF(COUNTIF(P88:W88,"F")>=1,"FAIL",(IF(COUNTIF(P88:W88,"P")>=1,"PASS",(IF(COUNTIF(P88:W88,"N/T")>=1,"N/T",(IF(COUNTIF(P88:W88,"N/A")>=1,"N/A","-"))))))) | O88: N/T | P88: N/T | T88: N/T | U88: =IF(COUNTIF(V88:W88,"F")>=1,"FAIL",(IF(COUNTIF(V88:W88,"P")>=1,"PASS",(IF(COUNTIF(V88:W88,"N/T")>=1,"N/T",(IF(COUNTIF(V88:W88,"N/A")>=1,"N/A","-"))))))) | V88: N/T | W88: N/T | X88: SPAQA-23460(TASK) | Z88: (공통) 안전모드 환경 필요 (N/T) | AA88: N/T : 특수상황/실패 조건 필요(조건) | AB88: TASK
B89: TC_CT_0043 | C89: Control | D89: Common | E89: 차량 제어 관련 UI | F89: 제어 연결 | G89: KR, EU | I89: 5 | J89: 1. 안전 모드 2. 외부 요청 | L89: 1. Control 진입 | M89: 1. 안전 모드 문구 Case2 "시스템 오류로 서비스 이용이 제한됩니다. 빠르게 복구 중이며, 잠시 후 앱을 다시 실행 해주세요. ※현재 상태에서는 푸시 알림이 오지 않을 수 있습니다." | N89: =IF(COUNTIF(P89:W89,"F")>=1,"FAIL",(IF(COUNTIF(P89:W89,"P")>=1,"PASS",(IF(COUNTIF(P89:W89,"N/T")>=1,"N/T",(IF(COUNTIF(P89:W89,"N/A")>=1,"N/A","-"))))))) | O89: N/T | P89: N/T | T89: P | U89: =IF(COUNTIF(V89:W89,"F")>=1,"FAIL",(IF(COUNTIF(V89:W89,"P")>=1,"PASS",(IF(COUNTIF(V89:W89,"N/T")>=1,"N/T",(IF(COUNTIF(V89:W89,"N/A")>=1,"N/A","-"))))))) | V89: P | W89: P | X89: SPAQA-23460(TASK) SPAQA-25416 | Z89: (공통) : 개발자 모드(강제 안전모드)로 확인 | AB89: TASK, Proxy
B90: TC_CT_0044 | C90: Control | D90: Common | E90: 차량 제어 관련 UI | F90: 제어 연결 | G90: KR, EU | I90: 4 | J90: 1. Service List OFF 상태 | K90: 1. ePrivacy 미지원 차량 | L90: 1. Control 진입 2. 배너 선택 | M90: 1. Service List 로 이동 - 누른 시점에 Service List OFF 항목 있을경우 | N90: =IF(COUNTIF(P90:W90,"F")>=1,"FAIL",(IF(COUNTIF(P90:W90,"P")>=1,"PASS",(IF(COUNTIF(P90:W90,"N/T")>=1,"N/T",(IF(COUNTIF(P90:W90,"N/A")>=1,"N/A","-"))))))) | O90: N/T | P90: N/T | T90: P | U90: =IF(COUNTIF(V90:W90,"F")>=1,"FAIL",(IF(COUNTIF(V90:W90,"P")>=1,"PASS",(IF(COUNTIF(V90:W90,"N/T")>=1,"N/T",(IF(COUNTIF(V90:W90,"N/A")>=1,"N/A","-"))))))) | V90: P | W90: P | X90: SPAQA-17217(TASK) SPAQA-19947 SPAQA-25353 | AB90: TASK
B91: TC_CT_0045 | C91: Control | D91: Common | E91: 차량 제어 관련 UI | F91: 제어 연결 | G91: KR, EU | I91: 4 | J91: 1. Service List ON 상태 | K91: 1. ePrivacy 미지원 차량 | L91: 1. Control 진입 2. 배너 선택 | M91: 1. 배너 소거 - 누른 시점에 Service List OFF 항목 없을경우 | N91: =IF(COUNTIF(P91:W91,"F")>=1,"FAIL",(IF(COUNTIF(P91:W91,"P")>=1,"PASS",(IF(COUNTIF(P91:W91,"N/T")>=1,"N/T",(IF(COUNTIF(P91:W91,"N/A")>=1,"N/A","-"))))))) | O91: N/T | P91: N/T | T91: P | U91: =IF(COUNTIF(V91:W91,"F")>=1,"FAIL",(IF(COUNTIF(V91:W91,"P")>=1,"PASS",(IF(COUNTIF(V91:W91,"N/T")>=1,"N/T",(IF(COUNTIF(V91:W91,"N/A")>=1,"N/A","-"))))))) | V91: P | W91: P | X91: SPAQA-17217(TASK) | AB91: TASK
B92: TC_CT_0046 | C92: Control | D92: Common | E92: 차량 제어 관련 UI | F92: 제어 연결 | G92: KR, EU | I92: 3 | J92: 1. Service List OFF 상태 | K92: 1. ePrivacy 지원 차량 | L92: 1. Control 진입 2. 배너의 새로고침 버튼 선택 | M92: 1. 새로고침 동작 | N92: =IF(COUNTIF(P92:W92,"F")>=1,"FAIL",(IF(COUNTIF(P92:W92,"P")>=1,"PASS",(IF(COUNTIF(P92:W92,"N/T")>=1,"N/T",(IF(COUNTIF(P92:W92,"N/A")>=1,"N/A","-"))))))) | O92: N/T | P92: N/T | T92: P | U92: =IF(COUNTIF(V92:W92,"F")>=1,"FAIL",(IF(COUNTIF(V92:W92,"P")>=1,"PASS",(IF(COUNTIF(V92:W92,"N/T")>=1,"N/T",(IF(COUNTIF(V92:W92,"N/A")>=1,"N/A","-"))))))) | V92: P | W92: P | X92: SPAQA-17217(TASK) SPAQA-19947 | Z92: K : MV원격사용불가(방전) (N/T) | AB92: TASK, 실차
B93: TC_CT_0047 | C93: Control | D93: Common | E93: 차량 제어 관련 UI | F93: 제어 연결 | G93: KR, EU | I93: 3 | J93: 1. Service List OFF 상태 | K93: 1. ePrivacy 지원 차량 | L93: 1. Control 진입 2. 배너 표출 확인 3. P2R 동작 진행 4. 상단 배너 확인 | M93: 1. 상단 배너 표출 유지된다. | N93: =IF(COUNTIF(P93:W93,"F")>=1,"FAIL",(IF(COUNTIF(P93:W93,"P")>=1,"PASS",(IF(COUNTIF(P93:W93,"N/T")>=1,"N/T",(IF(COUNTIF(P93:W93,"N/A")>=1,"N/A","-"))))))) | O93: N/T | P93: N/T | T93: P | U93: =IF(COUNTIF(V93:W93,"F")>=1,"FAIL",(IF(COUNTIF(V93:W93,"P")>=1,"PASS",(IF(COUNTIF(V93:W93,"N/T")>=1,"N/T",(IF(COUNTIF(V93:W93,"N/A")>=1,"N/A","-"))))))) | V93: P | W93: P | X93: SPAQA-17217(TASK) | Z93: K : MV원격사용불가(방전) (N/T) | AB93: 실차
B94: TC_CT_0048 | C94: Control | D94: Common | E94: 차량 제어 관련 UI | F94: 제어 연결 | G94: KR, EU | I94: 3 | J94: 1. Service List OFF 상태 | K94: 1. ePrivacy 지원 차량 | L94: 1. Control 진입 2. 배너 확인 3. 차량 단말에서 Service list On으로 변경 4. App에서 배너 내 새로고침 버튼 선택 | M94: 1. 새로고침 동작 - 누른 시점에 Service List Off 항목 없을 시, 배너 소거 | N94: =IF(COUNTIF(P94:W94,"F")>=1,"FAIL",(IF(COUNTIF(P94:W94,"P")>=1,"PASS",(IF(COUNTIF(P94:W94,"N/T")>=1,"N/T",(IF(COUNTIF(P94:W94,"N/A")>=1,"N/A","-"))))))) | O94: N/T | P94: N/T | T94: P | U94: =IF(COUNTIF(V94:W94,"F")>=1,"FAIL",(IF(COUNTIF(V94:W94,"P")>=1,"PASS",(IF(COUNTIF(V94:W94,"N/T")>=1,"N/T",(IF(COUNTIF(V94:W94,"N/A")>=1,"N/A","-"))))))) | V94: P | W94: P | X94: SPAQA-17217(TASK) | Z94: K : MV원격사용불가(방전) (N/T) | AB94: TASK, 실차
B95: TC_CT_0049 | C95: Control | D95: Common | E95: 차량 제어 관련 UI | F95: 제어 연결 | G95: KR, EU | I95: 4 | J95: 1. PIN 적용 | K95: 1. EV | L95: 1. Control > 제어 탭 진입 2. 제어 시도 | M95: 1. Pin 입력 표출 | N95: =IF(COUNTIF(P95:W95,"F")>=1,"FAIL",(IF(COUNTIF(P95:W95,"P")>=1,"PASS",(IF(COUNTIF(P95:W95,"N/T")>=1,"N/T",(IF(COUNTIF(P95:W95,"N/A")>=1,"N/A","-"))))))) | O95: N/T | P95: N/T | T95: P | U95: =IF(COUNTIF(V95:W95,"F")>=1,"FAIL",(IF(COUNTIF(V95:W95,"P")>=1,"PASS",(IF(COUNTIF(V95:W95,"N/T")>=1,"N/T",(IF(COUNTIF(V95:W95,"N/A")>=1,"N/A","-"))))))) | V95: P | W95: P | X95: SPAQA-18370(TASK) SPAQA-25738 | AA95: N/T : Blocked(조건) | AB95: TASK
B96: TC_CT_0050 | C96: Control | D96: Common | E96: 차량 제어 관련 UI | F96: 제어 연결 | G96: KR, EU | I96: 4 | J96: 1. PIN 적용 | K96: 1. EV | L96: 1. Control > 제어 탭 진입 2. 제어 시도 | M96: 1. Pin 입력 후 제어 성공 | N96: =IF(COUNTIF(P96:W96,"F")>=1,"FAIL",(IF(COUNTIF(P96:W96,"P")>=1,"PASS",(IF(COUNTIF(P96:W96,"N/T")>=1,"N/T",(IF(COUNTIF(P96:W96,"N/A")>=1,"N/A","-"))))))) | O96: N/T | P96: N/T | T96: P | U96: =IF(COUNTIF(V96:W96,"F")>=1,"FAIL",(IF(COUNTIF(V96:W96,"P")>=1,"PASS",(IF(COUNTIF(V96:W96,"N/T")>=1,"N/T",(IF(COUNTIF(V96:W96,"N/A")>=1,"N/A","-"))))))) | V96: P | W96: P | X96: SPAQA-18370(TASK) SPAQA-18513 SPAQA-25738 | AA96: N/T : Blocked(조건) | AB96: TASK
B97: TC_CT_0051 | C97: Control | D97: Common | E97: 차량 제어 관련 UI | F97: 제어 연결 | G97: KR, EU | I97: 1 | J97: 1. PIN 적용 | K97: 1. PHEV, GEN2 | L97: 1. Control > 제어 탭 진입 2. 시동 켜기/끄기 3. 제어 시도 | M97: 1. Pin 입력 표출 | N97: =IF(COUNTIF(P97:W97,"F")>=1,"FAIL",(IF(COUNTIF(P97:W97,"P")>=1,"PASS",(IF(COUNTIF(P97:W97,"N/T")>=1,"N/T",(IF(COUNTIF(P97:W97,"N/A")>=1,"N/A","-"))))))) | O97: N/T | P97: N/T | T97: P | U97: =IF(COUNTIF(V97:W97,"F")>=1,"FAIL",(IF(COUNTIF(V97:W97,"P")>=1,"PASS",(IF(COUNTIF(V97:W97,"N/T")>=1,"N/T",(IF(COUNTIF(V97:W97,"N/A")>=1,"N/A","-"))))))) | V97: N/T | W97: N/T | X97: SPAQA-18370(TASK) SPAQA-25738 | Z97: K/H : 차량 시동 제어 지원 차량 필요 (N/T) G : 내연 차량 필요 (N/T) | AA97: N/T : 차량/디바이스 필요(조건) | AB97: CheckList, TASK
B98: TC_CT_0052 | C98: Control | D98: Common | E98: 차량 제어 관련 UI | F98: 제어 연결 | G98: KR, EU | I98: 1 | J98: 1. PIN 적용 | K98: 1. PHEV, GEN2 | L98: 1. Control > 제어 탭 진입 2. 시동 켜기/끄기 3. 제어 시도 | M98: 1. Pin 입력 후 제어 성공 | N98: =IF(COUNTIF(P98:W98,"F")>=1,"FAIL",(IF(COUNTIF(P98:W98,"P")>=1,"PASS",(IF(COUNTIF(P98:W98,"N/T")>=1,"N/T",(IF(COUNTIF(P98:W98,"N/A")>=1,"N/A","-"))))))) | O98: N/T | P98: N/T | T98: P | U98: =IF(COUNTIF(V98:W98,"F")>=1,"FAIL",(IF(COUNTIF(V98:W98,"P")>=1,"PASS",(IF(COUNTIF(V98:W98,"N/T")>=1,"N/T",(IF(COUNTIF(V98:W98,"N/A")>=1,"N/A","-"))))))) | V98: N/T | W98: N/T | X98: SPAQA-18370(TASK) SPAQA-25738 | Z98: K/H : 차량 시동 제어 지원 차량 필요 (N/T) G : 내연 차량 필요 (N/T) | AA98: N/T : 차량/디바이스 필요(조건) | AB98: CheckList, TASK
B99: TC_CT_0053 | C99: Control | D99: 제어 | E99: 차량 제어 | F99: 제어 실행 | G99: KR, EU | K99: 1. 차량 12V 배터리 부족한 상태 | L99: 1. Control 진입 2. 모든의 원격제어 시도 * 내연 : 원격 시동 제외한 모든 원격제어 * EV : 즉시 공조, 즉시 충전을 제외한 모든 원격제어 | M99: 1. 팝업 표출 "The vehicle's 12V battery charge is low." "Using remote control may cause problems for the next the engine start. Do you want to start remote control?" [Cancel] [Activate] * 취소 : 닫힘, 현재 화면 유지 * 실행 : 원격제어 실행 | N99: =IF(COUNTIF(P99:W99,"F")>=1,"FAIL",(IF(COUNTIF(P99:W99,"P")>=1,"PASS",(IF(COUNTIF(P99:W99,"N/T")>=1,"N/T",(IF(COUNTIF(P99:W99,"N/A")>=1,"N/A","-"))))))) | O99: N/T | P99: N/T | T99: N/A | U99: =IF(COUNTIF(V99:W99,"F")>=1,"FAIL",(IF(COUNTIF(V99:W99,"P")>=1,"PASS",(IF(COUNTIF(V99:W99,"N/T")>=1,"N/T",(IF(COUNTIF(V99:W99,"N/A")>=1,"N/A","-"))))))) | V99: N/A | W99: N/A | X99: SPAQA-25479(TASK) | Z99: 사양변경 : 12V 배터리 부족 상태 팝업 미노출로 변경: spec out | AA99: 사양 아님(N/A) | AB99: TASK, 삭제
B100: TC_CT_0054 | C100: Control | D100: 제어 | E100: 차량 제어 | F100: 제어 실행 | G100: KR, EU | I100: 5 | K100: 1. 24V 배터리 부족한 상태 2. 상용 차량 | L100: 1. Control 진입 2. 모든 원격제어 시도 | M100: 1. 팝업 표출 "차량의 24V 배터리가 부족합니다." "원격제어를 이용하면 다음 번 시동을 걸지 못할 수 있습니다. 원격제어를 실행하시겠습니까?" [취소] [실행] * 취소 : 닫힘, 현재 화면 유지 * 실행 : 원격제어 실행 | N100: =IF(COUNTIF(P100:W100,"F")>=1,"FAIL",(IF(COUNTIF(P100:W100,"P")>=1,"PASS",(IF(COUNTIF(P100:W100,"N/T")>=1,"N/T",(IF(COUNTIF(P100:W100,"N/A")>=1,"N/A","-"))))))) | O100: N/T | P100: N/T | T100: N/T | U100: =IF(COUNTIF(V100:W100,"F")>=1,"FAIL",(IF(COUNTIF(V100:W100,"P")>=1,"PASS",(IF(COUNTIF(V100:W100,"N/T")>=1,"N/T",(IF(COUNTIF(V100:W100,"N/A")>=1,"N/A","-"))))))) | V100: N/T | W100: N/T | X100: SPAQA-25479(TASK) | Z100: (공통) 24V 배터리 부족한 상태의 대형 차량 필요(N/T) | AA100: N/T : 차량/디바이스 필요(조건) | AB100: Proxy
B101: TC_CT_0055 | C101: Control | D101: 제어 | E101: 차량 제어 | F101: 제어 실행 | G101: KR, EU | I101: 5 | K101: 1. 차량 24V 배터리 부족한 상태 2. 상용 차량 | L101: 1. Control 진입 2. 모든의 원격제어 시도 | M101: 1. 팝업 표출 "차량의 12V 배터리와 24V 배터리가 부족합니다." "원격제어를 이용하면 다음 번 시동을 걸지 못할 수 있습니다. 원격제어를 실행하시겠습니까?" [취소] [실행] * 취소 : 닫힘, 현재 화면 유지 * 실행 : 원격제어 실행 | N101: =IF(COUNTIF(P101:W101,"F")>=1,"FAIL",(IF(COUNTIF(P101:W101,"P")>=1,"PASS",(IF(COUNTIF(P101:W101,"N/T")>=1,"N/T",(IF(COUNTIF(P101:W101,"N/A")>=1,"N/A","-"))))))) | O101: N/T | P101: N/T | T101: N/A | U101: =IF(COUNTIF(V101:W101,"F")>=1,"FAIL",(IF(COUNTIF(V101:W101,"P")>=1,"PASS",(IF(COUNTIF(V101:W101,"N/T")>=1,"N/T",(IF(COUNTIF(V101:W101,"N/A")>=1,"N/A","-"))))))) | V101: N/A | W101: N/A | Z101: TC_CT_0054 중복: 삭제 | AA101: 사양 아님(N/A) | AB101: Proxy, 삭제
B102: TC_CT_0056 | C102: Control | D102: 제어 | E102: 차량 제어 | F102: 제어 실행 | G102: KR, EU | I102: 1 | L102: 1. Control 진입 2. 임의의 원격제어 시도 | M102: 1. 팝업 표출 "차량 제어 명령이 전송되었습니다." "오랫동안 차량을 운행하지 않았거나 통신 상태가 원활하지 않은 곳에 주차하면 푸시 알림을 받지 못하거나 차량이 정상적으로 제어되지 않을 수 있습니다." ㅁ 다시 보지 않기 닫기 * 닫기 : 시트 닫힘, 현재 화면 유지 * 다시 보지 않기 : 팝업 미표출 | N102: =IF(COUNTIF(P102:W102,"F")>=1,"FAIL",(IF(COUNTIF(P102:W102,"P")>=1,"PASS",(IF(COUNTIF(P102:W102,"N/T")>=1,"N/T",(IF(COUNTIF(P102:W102,"N/A")>=1,"N/A","-"))))))) | O102: N/T | P102: N/T | T102: P | U102: =IF(COUNTIF(V102:W102,"F")>=1,"FAIL",(IF(COUNTIF(V102:W102,"P")>=1,"PASS",(IF(COUNTIF(V102:W102,"N/T")>=1,"N/T",(IF(COUNTIF(V102:W102,"N/A")>=1,"N/A","-"))))))) | V102: P | W102: P | X102: SPAQA-15224 | AB102: CheckList
...

Sheet Map
C1: TC 추가 NO : | D1: =IFERROR(__xludf.DUMMYFUNCTION("""TC_""&""MAP""&""_""&TEXT(ARRAYFORMULA(MAX(IFERROR(VALUE(REGEXEXTRACT(B294:B1650, ""\d+"")))))+1,""0000"")"),"TC_MAP_1606")
B2: CCI One App | E2: EU FullTC | L2: =Control!L2 | M2: =IF(COUNTIF(N2:O2,"F")>=1,"FAIL",(IF(COUNTIF(N2:O2,"P")>=1,"PASS",(IF(COUNTIF(N2:O2,"N/T")>=1,"N/T",(IF(COUNTIF(N2:O2,"N/A")>=1,"N/A","-"))))))) | O2: 추가 | P2: 수정 | Q2: 삭제
E3: Project | H3: UID ver. | J3: 1월 피쳐컷 | L3: =Control!L3 | M3: =IF(COUNTIF(N3:O3,"F")>=1,"FAIL",(IF(COUNTIF(N3:O3,"P")>=1,"PASS",(IF(COUNTIF(N3:O3,"N/T")>=1,"N/T",(IF(COUNTIF(N3:O3,"N/A")>=1,"N/A","-"))))))) | O3: =COUNTIFS($AB:$AB,"*"&O2&"*") | P3: =COUNTIFS($AB:$AB,"*"&P2&"*") | Q3: =COUNTIFS($AB:$AB,"*"&Q2&"*")
E4: 담당자 | H4: 작성일자 | L4: =Control!L4 | M4: =IF(COUNTIF(N4:O4,"F")>=1,"FAIL",(IF(COUNTIF(N4:O4,"P")>=1,"PASS",(IF(COUNTIF(N4:O4,"N/T")>=1,"N/T",(IF(COUNTIF(N4:O4,"N/A")>=1,"N/A","-")))))))
L5: =Control!L5 | M5: =IF(COUNTIF(N5:O5,"F")>=1,"FAIL",(IF(COUNTIF(N5:O5,"P")>=1,"PASS",(IF(COUNTIF(N5:O5,"N/T")>=1,"N/T",(IF(COUNTIF(N5:O5,"N/A")>=1,"N/A","-"))))))) | N5: ← 색깔 업뎃 시 직접 색 지정하지 말고, 이거 복붙해 주세요(누가 처리 했는지 히스토리 보관용)
B6: 테스트 환경
B7: Tester
B9: Test Target | D9: Total TC | E9: RunRate | F9: PassRate | G9: PASS | H9: FAIL | I9: N/A | J9: N/T | N9: Brand | O9: KOA | R9: HOA | U9: GOA
B10: Total | D10: =SUM(D11:D25) | E10: =IFERROR(SUM($G10:J10)/$D10,"-") | F10: =IFERROR($G10/(SUM(G10:H10)),"-") | G10: =SUM(G11:G25) | H10: =SUM(H11:H25) | I10: =SUM(I11:I25) | J10: =SUM(J11:J25) | N10: OS 별 결과 | O10: Total | P10: Android | Q10: iOS | R10: Total | S10: Android | T10: iOS | U10: Total | V10: Android | W10: iOS
B11: Map | C11: Common | D11: =COUNTIF($D$29:$D$6877,$C11) | E11: =IFERROR(SUM($G11:J11)/$D11,"-") | F11: =IFERROR($G11/(SUM(G11:H11)),"-") | G11: =COUNTIFS($D:$D,$C11,$N:$N,G$9) | H11: =COUNTIFS($D:$D,$C11,$N:$N,H$9) | I11: =COUNTIFS($D:$D,$C11,$N:$N,I$9) | J11: =COUNTIFS($D:$D,$C11,$N:$N,J$9) | N11: Total | O11: =SUM(O12:O15) | P11: =SUM(P12:P15) | Q11: =SUM(Q12:Q15) | R11: =SUM(R12:R15) | S11: =SUM(S12:S15) | T11: =SUM(T12:T15) | U11: =SUM(U12:U15) | V11: =SUM(V12:V15) | W11: =SUM(W12:W15)
C12: Common (폴리엇 기준) | D12: =COUNTIF($D$29:$D$6877,$C12) | E12: =IFERROR(SUM($G12:J12)/$D12,"-") | F12: =IFERROR($G12/(SUM(G12:H12)),"-") | G12: =COUNTIFS($D:$D,$C12,$N:$N,G$9) | H12: =COUNTIFS($D:$D,$C12,$N:$N,H$9) | I12: =COUNTIFS($D:$D,$C12,$N:$N,I$9) | J12: =COUNTIFS($D:$D,$C12,$N:$N,J$9) | N12: PASS | O12: =COUNTIFS(O$28:O$10284,$N12) | P12: =COUNTIFS(P$28:P$10284,"P") | Q12: =COUNTIFS(Q$28:Q$10284,"P") | R12: =COUNTIFS(R$28:R$10284,$N12) | S12: =COUNTIFS(S$28:S$10284,"P") | T12: =COUNTIFS(T$28:T$10284,"P") | U12: =COUNTIFS(U$28:U$10284,$N12) | V12: =COUNTIFS(V$28:V$10284,"P") | W12: =COUNTIFS(W$28:W$10284,"P")
C13: 화면 분기 | D13: =COUNTIF($D$29:$D$6877,$C13) | E13: =IFERROR(SUM($G13:J13)/$D13,"-") | F13: =IFERROR($G13/(SUM(G13:H13)),"-") | G13: =COUNTIFS($D:$D,$C13,$N:$N,G$9) | H13: =COUNTIFS($D:$D,$C13,$N:$N,H$9) | I13: =COUNTIFS($D:$D,$C13,$N:$N,I$9) | J13: =COUNTIFS($D:$D,$C13,$N:$N,J$9) | N13: FAIL | O13: =COUNTIFS(O$27:O$10283,$N13) | P13: =COUNTIFS(P$27:P$10283,"F") | Q13: =COUNTIFS(Q$27:Q$10283,"F") | R13: =COUNTIFS(R$27:R$10283,$N13) | S13: =COUNTIFS(S$27:S$10283,"F") | T13: =COUNTIFS(T$27:T$10283,"F") | U13: =COUNTIFS(U$27:U$10283,$N13) | V13: =COUNTIFS(V$27:V$10283,"F") | W13: =COUNTIFS(W$27:W$10283,"F")
C14: 메인 지도 | D14: =COUNTIF($D$29:$D$6877,$C14) | E14: =IFERROR(SUM($G14:J14)/$D14,"-") | F14: =IFERROR($G14/(SUM(G14:H14)),"-") | G14: =COUNTIFS($D:$D,$C14,$N:$N,G$9) | H14: =COUNTIFS($D:$D,$C14,$N:$N,H$9) | I14: =COUNTIFS($D:$D,$C14,$N:$N,I$9) | J14: =COUNTIFS($D:$D,$C14,$N:$N,J$9) | N14: N/A | O14: =COUNTIFS(O$27:O$10283,$N14) | P14: =COUNTIFS(P$27:P$10283,$N14) | Q14: =COUNTIFS(Q$27:Q$10283,$N14) | R14: =COUNTIFS(R$27:R$10283,$N14) | S14: =COUNTIFS(S$27:S$10283,"N/A") | T14: =COUNTIFS(T$27:T$10283,"N/A") | U14: =COUNTIFS(U$27:U$10283,$N14) | V14: =COUNTIFS(V$27:V$10283,"N/A") | W14: =COUNTIFS(W$27:W$10283,"N/A")
C15: 홈 탭 | D15: =COUNTIF($D$29:$D$6877,$C15) | E15: =IFERROR(SUM($G15:J15)/$D15,"-") | F15: =IFERROR($G15/(SUM(G15:H15)),"-") | G15: =COUNTIFS($D:$D,$C15,$N:$N,G$9) | H15: =COUNTIFS($D:$D,$C15,$N:$N,H$9) | I15: =COUNTIFS($D:$D,$C15,$N:$N,I$9) | J15: =COUNTIFS($D:$D,$C15,$N:$N,J$9) | N15: N/T | O15: =COUNTIFS(O$27:O$10283,$N15) | P15: =COUNTIFS(P$27:P$10283,$N15) | Q15: =COUNTIFS(Q$27:Q$10283,$N15) | R15: =COUNTIFS(R$27:R$10283,$N15) | S15: =COUNTIFS(S$27:S$10283,"N/T") | T15: =COUNTIFS(T$27:T$10283,"N/T") | U15: =COUNTIFS(U$27:U$10283,$N15) | V15: =COUNTIFS(V$27:V$10283,"N/T") | W15: =COUNTIFS(W$27:W$10283,"N/T")
C16: 즐겨찾기 탭 | D16: =COUNTIF($D$29:$D$6877,$C16) | E16: =IFERROR(SUM($G16:J16)/$D16,"-") | F16: =IFERROR($G16/(SUM(G16:H16)),"-") | G16: =COUNTIFS($D:$D,$C16,$N:$N,G$9) | H16: =COUNTIFS($D:$D,$C16,$N:$N,H$9) | I16: =COUNTIFS($D:$D,$C16,$N:$N,I$9) | J16: =COUNTIFS($D:$D,$C16,$N:$N,J$9)
C17: 최근 검색 탭 | D17: =COUNTIF($D$29:$D$6877,$C17) | E17: =IFERROR(SUM($G17:J17)/$D17,"-") | F17: =IFERROR($G17/(SUM(G17:H17)),"-") | G17: =COUNTIFS($D:$D,$C17,$N:$N,G$9) | H17: =COUNTIFS($D:$D,$C17,$N:$N,H$9) | I17: =COUNTIFS($D:$D,$C17,$N:$N,I$9) | J17: =COUNTIFS($D:$D,$C17,$N:$N,J$9)
C18: 장소/주소 검색 | D18: =COUNTIF($D$29:$D$6877,$C18) | E18: =IFERROR(SUM($G18:J18)/$D18,"-") | F18: =IFERROR($G18/(SUM(G18:H18)),"-") | G18: =COUNTIFS($D:$D,$C18,$N:$N,G$9) | H18: =COUNTIFS($D:$D,$C18,$N:$N,H$9) | I18: =COUNTIFS($D:$D,$C18,$N:$N,I$9) | J18: =COUNTIFS($D:$D,$C18,$N:$N,J$9)
C19: 주변 검색 | D19: =COUNTIF($D$29:$D$6877,$C19) | E19: =IFERROR(SUM($G19:J19)/$D19,"-") | F19: =IFERROR($G19/(SUM(G19:H19)),"-") | G19: =COUNTIFS($D:$D,$C19,$N:$N,G$9) | H19: =COUNTIFS($D:$D,$C19,$N:$N,H$9) | I19: =COUNTIFS($D:$D,$C19,$N:$N,I$9) | J19: =COUNTIFS($D:$D,$C19,$N:$N,J$9)
C20: POI 상세 | D20: =COUNTIF($D$29:$D$6877,$C20) | E20: =IFERROR(SUM($G20:J20)/$D20,"-") | F20: =IFERROR($G20/(SUM(G20:H20)),"-") | G20: =COUNTIFS($D:$D,$C20,$N:$N,G$9) | H20: =COUNTIFS($D:$D,$C20,$N:$N,H$9) | I20: =COUNTIFS($D:$D,$C20,$N:$N,I$9) | J20: =COUNTIFS($D:$D,$C20,$N:$N,J$9)
C21: 경로 탐색 | D21: =COUNTIF($D$29:$D$6877,$C21) | E21: =IFERROR(SUM($G21:J21)/$D21,"-") | F21: =IFERROR($G21/(SUM(G21:H21)),"-") | G21: =COUNTIFS($D:$D,$C21,$N:$N,G$9) | H21: =COUNTIFS($D:$D,$C21,$N:$N,H$9) | I21: =COUNTIFS($D:$D,$C21,$N:$N,I$9) | J21: =COUNTIFS($D:$D,$C21,$N:$N,J$9)
C22: 내 차 위치 | D22: =COUNTIF($D$29:$D$6877,$C22) | E22: =IFERROR(SUM($G22:J22)/$D22,"-") | F22: =IFERROR($G22/(SUM(G22:H22)),"-") | G22: =COUNTIFS($D:$D,$C22,$N:$N,G$9) | H22: =COUNTIFS($D:$D,$C22,$N:$N,H$9) | I22: =COUNTIFS($D:$D,$C22,$N:$N,I$9) | J22: =COUNTIFS($D:$D,$C22,$N:$N,J$9)
C23: 최종 목적지 안내 | D23: =COUNTIF($D$29:$D$6877,$C23) | E23: =IFERROR(SUM($G23:J23)/$D23,"-") | F23: =IFERROR($G23/(SUM(G23:H23)),"-") | G23: =COUNTIFS($D:$D,$C23,$N:$N,G$9) | H23: =COUNTIFS($D:$D,$C23,$N:$N,H$9) | I23: =COUNTIFS($D:$D,$C23,$N:$N,I$9) | J23: =COUNTIFS($D:$D,$C23,$N:$N,J$9)
C24: 발레 모드 | D24: =COUNTIF($D$29:$D$6877,$C24) | E24: =IFERROR(SUM($G24:J24)/$D24,"-") | F24: =IFERROR($G24/(SUM(G24:H24)),"-") | G24: =COUNTIFS($D:$D,$C24,$N:$N,G$9) | H24: =COUNTIFS($D:$D,$C24,$N:$N,H$9) | I24: =COUNTIFS($D:$D,$C24,$N:$N,I$9) | J24: =COUNTIFS($D:$D,$C24,$N:$N,J$9)
C25: 외부 맵 S2C 요청 (OS Share) | D25: =COUNTIF($D$29:$D$6877,$C25) | E25: =IFERROR(SUM($G25:J25)/$D25,"-") | F25: =IFERROR($G25/(SUM(G25:H25)),"-") | G25: =COUNTIFS($D:$D,$C25,$N:$N,G$9) | H25: =COUNTIFS($D:$D,$C25,$N:$N,H$9) | I25: =COUNTIFS($D:$D,$C25,$N:$N,I$9) | J25: =COUNTIFS($D:$D,$C25,$N:$N,J$9)
B27: TC ID | C27: 카테고리 | D27: 대분류 | E27: 중분류 | F27: 소분류 | G27: 향지 | H27: 브랜드 | I27: 우선순위 | J27: Pre-condition | L27: TC procedure | M27: Expected result | N27: Result | O27: KOA Result | P27: KOA | R27: HOA Result | S27: HOA | U27: GOA Result | V27: GOA | X27: Closed 지라 NO | Y27: 지라 NO. | Z27: NT/NA 상세 사유 | AA27: N/A N/T 필터 | AB27: LABEL
J28: App 동작 조건 | K28: 차량 동작 조건 | P28: Android | Q28: iOS | S28: Android | T28: iOS | V28: Android | W28: iOS
B29: TC_MAP_0001 | C29: Map | D29: Common | E29: 지도 정보 표시 | F29: 로고 | G29: EU | I29: 4 | J29: 1. Here 맵 | L29: 1. Map 진입 2. 드로어 최소화 3. 지도 확인 | M29: 1. 지도 좌하단에 Here 로고 노출 | N29: =IF(COUNTIF(P29:W29,"F")>=1,"FAIL",(IF(COUNTIF(P29:W29,"P")>=1,"PASS",(IF(COUNTIF(P29:W29,"N/T")>=1,"N/T",(IF(COUNTIF(P29:W29,"N/A")>=1,"N/A","-"))))))) | O29: =IF(COUNTIF(P29:Q29,"F")>=1,"FAIL",(IF(COUNTIF(P29:Q29,"P")>=1,"PASS",(IF(COUNTIF(P29:Q29,"N/T")>=1,"N/T",(IF(COUNTIF(P29:Q29,"N/A")>=1,"N/A","-"))))))) | P29: P | Q29: P | R29: =IF(COUNTIF(S29:T29,"F")>=1,"FAIL",(IF(COUNTIF(S29:T29,"P")>=1,"PASS",(IF(COUNTIF(S29:T29,"N/T")>=1,"N/T",(IF(COUNTIF(S29:T29,"N/A")>=1,"N/A","-"))))))) | S29: P | T29: P | U29: =IF(COUNTIF(V29:W29,"F")>=1,"FAIL",(IF(COUNTIF(V29:W29,"P")>=1,"PASS",(IF(COUNTIF(V29:W29,"N/T")>=1,"N/T",(IF(COUNTIF(V29:W29,"N/A")>=1,"N/A","-"))))))) | V29: P | W29: P | X29: SPAQA-23885 SPAQA-25036 SPAQA-26158 SPAQA-26160
B30: TC_MAP_0002 | C30: Map | D30: Common | E30: 지도 정보 표시 | F30: 로고 | G30: EU | I30: 4 | J30: 1. Here 맵 | L30: 1. Map 진입 2. 드로어 확장 3. 지도 확인 | M30: 1. Here 로고가 Bottom Sheet에 가려짐 | N30: =IF(COUNTIF(P30:W30,"F")>=1,"FAIL",(IF(COUNTIF(P30:W30,"P")>=1,"PASS",(IF(COUNTIF(P30:W30,"N/T")>=1,"N/T",(IF(COUNTIF(P30:W30,"N/A")>=1,"N/A","-"))))))) | O30: =IF(COUNTIF(P30:Q30,"F")>=1,"FAIL",(IF(COUNTIF(P30:Q30,"P")>=1,"PASS",(IF(COUNTIF(P30:Q30,"N/T")>=1,"N/T",(IF(COUNTIF(P30:Q30,"N/A")>=1,"N/A","-"))))))) | P30: P | Q30: P | R30: =IF(COUNTIF(S30:T30,"F")>=1,"FAIL",(IF(COUNTIF(S30:T30,"P")>=1,"PASS",(IF(COUNTIF(S30:T30,"N/T")>=1,"N/T",(IF(COUNTIF(S30:T30,"N/A")>=1,"N/A","-"))))))) | S30: P | T30: P | U30: =IF(COUNTIF(V30:W30,"F")>=1,"FAIL",(IF(COUNTIF(V30:W30,"P")>=1,"PASS",(IF(COUNTIF(V30:W30,"N/T")>=1,"N/T",(IF(COUNTIF(V30:W30,"N/A")>=1,"N/A","-"))))))) | V30: P | W30: P
A31: R_179 | B31: TC_MAP_0003 | C31: Map | D31: Common | E31: 지도 정보 표시 | F31: 로고 | G31: EU | I31: 4 | J31: 1. Google 맵 | L31: 1. Map 진입 2. 드로어 최소화 3. 지도 확인 | M31: 1. Bottom Sheet 좌상단에 Google 로고 노출 | N31: =IF(COUNTIF(P31:W31,"F")>=1,"FAIL",(IF(COUNTIF(P31:W31,"P")>=1,"PASS",(IF(COUNTIF(P31:W31,"N/T")>=1,"N/T",(IF(COUNTIF(P31:W31,"N/A")>=1,"N/A","-"))))))) | O31: =IF(COUNTIF(P31:Q31,"F")>=1,"FAIL",(IF(COUNTIF(P31:Q31,"P")>=1,"PASS",(IF(COUNTIF(P31:Q31,"N/T")>=1,"N/T",(IF(COUNTIF(P31:Q31,"N/A")>=1,"N/A","-"))))))) | P31: P | Q31: P | R31: =IF(COUNTIF(S31:T31,"F")>=1,"FAIL",(IF(COUNTIF(S31:T31,"P")>=1,"PASS",(IF(COUNTIF(S31:T31,"N/T")>=1,"N/T",(IF(COUNTIF(S31:T31,"N/A")>=1,"N/A","-"))))))) | S31: P | T31: P | U31: =IF(COUNTIF(V31:W31,"F")>=1,"FAIL",(IF(COUNTIF(V31:W31,"P")>=1,"PASS",(IF(COUNTIF(V31:W31,"N/T")>=1,"N/T",(IF(COUNTIF(V31:W31,"N/A")>=1,"N/A","-"))))))) | V31: P | W31: P | X31: SPAQA-22906 SPAQA-22912 SPAQA-22373 SPAQA-26160 SPAQA-26431 | AB31: TASK
B32: TC_MAP_0004 | C32: Map | D32: Common | E32: 지도 정보 표시 | F32: 로고 | G32: EU | I32: 4 | J32: 1. Google 맵 | L32: 1. Map 진입 2. 드로어 확장 3. 지도 확인 | M32: 1. Google 로고가 Bottom Sheet를 따라 좌상단 노출 유지 됨 | N32: =IF(COUNTIF(P32:W32,"F")>=1,"FAIL",(IF(COUNTIF(P32:W32,"P")>=1,"PASS",(IF(COUNTIF(P32:W32,"N/T")>=1,"N/T",(IF(COUNTIF(P32:W32,"N/A")>=1,"N/A","-"))))))) | O32: =IF(COUNTIF(P32:Q32,"F")>=1,"FAIL",(IF(COUNTIF(P32:Q32,"P")>=1,"PASS",(IF(COUNTIF(P32:Q32,"N/T")>=1,"N/T",(IF(COUNTIF(P32:Q32,"N/A")>=1,"N/A","-"))))))) | P32: P | Q32: P | R32: =IF(COUNTIF(S32:T32,"F")>=1,"FAIL",(IF(COUNTIF(S32:T32,"P")>=1,"PASS",(IF(COUNTIF(S32:T32,"N/T")>=1,"N/T",(IF(COUNTIF(S32:T32,"N/A")>=1,"N/A","-"))))))) | S32: P | T32: P | U32: =IF(COUNTIF(V32:W32,"F")>=1,"FAIL",(IF(COUNTIF(V32:W32,"P")>=1,"PASS",(IF(COUNTIF(V32:W32,"N/T")>=1,"N/T",(IF(COUNTIF(V32:W32,"N/A")>=1,"N/A","-"))))))) | V32: P | W32: P | X32: SPAQA-22906 SPAQA-22912 SPAQA-22373 SPAQA-26242 | AB32: TASK
B33: TC_MAP_0005 | C33: Map | D33: Common | E33: 지도 정보 표시 | F33: 로고 | G33: EU | I33: 4 | L33: 1. Map 진입 2. 임의의 Poi 전체 상세 화면 진입 3. 상세 화면 내 미니맵 확인 | M33: 1. 미니맵 좌 하단에 로고 노출 | N33: =IF(COUNTIF(P33:W33,"F")>=1,"FAIL",(IF(COUNTIF(P33:W33,"P")>=1,"PASS",(IF(COUNTIF(P33:W33,"N/T")>=1,"N/T",(IF(COUNTIF(P33:W33,"N/A")>=1,"N/A","-"))))))) | O33: =IF(COUNTIF(P33:Q33,"F")>=1,"FAIL",(IF(COUNTIF(P33:Q33,"P")>=1,"PASS",(IF(COUNTIF(P33:Q33,"N/T")>=1,"N/T",(IF(COUNTIF(P33:Q33,"N/A")>=1,"N/A","-"))))))) | P33: P | Q33: P | R33: =IF(COUNTIF(S33:T33,"F")>=1,"FAIL",(IF(COUNTIF(S33:T33,"P")>=1,"PASS",(IF(COUNTIF(S33:T33,"N/T")>=1,"N/T",(IF(COUNTIF(S33:T33,"N/A")>=1,"N/A","-"))))))) | S33: P | T33: P | U33: =IF(COUNTIF(V33:W33,"F")>=1,"FAIL",(IF(COUNTIF(V33:W33,"P")>=1,"PASS",(IF(COUNTIF(V33:W33,"N/T")>=1,"N/T",(IF(COUNTIF(V33:W33,"N/A")>=1,"N/A","-"))))))) | V33: P | W33: P
B34: TC_MAP_0006 | C34: Map | D34: Common | E34: 지도 재진입 | F34: 지도 재진입 | G34: KR, EU, NA | I34: 4 | J34: 1. 내 차 위치 조회 가능할 경우 | L34: 1. Map 진입 2. 메인 지도 확인 | M34: 1. 내 차 위치 마커 포커스 2. Default 줌레벨로 원복 | N34: =IF(COUNTIF(P34:W34,"F")>=1,"FAIL",(IF(COUNTIF(P34:W34,"P")>=1,"PASS",(IF(COUNTIF(P34:W34,"N/T")>=1,"N/T",(IF(COUNTIF(P34:W34,"N/A")>=1,"N/A","-"))))))) | O34: =IF(COUNTIF(P34:Q34,"F")>=1,"FAIL",(IF(COUNTIF(P34:Q34,"P")>=1,"PASS",(IF(COUNTIF(P34:Q34,"N/T")>=1,"N/T",(IF(COUNTIF(P34:Q34,"N/A")>=1,"N/A","-"))))))) | P34: P | Q34: P | R34: =IF(COUNTIF(S34:T34,"F")>=1,"FAIL",(IF(COUNTIF(S34:T34,"P")>=1,"PASS",(IF(COUNTIF(S34:T34,"N/T")>=1,"N/T",(IF(COUNTIF(S34:T34,"N/A")>=1,"N/A","-"))))))) | S34: P | T34: P | U34: =IF(COUNTIF(V34:W34,"F")>=1,"FAIL",(IF(COUNTIF(V34:W34,"P")>=1,"PASS",(IF(COUNTIF(V34:W34,"N/T")>=1,"N/T",(IF(COUNTIF(V34:W34,"N/A")>=1,"N/A","-"))))))) | V34: P | W34: P | X34: SPAQA-15625 SPAQA-25093 SPAQA-24505 SPAQA-24846 SPAQA-24844 SPAQA-26515
A35: Q_012 | B35: TC_MAP_0007 | C35: Map | D35: Common | E35: 지도 재진입 | F35: 지도 재진입 | G35: KR, EU, NA | I35: 5 | J35: 1. 내 차 위치 조회 불가, 내 위치 조회 가능할 경우 | L35: 1. Map 진입 2. 메인 지도 확인 | M35: 1. 내 위치 마커 포커스 2. Default 줌레벨로 원복 | N35: =IF(COUNTIF(P35:W35,"F")>=1,"FAIL",(IF(COUNTIF(P35:W35,"P")>=1,"PASS",(IF(COUNTIF(P35:W35,"N/T")>=1,"N/T",(IF(COUNTIF(P35:W35,"N/A")>=1,"N/A","-"))))))) | O35: =IF(COUNTIF(P35:Q35,"F")>=1,"FAIL",(IF(COUNTIF(P35:Q35,"P")>=1,"PASS",(IF(COUNTIF(P35:Q35,"N/T")>=1,"N/T",(IF(COUNTIF(P35:Q35,"N/A")>=1,"N/A","-"))))))) | P35: P | Q35: P | R35: =IF(COUNTIF(S35:T35,"F")>=1,"FAIL",(IF(COUNTIF(S35:T35,"P")>=1,"PASS",(IF(COUNTIF(S35:T35,"N/T")>=1,"N/T",(IF(COUNTIF(S35:T35,"N/A")>=1,"N/A","-"))))))) | S35: P | T35: P | U35: =IF(COUNTIF(V35:W35,"F")>=1,"FAIL",(IF(COUNTIF(V35:W35,"P")>=1,"PASS",(IF(COUNTIF(V35:W35,"N/T")>=1,"N/T",(IF(COUNTIF(V35:W35,"N/A")>=1,"N/A","-"))))))) | V35: P | W35: P | X35: SPAQA-24199 SPAQA-24207 SPAQA-25682
B36: TC_MAP_0008 | C36: Map | D36: Common | E36: 지도 재진입 | F36: 지도 재진입 | G36: KR, EU, NA | I36: 5 | J36: 1. 내 차 위치, 내 위치 조회 불가할 경우 | L36: 1. Map 진입 2. 메인 지도 확인 | M36: 1. Default 위치 포커스 2. Default 축척으로 원복 | N36: =IF(COUNTIF(P36:W36,"F")>=1,"FAIL",(IF(COUNTIF(P36:W36,"P")>=1,"PASS",(IF(COUNTIF(P36:W36,"N/T")>=1,"N/T",(IF(COUNTIF(P36:W36,"N/A")>=1,"N/A","-"))))))) | O36: =IF(COUNTIF(P36:Q36,"F")>=1,"FAIL",(IF(COUNTIF(P36:Q36,"P")>=1,"PASS",(IF(COUNTIF(P36:Q36,"N/T")>=1,"N/T",(IF(COUNTIF(P36:Q36,"N/A")>=1,"N/A","-"))))))) | P36: P | Q36: P | R36: =IF(COUNTIF(S36:T36,"F")>=1,"FAIL",(IF(COUNTIF(S36:T36,"P")>=1,"PASS",(IF(COUNTIF(S36:T36,"N/T")>=1,"N/T",(IF(COUNTIF(S36:T36,"N/A")>=1,"N/A","-"))))))) | S36: P | T36: P | U36: =IF(COUNTIF(V36:W36,"F")>=1,"FAIL",(IF(COUNTIF(V36:W36,"P")>=1,"PASS",(IF(COUNTIF(V36:W36,"N/T")>=1,"N/T",(IF(COUNTIF(V36:W36,"N/A")>=1,"N/A","-"))))))) | V36: P | W36: P | Z36: 내 위치 OFF: App 내 위치 권한 OFF 내 차 위치 OFF: E-privacy 미지원 차량에서 Servicelist OFF
B37: TC_MAP_0009 | C37: Map | D37: Common | E37: 지도 재진입 | F37: 지도 재진입 | G37: KR, EU, NA | I37: 4 | L37: 1. Map 진입 2. BG 갔다가 FG 화면 복귀 3. 메인 지도 확인 | M37: 1. 지도 위치 / 줌레벨 유지 (이전 상태 유지) | N37: =IF(COUNTIF(P37:W37,"F")>=1,"FAIL",(IF(COUNTIF(P37:W37,"P")>=1,"PASS",(IF(COUNTIF(P37:W37,"N/T")>=1,"N/T",(IF(COUNTIF(P37:W37,"N/A")>=1,"N/A","-"))))))) | O37: =IF(COUNTIF(P37:Q37,"F")>=1,"FAIL",(IF(COUNTIF(P37:Q37,"P")>=1,"PASS",(IF(COUNTIF(P37:Q37,"N/T")>=1,"N/T",(IF(COUNTIF(P37:Q37,"N/A")>=1,"N/A","-"))))))) | P37: P | Q37: P | R37: =IF(COUNTIF(S37:T37,"F")>=1,"FAIL",(IF(COUNTIF(S37:T37,"P")>=1,"PASS",(IF(COUNTIF(S37:T37,"N/T")>=1,"N/T",(IF(COUNTIF(S37:T37,"N/A")>=1,"N/A","-"))))))) | S37: P | T37: P | U37: =IF(COUNTIF(V37:W37,"F")>=1,"FAIL",(IF(COUNTIF(V37:W37,"P")>=1,"PASS",(IF(COUNTIF(V37:W37,"N/T")>=1,"N/T",(IF(COUNTIF(V37:W37,"N/A")>=1,"N/A","-"))))))) | V37: P | W37: P | X37: SPAQA-26153
B38: TC_MAP_0010 | C38: Map | D38: Common | E38: 지도 재진입 | F38: 지도 재진입 | G38: KR, EU, NA | I38: 5 | K38: 1. 실차 주행 가능 상태 | L38: 1. Map 진입 2. BG 화면으로 전환 3. 실차 주행하여 다른 위치로 이동 4. FG 화면 복귀 5. 메인 지도 내 내 차 위치 마커 확인 | M38: 1. 이동한 위치에 맞게 내 차 위치 마커 업데이트 됨 | N38: =IF(COUNTIF(P38:W38,"F")>=1,"FAIL",(IF(COUNTIF(P38:W38,"P")>=1,"PASS",(IF(COUNTIF(P38:W38,"N/T")>=1,"N/T",(IF(COUNTIF(P38:W38,"N/A")>=1,"N/A","-"))))))) | O38: =IF(COUNTIF(P38:Q38,"F")>=1,"FAIL",(IF(COUNTIF(P38:Q38,"P")>=1,"PASS",(IF(COUNTIF(P38:Q38,"N/T")>=1,"N/T",(IF(COUNTIF(P38:Q38,"N/A")>=1,"N/A","-"))))))) | P38: N/T | Q38: N/T | R38: =IF(COUNTIF(S38:T38,"F")>=1,"FAIL",(IF(COUNTIF(S38:T38,"P")>=1,"PASS",(IF(COUNTIF(S38:T38,"N/T")>=1,"N/T",(IF(COUNTIF(S38:T38,"N/A")>=1,"N/A","-"))))))) | S38: N/T | T38: N/T | U38: =IF(COUNTIF(V38:W38,"F")>=1,"FAIL",(IF(COUNTIF(V38:W38,"P")>=1,"PASS",(IF(COUNTIF(V38:W38,"N/T")>=1,"N/T",(IF(COUNTIF(V38:W38,"N/A")>=1,"N/A","-"))))))) | V38: N/T | W38: N/T | Z38: (공통) 차량 위치가 유럽으로 고정되어 있어 확인 불가(N/T) | AA38: N/T : 외부 환경 필요(환경) | AB38: 실차
B39: TC_MAP_0011 | C39: Map | D39: Common | E39: 지도 재진입 | F39: 지도 재진입 | G39: KR, EU, NA | I39: 5 | K39: 1. 실차 주행 가능 상태 | L39: 1. Map 진입 2. BG 화면으로 전환 3. 실차 주행하여 다른 위치로 이동 4. FG 화면 복귀 5. 홈 탭 내 내 차 위치 영역 확인 | M39: 1. 이동한 위치에 맞는 주소 및 직선 거리 업데이트 됨 | N39: =IF(COUNTIF(P39:W39,"F")>=1,"FAIL",(IF(COUNTIF(P39:W39,"P")>=1,"PASS",(IF(COUNTIF(P39:W39,"N/T")>=1,"N/T",(IF(COUNTIF(P39:W39,"N/A")>=1,"N/A","-"))))))) | O39: =IF(COUNTIF(P39:Q39,"F")>=1,"FAIL",(IF(COUNTIF(P39:Q39,"P")>=1,"PASS",(IF(COUNTIF(P39:Q39,"N/T")>=1,"N/T",(IF(COUNTIF(P39:Q39,"N/A")>=1,"N/A","-"))))))) | P39: N/T | Q39: N/T | R39: =IF(COUNTIF(S39:T39,"F")>=1,"FAIL",(IF(COUNTIF(S39:T39,"P")>=1,"PASS",(IF(COUNTIF(S39:T39,"N/T")>=1,"N/T",(IF(COUNTIF(S39:T39,"N/A")>=1,"N/A","-"))))))) | S39: N/T | T39: N/T | U39: =IF(COUNTIF(V39:W39,"F")>=1,"FAIL",(IF(COUNTIF(V39:W39,"P")>=1,"PASS",(IF(COUNTIF(V39:W39,"N/T")>=1,"N/T",(IF(COUNTIF(V39:W39,"N/A")>=1,"N/A","-"))))))) | V39: N/T | W39: N/T | Z39: (공통) 차량 위치가 유럽으로 고정되어 있어 확인 불가(N/T) | AA39: N/T : 외부 환경 필요(환경) | AB39: 실차
B40: TC_MAP_0012 | C40: Map | D40: Common | E40: 지도 재진입 | F40: 지도 재진입 | G40: KR, EU, NA | I40: 4 | L40: 1. Map 진입 2. 다른 화면 이동 3. [<] 또는 [X] 버튼 사용하여 기존 화면 복귀 | M40: 1. 지도 위치 / 줌레벨 유지 (이전 상태 유지) | N40: =IF(COUNTIF(P40:W40,"F")>=1,"FAIL",(IF(COUNTIF(P40:W40,"P")>=1,"PASS",(IF(COUNTIF(P40:W40,"N/T")>=1,"N/T",(IF(COUNTIF(P40:W40,"N/A")>=1,"N/A","-"))))))) | O40: =IF(COUNTIF(P40:Q40,"F")>=1,"FAIL",(IF(COUNTIF(P40:Q40,"P")>=1,"PASS",(IF(COUNTIF(P40:Q40,"N/T")>=1,"N/T",(IF(COUNTIF(P40:Q40,"N/A")>=1,"N/A","-"))))))) | P40: P | Q40: P | R40: =IF(COUNTIF(S40:T40,"F")>=1,"FAIL",(IF(COUNTIF(S40:T40,"P")>=1,"PASS",(IF(COUNTIF(S40:T40,"N/T")>=1,"N/T",(IF(COUNTIF(S40:T40,"N/A")>=1,"N/A","-"))))))) | S40: P | T40: P | U40: =IF(COUNTIF(V40:W40,"F")>=1,"FAIL",(IF(COUNTIF(V40:W40,"P")>=1,"PASS",(IF(COUNTIF(V40:W40,"N/T")>=1,"N/T",(IF(COUNTIF(V40:W40,"N/A")>=1,"N/A","-"))))))) | V40: P | W40: P
B41: TC_MAP_0013 | C41: Map | D41: Common | E41: 지도 재진입 | F41: 지도 재진입 | G41: KR, EU, NA | I41: 4 | J41: 1. 내 차 위치 버튼 On 상태 | L41: 1. Map 진입 2. 다른 화면 이동 3. [<] 또는 [X] 버튼 사용하여 기존 화면 복귀 | M41: 1. 내 차 위치 버튼 비활성화 * [내 차 위치]는 FSM이므로 해당되지 않음 | N41: =IF(COUNTIF(P41:W41,"F")>=1,"FAIL",(IF(COUNTIF(P41:W41,"P")>=1,"PASS",(IF(COUNTIF(P41:W41,"N/T")>=1,"N/T",(IF(COUNTIF(P41:W41,"N/A")>=1,"N/A","-"))))))) | O41: =IF(COUNTIF(P41:Q41,"F")>=1,"FAIL",(IF(COUNTIF(P41:Q41,"P")>=1,"PASS",(IF(COUNTIF(P41:Q41,"N/T")>=1,"N/T",(IF(COUNTIF(P41:Q41,"N/A")>=1,"N/A","-"))))))) | P41: P | Q41: P | R41: =IF(COUNTIF(S41:T41,"F")>=1,"FAIL",(IF(COUNTIF(S41:T41,"P")>=1,"PASS",(IF(COUNTIF(S41:T41,"N/T")>=1,"N/T",(IF(COUNTIF(S41:T41,"N/A")>=1,"N/A","-"))))))) | S41: P | T41: P | U41: =IF(COUNTIF(V41:W41,"F")>=1,"FAIL",(IF(COUNTIF(V41:W41,"P")>=1,"PASS",(IF(COUNTIF(V41:W41,"N/T")>=1,"N/T",(IF(COUNTIF(V41:W41,"N/A")>=1,"N/A","-"))))))) | V41: P | W41: P | X41: SPAQA-23887
B42: TC_MAP_0014 | C42: Map | D42: Common | E42: 지도 재진입 | F42: 지도 재진입 | G42: KR, EU, NA | I42: 4 | J42: 1. 내 위치 버튼 On 상태 | L42: 1. Map 진입 2. 다른 화면 이동 3. [<] 또는 [X] 버튼 사용하여 기존 화면 복귀 | M42: 1. 내 위치 버튼 비활성화 | N42: =IF(COUNTIF(P42:W42,"F")>=1,"FAIL",(IF(COUNTIF(P42:W42,"P")>=1,"PASS",(IF(COUNTIF(P42:W42,"N/T")>=1,"N/T",(IF(COUNTIF(P42:W42,"N/A")>=1,"N/A","-"))))))) | O42: =IF(COUNTIF(P42:Q42,"F")>=1,"FAIL",(IF(COUNTIF(P42:Q42,"P")>=1,"PASS",(IF(COUNTIF(P42:Q42,"N/T")>=1,"N/T",(IF(COUNTIF(P42:Q42,"N/A")>=1,"N/A","-"))))))) | P42: P | Q42: P | R42: =IF(COUNTIF(S42:T42,"F")>=1,"FAIL",(IF(COUNTIF(S42:T42,"P")>=1,"PASS",(IF(COUNTIF(S42:T42,"N/T")>=1,"N/T",(IF(COUNTIF(S42:T42,"N/A")>=1,"N/A","-"))))))) | S42: P | T42: P | U42: =IF(COUNTIF(V42:W42,"F")>=1,"FAIL",(IF(COUNTIF(V42:W42,"P")>=1,"PASS",(IF(COUNTIF(V42:W42,"N/T")>=1,"N/T",(IF(COUNTIF(V42:W42,"N/A")>=1,"N/A","-"))))))) | V42: P | W42: P
B43: TC_MAP_1524 | C43: Map | D43: Common | E43: 지도 재진입 | F43: 지도 재진입 | G43: KR, EU, NA | H43: KOA | I43: 4 | L43: 1. Map 진입 2. 하단 드로어 영역 축소/확대 3. 타 GNB 선택 후 Map 탭 복귀 4. 드로어 영역 상태 확인 | M43: 1. 확장 상태 유지 ※ 표시되는 콘텐츠는 포커스 된 기준으로 변경 | N43: =IF(COUNTIF(P43:W43,"F")>=1,"FAIL",(IF(COUNTIF(P43:W43,"P")>=1,"PASS",(IF(COUNTIF(P43:W43,"N/T")>=1,"N/T",(IF(COUNTIF(P43:W43,"N/A")>=1,"N/A","-"))))))) | O43: =IF(COUNTIF(P43:Q43,"F")>=1,"FAIL",(IF(COUNTIF(P43:Q43,"P")>=1,"PASS",(IF(COUNTIF(P43:Q43,"N/T")>=1,"N/T",(IF(COUNTIF(P43:Q43,"N/A")>=1,"N/A","-"))))))) | P43: P | Q43: P | R43: =IF(COUNTIF(S43:T43,"F")>=1,"FAIL",(IF(COUNTIF(S43:T43,"P")>=1,"PASS",(IF(COUNTIF(S43:T43,"N/T")>=1,"N/T",(IF(COUNTIF(S43:T43,"N/A")>=1,"N/A","-"))))))) | S43: N/A | T43: N/A | U43: =IF(COUNTIF(V43:W43,"F")>=1,"FAIL",(IF(COUNTIF(V43:W43,"P")>=1,"PASS",(IF(COUNTIF(V43:W43,"N/T")>=1,"N/T",(IF(COUNTIF(V43:W43,"N/A")>=1,"N/A","-"))))))) | V43: N/A | W43: N/A | X43: SPAQA-23900 | Z43: H/G: Map FSM 화면으로 사양 아님(N/A) | AA43: 사양 아님(N/A)
B44: TC_MAP_0015 | C44: Map | D44: Common | E44: 신약관 동의 | F44: 신약관 동의 | G44: KR, EU | I44: 5 | J44: 1. 신약관 미동의 상태 | L44: 1. Map 진입 2. 화면 확인 | M44: 1. 신약관 동의 안내 화면 노출 (iC) 새로운 약관 동의 안내 더욱 안전한 서비스를 위해 새로운 {CCS_SERVICE_NAME} 이용 약관에 동의해 주세요. [약관 확인] | N44: =IF(COUNTIF(P44:W44,"F")>=1,"FAIL",(IF(COUNTIF(P44:W44,"P")>=1,"PASS",(IF(COUNTIF(P44:W44,"N/T")>=1,"N/T",(IF(COUNTIF(P44:W44,"N/A")>=1,"N/A","-"))))))) | O44: =IF(COUNTIF(P44:Q44,"F")>=1,"FAIL",(IF(COUNTIF(P44:Q44,"P")>=1,"PASS",(IF(COUNTIF(P44:Q44,"N/T")>=1,"N/T",(IF(COUNTIF(P44:Q44,"N/A")>=1,"N/A","-"))))))) | P44: N/T | Q44: N/T | R44: =IF(COUNTIF(S44:T44,"F")>=1,"FAIL",(IF(COUNTIF(S44:T44,"P")>=1,"PASS",(IF(COUNTIF(S44:T44,"N/T")>=1,"N/T",(IF(COUNTIF(S44:T44,"N/A")>=1,"N/A","-"))))))) | S44: N/T | T44: N/T | U44: =IF(COUNTIF(V44:W44,"F")>=1,"FAIL",(IF(COUNTIF(V44:W44,"P")>=1,"PASS",(IF(COUNTIF(V44:W44,"N/T")>=1,"N/T",(IF(COUNTIF(V44:W44,"N/A")>=1,"N/A","-"))))))) | V44: N/T | W44: N/T | Z44: (공통) 신약관 확인 불가(N/T) | AA44: N/T : 특수상황/실패 조건 필요(조건)
B45: TC_MAP_0016 | C45: Map | D45: Common | E45: 신약관 동의 | F45: 신약관 동의 | G45: KR, EU | I45: 5 | J45: 1. 신약관 미동의 상태 | L45: 1. Map 진입 2. 화면 확인 3. [약관 확인] 버튼 선택 | M45: 1. {CCS_SERVICE} 이용 약관 화면 이동 | N45: =IF(COUNTIF(P45:W45,"F")>=1,"FAIL",(IF(COUNTIF(P45:W45,"P")>=1,"PASS",(IF(COUNTIF(P45:W45,"N/T")>=1,"N/T",(IF(COUNTIF(P45:W45,"N/A")>=1,"N/A","-"))))))) | O45: =IF(COUNTIF(P45:Q45,"F")>=1,"FAIL",(IF(COUNTIF(P45:Q45,"P")>=1,"PASS",(IF(COUNTIF(P45:Q45,"N/T")>=1,"N/T",(IF(COUNTIF(P45:Q45,"N/A")>=1,"N/A","-"))))))) | P45: N/T | Q45: N/T | R45: =IF(COUNTIF(S45:T45,"F")>=1,"FAIL",(IF(COUNTIF(S45:T45,"P")>=1,"PASS",(IF(COUNTIF(S45:T45,"N/T")>=1,"N/T",(IF(COUNTIF(S45:T45,"N/A")>=1,"N/A","-"))))))) | S45: N/T | T45: N/T | U45: =IF(COUNTIF(V45:W45,"F")>=1,"FAIL",(IF(COUNTIF(V45:W45,"P")>=1,"PASS",(IF(COUNTIF(V45:W45,"N/T")>=1,"N/T",(IF(COUNTIF(V45:W45,"N/A")>=1,"N/A","-"))))))) | V45: N/T | W45: N/T | Z45: (공통) 신약관 확인 불가(N/T) | AA45: N/T : 특수상황/실패 조건 필요(조건)
B46: TC_MAP_0017 | C46: Map | D46: Common | E46: 신약관 동의 | F46: 신약관 동의 | G46: KR, EU | I46: 5 | J46: 1. 차주/피공유자 모두 신약관 미동의 상태 | L46: 1. 피공유자 Map 진입 2. [약관 확인] 버튼 선택 3. 신약관 동의 프로세스 진행 4. 신약관 동의 완료 | M46: 1. 팝업 표출 차주가 약관에 동의한 후 서비스를 이용할 수 있어요. [확인] | N46: =IF(COUNTIF(P46:W46,"F")>=1,"FAIL",(IF(COUNTIF(P46:W46,"P")>=1,"PASS",(IF(COUNTIF(P46:W46,"N/T")>=1,"N/T",(IF(COUNTIF(P46:W46,"N/A")>=1,"N/A","-"))))))) | O46: =IF(COUNTIF(P46:Q46,"F")>=1,"FAIL",(IF(COUNTIF(P46:Q46,"P")>=1,"PASS",(IF(COUNTIF(P46:Q46,"N/T")>=1,"N/T",(IF(COUNTIF(P46:Q46,"N/A")>=1,"N/A","-"))))))) | P46: N/T | Q46: N/T | R46: =IF(COUNTIF(S46:T46,"F")>=1,"FAIL",(IF(COUNTIF(S46:T46,"P")>=1,"PASS",(IF(COUNTIF(S46:T46,"N/T")>=1,"N/T",(IF(COUNTIF(S46:T46,"N/A")>=1,"N/A","-"))))))) | S46: N/T | T46: N/T | U46: =IF(COUNTIF(V46:W46,"F")>=1,"FAIL",(IF(COUNTIF(V46:W46,"P")>=1,"PASS",(IF(COUNTIF(V46:W46,"N/T")>=1,"N/T",(IF(COUNTIF(V46:W46,"N/A")>=1,"N/A","-"))))))) | V46: N/T | W46: N/T | Z46: (공통) 신약관 확인 불가(N/T) | AA46: N/T : 특수상황/실패 조건 필요(조건)
B47: TC_MAP_0018 | C47: Map | D47: Common | E47: 신약관 동의 | F47: 신약관 동의 | G47: KR, EU | I47: 5 | J47: 1. 차주/피공유자 모두 신약관 미동의 상태 | L47: 1. 피공유자 Map 진입 2. [약관 확인] 버튼 선택 3. 신약관 동의 프로세스 진행 4. 신약관 동의 완료 5. 팝업 내 [확인] 버튼 선택 | M47: 1. 팝업 닫힘 | N47: =IF(COUNTIF(P47:W47,"F")>=1,"FAIL",(IF(COUNTIF(P47:W47,"P")>=1,"PASS",(IF(COUNTIF(P47:W47,"N/T")>=1,"N/T",(IF(COUNTIF(P47:W47,"N/A")>=1,"N/A","-"))))))) | O47: =IF(COUNTIF(P47:Q47,"F")>=1,"FAIL",(IF(COUNTIF(P47:Q47,"P")>=1,"PASS",(IF(COUNTIF(P47:Q47,"N/T")>=1,"N/T",(IF(COUNTIF(P47:Q47,"N/A")>=1,"N/A","-"))))))) | P47: N/T | Q47: N/T | R47: =IF(COUNTIF(S47:T47,"F")>=1,"FAIL",(IF(COUNTIF(S47:T47,"P")>=1,"PASS",(IF(COUNTIF(S47:T47,"N/T")>=1,"N/T",(IF(COUNTIF(S47:T47,"N/A")>=1,"N/A","-"))))))) | S47: N/T | T47: N/T | U47: =IF(COUNTIF(V47:W47,"F")>=1,"FAIL",(IF(COUNTIF(V47:W47,"P")>=1,"PASS",(IF(COUNTIF(V47:W47,"N/T")>=1,"N/T",(IF(COUNTIF(V47:W47,"N/A")>=1,"N/A","-"))))))) | V47: N/T | W47: N/T | Z47: (공통) 신약관 확인 불가(N/T) | AA47: N/T : 특수상황/실패 조건 필요(조건)
B48: TC_MAP_0019 | C48: Map | D48: Common | E48: Block case | F48: Block case | G48: KR, EU | I48: 5 | J48: 1. API 호출 실패 또는 API 응답값이 없는 경우 | L48: 1. Map 진입 2. 화면 확인 | M48: 1. Block 화면 노출 (ic) 지도 오류 안내 지도를 표시하지 못했습니다. 다시 시도해 주세요. [다시 시도] | N48: =IF(COUNTIF(P48:W48,"F")>=1,"FAIL",(IF(COUNTIF(P48:W48,"P")>=1,"PASS",(IF(COUNTIF(P48:W48,"N/T")>=1,"N/T",(IF(COUNTIF(P48:W48,"N/A")>=1,"N/A","-"))))))) | O48: =IF(COUNTIF(P48:Q48,"F")>=1,"FAIL",(IF(COUNTIF(P48:Q48,"P")>=1,"PASS",(IF(COUNTIF(P48:Q48,"N/T")>=1,"N/T",(IF(COUNTIF(P48:Q48,"N/A")>=1,"N/A","-"))))))) | P48: N/T | Q48: N/T | R48: =IF(COUNTIF(S48:T48,"F")>=1,"FAIL",(IF(COUNTIF(S48:T48,"P")>=1,"PASS",(IF(COUNTIF(S48:T48,"N/T")>=1,"N/T",(IF(COUNTIF(S48:T48,"N/A")>=1,"N/A","-"))))))) | S48: N/T | T48: N/T | U48: =IF(COUNTIF(V48:W48,"F")>=1,"FAIL",(IF(COUNTIF(V48:W48,"P")>=1,"PASS",(IF(COUNTIF(V48:W48,"N/T")>=1,"N/T",(IF(COUNTIF(V48:W48,"N/A")>=1,"N/A","-"))))))) | V48: N/T | W48: N/T | Z48: (공통) 신약관 확인 불가(N/T) | AA48: N/T : 특수상황/실패 조건 필요(조건)
B49: TC_MAP_0020 | C49: Map | D49: Common | E49: Block case | F49: Block case | G49: KR, EU | I49: 5 | J49: 1. API 호출 실패 또는 API 응답값이 없는 경우 | L49: 1. Map 진입 2. 화면 확인 3. [다시 시도] 버튼 선택 | M49: 1. API 호출 재실행 | N49: =IF(COUNTIF(P49:W49,"F")>=1,"FAIL",(IF(COUNTIF(P49:W49,"P")>=1,"PASS",(IF(COUNTIF(P49:W49,"N/T")>=1,"N/T",(IF(COUNTIF(P49:W49,"N/A")>=1,"N/A","-"))))))) | O49: =IF(COUNTIF(P49:Q49,"F")>=1,"FAIL",(IF(COUNTIF(P49:Q49,"P")>=1,"PASS",(IF(COUNTIF(P49:Q49,"N/T")>=1,"N/T",(IF(COUNTIF(P49:Q49,"N/A")>=1,"N/A","-"))))))) | P49: N/T | Q49: N/T | R49: =IF(COUNTIF(S49:T49,"F")>=1,"FAIL",(IF(COUNTIF(S49:T49,"P")>=1,"PASS",(IF(COUNTIF(S49:T49,"N/T")>=1,"N/T",(IF(COUNTIF(S49:T49,"N/A")>=1,"N/A","-"))))))) | S49: N/T | T49: N/T | U49: =IF(COUNTIF(V49:W49,"F")>=1,"FAIL",(IF(COUNTIF(V49:W49,"P")>=1,"PASS",(IF(COUNTIF(V49:W49,"N/T")>=1,"N/T",(IF(COUNTIF(V49:W49,"N/A")>=1,"N/A","-"))))))) | V49: N/T | W49: N/T | Z49: (공통) 신약관 확인 불가(N/T) | AA49: N/T : 특수상황/실패 조건 필요(조건)
B50: TC_MAP_0021 | C50: Map | D50: Common | E50: Block case | F50: Block case | G50: EU, KR, NA | I50: 5 | J50: 1. 비정상 이용자 (예. 미터링) 서비스 이용에 제한이 걸린 상태 (BK01, BK02, S504) | L50: 1. Map 진입 | M50: 1. block Case 화면 노출된다. Title [아이콘] {CCS_Service} 이용 안내 서비스 운영 정책에 따라 현재 접근이 제한되었습니다. * 자세한 사유를 확인하거나, 해제를 요청하려면 고객센터:{%s}로 문의해. 주세요. | N50: =IF(COUNTIF(P50:W50,"F")>=1,"FAIL",(IF(COUNTIF(P50:W50,"P")>=1,"PASS",(IF(COUNTIF(P50:W50,"N/T")>=1,"N/T",(IF(COUNTIF(P50:W50,"N/A")>=1,"N/A","-"))))))) | O50: =IF(COUNTIF(P50:Q50,"F")>=1,"FAIL",(IF(COUNTIF(P50:Q50,"P")>=1,"PASS",(IF(COUNTIF(P50:Q50,"N/T")>=1,"N/T",(IF(COUNTIF(P50:Q50,"N/A")>=1,"N/A","-"))))))) | P50: N/T | Q50: N/T | R50: =IF(COUNTIF(S50:T50,"F")>=1,"FAIL",(IF(COUNTIF(S50:T50,"P")>=1,"PASS",(IF(COUNTIF(S50:T50,"N/T")>=1,"N/T",(IF(COUNTIF(S50:T50,"N/A")>=1,"N/A","-"))))))) | S50: N/T | T50: N/T | U50: =IF(COUNTIF(V50:W50,"F")>=1,"FAIL",(IF(COUNTIF(V50:W50,"P")>=1,"PASS",(IF(COUNTIF(V50:W50,"N/T")>=1,"N/T",(IF(COUNTIF(V50:W50,"N/A")>=1,"N/A","-"))))))) | V50: N/T | W50: N/T | Z50: (공통) 미터링 상태 필요(N/T) | AA50: N/T : 특수상황/실패 조건 필요(조건)
B51: TC_MAP_0022 | C51: Map | D51: Common | E51: 지도 마커 | F51: 지도 마커 | G51: KR, EU, NA | I51: 4 | J51: 1. 프로필 등록 | L51: 1. Map 진입 2. 우리집, 사무실, 즐겨찾기1, 등록지, 즐겨찾는 충전소를 같은 POI로 등록 3. 즐겨찾기2, 즐겨찾기3은 2번에서 추가한 POI와 가까운 위치로 각각 다른 POI 등록 4. 메인 지도 내 마커 우선 순위 비교 | M51: 1. 마커끼리 겹쳐있을 때 아래 우선 순위에 따라 노출 - 우리집 (우리집 마커) - 사무실 (사무실 마커) - 즐겨찾기 1 (핀마커) - 즐겨찾기 2 (핀마커) - 즐겨찾기 3 (핀마커) - 등록지 (별 마커) - 즐겨찾는 충전소 (즐겨찾는 충전소 마커) - 일반 or 주변 POI 마커 | N51: =IF(COUNTIF(P51:W51,"F")>=1,"FAIL",(IF(COUNTIF(P51:W51,"P")>=1,"PASS",(IF(COUNTIF(P51:W51,"N/T")>=1,"N/T",(IF(COUNTIF(P51:W51,"N/A")>=1,"N/A","-"))))))) | O51: =IF(COUNTIF(P51:Q51,"F")>=1,"FAIL",(IF(COUNTIF(P51:Q51,"P")>=1,"PASS",(IF(COUNTIF(P51:Q51,"N/T")>=1,"N/T",(IF(COUNTIF(P51:Q51,"N/A")>=1,"N/A","-"))))))) | P51: P | Q51: P | R51: =IF(COUNTIF(S51:T51,"F")>=1,"FAIL",(IF(COUNTIF(S51:T51,"P")>=1,"PASS",(IF(COUNTIF(S51:T51,"N/T")>=1,"N/T",(IF(COUNTIF(S51:T51,"N/A")>=1,"N/A","-"))))))) | S51: P | T51: P | U51: =IF(COUNTIF(V51:W51,"F")>=1,"FAIL",(IF(COUNTIF(V51:W51,"P")>=1,"PASS",(IF(COUNTIF(V51:W51,"N/T")>=1,"N/T",(IF(COUNTIF(V51:W51,"N/A")>=1,"N/A","-"))))))) | V51: P | W51: P | X51: SPAQA-23297 SPAQA-24173 SPAQA-25319 SPAQA-25446 SPAQA-25652
B52: TC_MAP_0023 | C52: Map | D52: Common | E52: 지도 마커 | F52: 지도 마커 | G52: KR, EU, NA | I52: 4 | J52: 1. 프로필 등록 | L52: 1. Map 진입 2. 메인 지도에서 롱 탭 실행 3. 메인 지도 내 마커 우선 순위 비교 | M52: 1. 롱 탭 마커가 즐겨찾기 마커보다 우선적으로 노출 (=겹쳐있을 때 롱 탭 마커가 위에 있음) | N52: =IF(COUNTIF(P52:W52,"F")>=1,"FAIL",(IF(COUNTIF(P52:W52,"P")>=1,"PASS",(IF(COUNTIF(P52:W52,"N/T")>=1,"N/T",(IF(COUNTIF(P52:W52,"N/A")>=1,"N/A","-"))))))) | O52: =IF(COUNTIF(P52:Q52,"F")>=1,"FAIL",(IF(COUNTIF(P52:Q52,"P")>=1,"PASS",(IF(COUNTIF(P52:Q52,"N/T")>=1,"N/T",(IF(COUNTIF(P52:Q52,"N/A")>=1,"N/A","-"))))))) | P52: P | Q52: P | R52: =IF(COUNTIF(S52:T52,"F")>=1,"FAIL",(IF(COUNTIF(S52:T52,"P")>=1,"PASS",(IF(COUNTIF(S52:T52,"N/T")>=1,"N/T",(IF(COUNTIF(S52:T52,"N/A")>=1,"N/A","-"))))))) | S52: P | T52: P | U52: =IF(COUNTIF(V52:W52,"F")>=1,"FAIL",(IF(COUNTIF(V52:W52,"P")>=1,"PASS",(IF(COUNTIF(V52:W52,"N/T")>=1,"N/T",(IF(COUNTIF(V52:W52,"N/A")>=1,"N/A","-"))))))) | V52: P | W52: P | X52: SPAQA-25185
B53: TC_MAP_0024 | C53: Map | D53: Common | E53: 지도 마커 | F53: 지도 마커 | G53: KR, EU, NA | I53: 4 | J53: 1. 프로필 등록 | L53: 1. Map 진입 2. 임의의 검색 실행(통합 검색 or 주변 검색) 3. 검색 결과 화면에서 롱 탭 실행 4. 검색 결과 화면 내 마커 우선 순위 비교 | M53: 1. 롱 탭 마커가 다른 검색 결과 마커(일반 속성의 POI / 주변 검색 속성의 POI 등)보다 우선적으로 노출 (=겹쳐있을 때 롱 탭 마커가 위에 있음) | N53: =IF(COUNTIF(P53:W53,"F")>=1,"FAIL",(IF(COUNTIF(P53:W53,"P")>=1,"PASS",(IF(COUNTIF(P53:W53,"N/T")>=1,"N/T",(IF(COUNTIF(P53:W53,"N/A")>=1,"N/A","-"))))))) | O53: =IF(COUNTIF(P53:Q53,"F")>=1,"FAIL",(IF(COUNTIF(P53:Q53,"P")>=1,"PASS",(IF(COUNTIF(P53:Q53,"N/T")>=1,"N/T",(IF(COUNTIF(P53:Q53,"N/A")>=1,"N/A","-"))))))) | P53: P | Q53: P | R53: =IF(COUNTIF(S53:T53,"F")>=1,"FAIL",(IF(COUNTIF(S53:T53,"P")>=1,"PASS",(IF(COUNTIF(S53:T53,"N/T")>=1,"N/T",(IF(COUNTIF(S53:T53,"N/A")>=1,"N/A","-"))))))) | S53: P | T53: P | U53: =IF(COUNTIF(V53:W53,"F")>=1,"FAIL",(IF(COUNTIF(V53:W53,"P")>=1,"PASS",(IF(COUNTIF(V53:W53,"N/T")>=1,"N/T",(IF(COUNTIF(V53:W53,"N/A")>=1,"N/A","-"))))))) | V53: P | W53: P
B54: TC_MAP_0025 | C54: Map | D54: Common | E54: 지도 마커 | F54: 지도 마커 | G54: KR, EU, NA | I54: 4 | L54: 1. Map 진입 2. 경로 탐색 버튼 선택 3. 비어 있는 검색 필드 선택 4. [지도에서 선택] 버튼 선택 5. 지도에서 선택 화면 내 마커 우선 순위 비교 | M54: 1. 마커끼리 겹쳐있을 때 아래 우선 순위에 따라 노출 1) 지도 선택 마커 2) 내 위치 | N54: =IF(COUNTIF(P54:W54,"F")>=1,"FAIL",(IF(COUNTIF(P54:W54,"P")>=1,"PASS",(IF(COUNTIF(P54:W54,"N/T")>=1,"N/T",(IF(COUNTIF(P54:W54,"N/A")>=1,"N/A","-"))))))) | O54: =IF(COUNTIF(P54:Q54,"F")>=1,"FAIL",(IF(COUNTIF(P54:Q54,"P")>=1,"PASS",(IF(COUNTIF(P54:Q54,"N/T")>=1,"N/T",(IF(COUNTIF(P54:Q54,"N/A")>=1,"N/A","-"))))))) | P54: P | Q54: P | R54: =IF(COUNTIF(S54:T54,"F")>=1,"FAIL",(IF(COUNTIF(S54:T54,"P")>=1,"PASS",(IF(COUNTIF(S54:T54,"N/T")>=1,"N/T",(IF(COUNTIF(S54:T54,"N/A")>=1,"N/A","-"))))))) | S54: P | T54: P | U54: =IF(COUNTIF(V54:W54,"F")>=1,"FAIL",(IF(COUNTIF(V54:W54,"P")>=1,"PASS",(IF(COUNTIF(V54:W54,"N/T")>=1,"N/T",(IF(COUNTIF(V54:W54,"N/A")>=1,"N/A","-"))))))) | V54: P | W54: P
B55: TC_MAP_0026 | C55: Map | D55: Common | E55: 지도 마커 | F55: 지도 마커 | G55: KR, EU, NA | I55: 4 | L55: 1. Map 진입 2. 경로 탐색 버튼 선택 3. + 버튼(=경유지 추가 버튼) 선택 4. 출발지, 경유지, 도착지에 임의의 POI 지정 후 [확인] 버튼 선택 5. 경로 탐색 결과 화면 내 마커 우선 순위 확인 | M55: 1. 마커끼리 겹쳐있을 때 아래 우선 순위에 따라 노출 1) 내 위치 2) 출발지 마커 3) 도착지 마커 4) 경유지 마커 (추천 충전소 마커 포함 - 경유지는 출발지에서 가까운 순이 우선) | N55: =IF(COUNTIF(P55:W55,"F")>=1,"FAIL",(IF(COUNTIF(P55:W55,"P")>=1,"PASS",(IF(COUNTIF(P55:W55,"N/T")>=1,"N/T",(IF(COUNTIF(P55:W55,"N/A")>=1,"N/A","-"))))))) | O55: =IF(COUNTIF(P55:Q55,"F")>=1,"FAIL",(IF(COUNTIF(P55:Q55,"P")>=1,"PASS",(IF(COUNTIF(P55:Q55,"N/T")>=1,"N/T",(IF(COUNTIF(P55:Q55,"N/A")>=1,"N/A","-"))))))) | P55: P | Q55: P | R55: =IF(COUNTIF(S55:T55,"F")>=1,"FAIL",(IF(COUNTIF(S55:T55,"P")>=1,"PASS",(IF(COUNTIF(S55:T55,"N/T")>=1,"N/T",(IF(COUNTIF(S55:T55,"N/A")>=1,"N/A","-"))))))) | S55: P | T55: P | U55: =IF(COUNTIF(V55:W55,"F")>=1,"FAIL",(IF(COUNTIF(V55:W55,"P")>=1,"PASS",(IF(COUNTIF(V55:W55,"N/T")>=1,"N/T",(IF(COUNTIF(V55:W55,"N/A")>=1,"N/A","-"))))))) | V55: P | W55: P | X55: SPAQA-18657 SPAQA-23061 SPAQA-24390 SPAQA-24604 SPAQA-25146 SPAQA-25478
B56: TC_MAP_0027 | C56: Map | D56: Common | E56: 지도 마커 | F56: 지도 마커 | G56: KR, EU, NA | I56: 5 | J56: 1. 프로필 등록 | L56: 1. 최종 목적지 알림 푸시 수신 후 앱에서 선택 2. 최종 목적지 안내 화면 표출 | M56: 1. 마커끼리 겹쳐있을 때 아래 우선 순위에 따라 노출 1) 내 위치 2) 내 차 위치 3) 최종 목적지 | N56: =IF(COUNTIF(P56:W56,"F")>=1,"FAIL",(IF(COUNTIF(P56:W56,"P")>=1,"PASS",(IF(COUNTIF(P56:W56,"N/T")>=1,"N/T",(IF(COUNTIF(P56:W56,"N/A")>=1,"N/A","-"))))))) | O56: =IF(COUNTIF(P56:Q56,"F")>=1,"FAIL",(IF(COUNTIF(P56:Q56,"P")>=1,"PASS",(IF(COUNTIF(P56:Q56,"N/T")>=1,"N/T",(IF(COUNTIF(P56:Q56,"N/A")>=1,"N/A","-"))))))) | P56: N/T | Q56: N/T | R56: =IF(COUNTIF(S56:T56,"F")>=1,"FAIL",(IF(COUNTIF(S56:T56,"P")>=1,"PASS",(IF(COUNTIF(S56:T56,"N/T")>=1,"N/T",(IF(COUNTIF(S56:T56,"N/A")>=1,"N/A","-"))))))) | S56: N/T | T56: N/T | U56: =IF(COUNTIF(V56:W56,"F")>=1,"FAIL",(IF(COUNTIF(V56:W56,"P")>=1,"PASS",(IF(COUNTIF(V56:W56,"N/T")>=1,"N/T",(IF(COUNTIF(V56:W56,"N/A")>=1,"N/A","-"))))))) | V56: N/T | W56: N/T | Z56: (공통) 내 위치 내 차 위치 겹치는 경우(N/T) | AA56: N/T : 특수상황/실패 조건 필요(조건) | AB56: 실차
B57: TC_MAP_0028 | C57: Map | D57: Common | E57: 지도 마커 | F57: 지도 마커 | G57: KR, EU, NA | I57: 4 | J57: 1. 프로필 등록 2. 동일한 위치를 즐겨찾기로 저장 할 경우 3. 발레 모드의 마커 우선 순위 | L57: 1. 발레모드 Map 진입 | M57: 1. 내 위치 2. 발레 차량 3. 발레 시작 4. 주차 위치 | N57: =IF(COUNTIF(P57:W57,"F")>=1,"FAIL",(IF(COUNTIF(P57:W57,"P")>=1,"PASS",(IF(COUNTIF(P57:W57,"N/T")>=1,"N/T",(IF(COUNTIF(P57:W57,"N/A")>=1,"N/A","-"))))))) | O57: =IF(COUNTIF(P57:Q57,"F")>=1,"FAIL",(IF(COUNTIF(P57:Q57,"P")>=1,"PASS",(IF(COUNTIF(P57:Q57,"N/T")>=1,"N/T",(IF(COUNTIF(P57:Q57,"N/A")>=1,"N/A","-"))))))) | P57: N/T | Q57: N/T | R57: =IF(COUNTIF(S57:T57,"F")>=1,"FAIL",(IF(COUNTIF(S57:T57,"P")>=1,"PASS",(IF(COUNTIF(S57:T57,"N/T")>=1,"N/T",(IF(COUNTIF(S57:T57,"N/A")>=1,"N/A","-"))))))) | S57: N/T | T57: N/T | U57: =IF(COUNTIF(V57:W57,"F")>=1,"FAIL",(IF(COUNTIF(V57:W57,"P")>=1,"PASS",(IF(COUNTIF(V57:W57,"N/T")>=1,"N/T",(IF(COUNTIF(V57:W57,"N/A")>=1,"N/A","-"))))))) | V57: N/T | W57: N/T | Z57: (공통) 차량 이동 위치 확인 불가로 인한(N/T) | AA57: N/T : 특수상황/실패 조건 필요(조건) | AB57: 실차
B58: TC_MAP_0029 | C58: Map | D58: Common | E58: 지도 마커 | F58: 지도 마커 | G58: KR, EU, NA | J58: 1. 프로필 등록 2. 동일한 위치를 즐겨찾기로 저장 할 경우 3. 지도 마커 전체 우선 순위 | L58: 1. Map 진입 | M58: - 지도 마커 우선 순위 1. 지도 선택 마커 2. 내 위치 마커 3. 내 차 위치 마커 4. Focus 상태의 마커 (선택 상태) 5. 롱탭 후 일반 마커 6. 검색 결과 마커 - 6-1) 일반 검색 POI 마커 6-2) 주변 검색 POI 마커 7. 출발지 마커 8. 공유차량 마커 (마커 겹치는 경우 번호 순서대로 우선순위 부여) (KR) 9 도착지 마커 10. 경유지 마커 (마커 겹치는 경우 출발지에서 가까운 순서대로 우선순위 부여) 10-1) 일반 경유지 마커 10-2) 추천 충전소 마커 11. 최종 목적지 마커 12. 발레 차량 마커 13. 발레 시작 마커 14. 주차 위치 마커 15. 즐겨찾기 마커 15-1) 즐겨찾는 등록지 마커 (‘우리집 - 사무실 - 즐겨찾기1 - 즐겨찾기2 - 즐겨찾기3’ 순) 15-2) 즐겨찾는 충전소 마커 (최신 등록한 장소의 마커를 최우선으로 표시) 15-3) 등록지 마커 (최신 등록한 장소의 마커를 최우선으로 표시 | N58: =IF(COUNTIF(P58:W58,"F")>=1,"FAIL",(IF(COUNTIF(P58:W58,"P")>=1,"PASS",(IF(COUNTIF(P58:W58,"N/T")>=1,"N/T",(IF(COUNTIF(P58:W58,"N/A")>=1,"N/A","-"))))))) | O58: =IF(COUNTIF(P58:Q58,"F")>=1,"FAIL",(IF(COUNTIF(P58:Q58,"P")>=1,"PASS",(IF(COUNTIF(P58:Q58,"N/T")>=1,"N/T",(IF(COUNTIF(P58:Q58,"N/A")>=1,"N/A","-"))))))) | P58: N/A | Q58: N/A | R58: =IF(COUNTIF(S58:T58,"F")>=1,"FAIL",(IF(COUNTIF(S58:T58,"P")>=1,"PASS",(IF(COUNTIF(S58:T58,"N/T")>=1,"N/T",(IF(COUNTIF(S58:T58,"N/A")>=1,"N/A","-"))))))) | S58: N/A | T58: N/A | U58: =IF(COUNTIF(V58:W58,"F")>=1,"FAIL",(IF(COUNTIF(V58:W58,"P")>=1,"PASS",(IF(COUNTIF(V58:W58,"N/T")>=1,"N/T",(IF(COUNTIF(V58:W58,"N/A")>=1,"N/A","-"))))))) | V58: N/A | W58: N/A | X58: SPAQA-15800 | Z58: 삭제 TC(N/A) | AA58: 사양 아님(N/A) | AB58: 삭제
B59: TC_MAP_0030 | C59: Map | D59: Common | E59: 지도 마커 | F59: 지도 마커 | G59: KR, EU | I59: 1 | J59: 1. 위치 서비스 on 상태 2. 내 위치 조회 가능 상태 | L59: 1. Map 탭 진입 2. 내 위치 마커 확인 | M59: 1. 내 위치 마커 노출된다. -Default로 삼각형 타입 제공 | N59: =IF(COUNTIF(P59:W59,"F")>=1,"FAIL",(IF(COUNTIF(P59:W59,"P")>=1,"PASS",(IF(COUNTIF(P59:W59,"N/T")>=1,"N/T",(IF(COUNTIF(P59:W59,"N/A")>=1,"N/A","-"))))))) | O59: =IF(COUNTIF(P59:Q59,"F")>=1,"FAIL",(IF(COUNTIF(P59:Q59,"P")>=1,"PASS",(IF(COUNTIF(P59:Q59,"N/T")>=1,"N/T",(IF(COUNTIF(P59:Q59,"N/A")>=1,"N/A","-"))))))) | P59: P | Q59: P | R59: =IF(COUNTIF(S59:T59,"F")>=1,"FAIL",(IF(COUNTIF(S59:T59,"P")>=1,"PASS",(IF(COUNTIF(S59:T59,"N/T")>=1,"N/T",(IF(COUNTIF(S59:T59,"N/A")>=1,"N/A","-"))))))) | S59: P | T59: P | U59: =IF(COUNTIF(V59:W59,"F")>=1,"FAIL",(IF(COUNTIF(V59:W59,"P")>=1,"PASS",(IF(COUNTIF(V59:W59,"N/T")>=1,"N/T",(IF(COUNTIF(V59:W59,"N/A")>=1,"N/A","-"))))))) | V59: P | W59: P | X59: SPAQA-16850 SPAQA-18993 SPAQA-25166 SPAQA-26122 | AB59: Sanity, CheckList
B60: TC_MAP_0031 | C60: Map | D60: Common | E60: 지도 마커 | F60: 지도 마커 | G60: KR, EU | I60: 1 | J60: 1. 내 차 위치 조회 상태 | L60: 1. Map 탭 진입 2. 내 차 위치 마커 확인 | M60: 1. 내 차 위치 마커 노출된다. | N60: =IF(COUNTIF(P60:W60,"F")>=1,"FAIL",(IF(COUNTIF(P60:W60,"P")>=1,"PASS",(IF(COUNTIF(P60:W60,"N/T")>=1,"N/T",(IF(COUNTIF(P60:W60,"N/A")>=1,"N/A","-"))))))) | O60: =IF(COUNTIF(P60:Q60,"F")>=1,"FAIL",(IF(COUNTIF(P60:Q60,"P")>=1,"PASS",(IF(COUNTIF(P60:Q60,"N/T")>=1,"N/T",(IF(COUNTIF(P60:Q60,"N/A")>=1,"N/A","-"))))))) | P60: P | Q60: P | R60: =IF(COUNTIF(S60:T60,"F")>=1,"FAIL",(IF(COUNTIF(S60:T60,"P")>=1,"PASS",(IF(COUNTIF(S60:T60,"N/T")>=1,"N/T",(IF(COUNTIF(S60:T60,"N/A")>=1,"N/A","-"))))))) | S60: P | T60: P | U60: =IF(COUNTIF(V60:W60,"F")>=1,"FAIL",(IF(COUNTIF(V60:W60,"P")>=1,"PASS",(IF(COUNTIF(V60:W60,"N/T")>=1,"N/T",(IF(COUNTIF(V60:W60,"N/A")>=1,"N/A","-"))))))) | V60: P | W60: P | X60: SPAQA-14959 SPAQA-19804 | AB60: Sanity, CheckList
A61: Q_013 | B61: TC_MAP_0032 | C61: Map | D61: Common | E61: 지도 마커 | F61: 지도 마커 | G61: KR, EU | I61: 5 | J61: 1. 내 차 위치 미조회 상태 | L61: 1. Map 탭 진입 2. 내 차 위치 마커 확인 | M61: 1. 내 차 위치 마커 미노출된다. | N61: =IF(COUNTIF(P61:W61,"F")>=1,"FAIL",(IF(COUNTIF(P61:W61,"P")>=1,"PASS",(IF(COUNTIF(P61:W61,"N/T")>=1,"N/T",(IF(COUNTIF(P61:W61,"N/A")>=1,"N/A","-"))))))) | O61: =IF(COUNTIF(P61:Q61,"F")>=1,"FAIL",(IF(COUNTIF(P61:Q61,"P")>=1,"PASS",(IF(COUNTIF(P61:Q61,"N/T")>=1,"N/T",(IF(COUNTIF(P61:Q61,"N/A")>=1,"N/A","-"))))))) | P61: P | Q61: P | R61: =IF(COUNTIF(S61:T61,"F")>=1,"FAIL",(IF(COUNTIF(S61:T61,"P")>=1,"PASS",(IF(COUNTIF(S61:T61,"N/T")>=1,"N/T",(IF(COUNTIF(S61:T61,"N/A")>=1,"N/A","-"))))))) | S61: P | T61: P | U61: =IF(COUNTIF(V61:W61,"F")>=1,"FAIL",(IF(COUNTIF(V61:W61,"P")>=1,"PASS",(IF(COUNTIF(V61:W61,"N/T")>=1,"N/T",(IF(COUNTIF(V61:W61,"N/A")>=1,"N/A","-"))))))) | V61: P | W61: P | X61: SPAQA-23598
B62: TC_MAP_0033 | C62: Map | D62: Common | E62: 지도 마커 | F62: 지도 마커 | G62: KR, EU | I62: 5 | J62: 1. 위치 서비스 off or 내 위치 조회 불가 | L62: 1. Map 탭 진입 2. 내 위치 마커 확인 | M62: 1. 내 위치 마커 미노출 된다 | N62: =IF(COUNTIF(P62:W62,"F")>=1,"FAIL",(IF(COUNTIF(P62:W62,"P")>=1,"PASS",(IF(COUNTIF(P62:W62,"N/T")>=1,"N/T",(IF(COUNTIF(P62:W62,"N/A")>=1,"N/A","-"))))))) | O62: =IF(COUNTIF(P62:Q62,"F")>=1,"FAIL",(IF(COUNTIF(P62:Q62,"P")>=1,"PASS",(IF(COUNTIF(P62:Q62,"N/T")>=1,"N/T",(IF(COUNTIF(P62:Q62,"N/A")>=1,"N/A","-"))))))) | P62: P | Q62: P | R62: =IF(COUNTIF(S62:T62,"F")>=1,"FAIL",(IF(COUNTIF(S62:T62,"P")>=1,"PASS",(IF(COUNTIF(S62:T62,"N/T")>=1,"N/T",(IF(COUNTIF(S62:T62,"N/A")>=1,"N/A","-"))))))) | S62: P | T62: P | U62: =IF(COUNTIF(V62:W62,"F")>=1,"FAIL",(IF(COUNTIF(V62:W62,"P")>=1,"PASS",(IF(COUNTIF(V62:W62,"N/T")>=1,"N/T",(IF(COUNTIF(V62:W62,"N/A")>=1,"N/A","-"))))))) | V62: P | W62: P
A63: b_001 | B63: TC_MAP_0034 | C63: Map | D63: Common | E63: 지도 마커 | F63: 지도 마커 | G63: KR, EU | I63: 1 | J63: 1. 내 차 위치 조회 상태 | L63: 1. Map 탭 진입 2. 노출되는 내 차 위치 마커 선택 | M63: 1. 내 차 위치 화면으로 이동 | N63: =IF(COUNTIF(P63:W63,"F")>=1,"FAIL",(IF(COUNTIF(P63:W63,"P")>=1,"PASS",(IF(COUNTIF(P63:W63,"N/T")>=1,"N/T",(IF(COUNTIF(P63:W63,"N/A")>=1,"N/A","-"))))))) | O63: =IF(COUNTIF(P63:Q63,"F")>=1,"FAIL",(IF(COUNTIF(P63:Q63,"P")>=1,"PASS",(IF(COUNTIF(P63:Q63,"N/T")>=1,"N/T",(IF(COUNTIF(P63:Q63,"N/A")>=1,"N/A","-"))))))) | P63: P | Q63: P | R63: =IF(COUNTIF(S63:T63,"F")>=1,"FAIL",(IF(COUNTIF(S63:T63,"P")>=1,"PASS",(IF(COUNTIF(S63:T63,"N/T")>=1,"N/T",(IF(COUNTIF(S63:T63,"N/A")>=1,"N/A","-"))))))) | S63: P | T63: P | U63: =IF(COUNTIF(V63:W63,"F")>=1,"FAIL",(IF(COUNTIF(V63:W63,"P")>=1,"PASS",(IF(COUNTIF(V63:W63,"N/T")>=1,"N/T",(IF(COUNTIF(V63:W63,"N/A")>=1,"N/A","-"))))))) | V63: P | W63: P | X63: SPAQA-22475 SPAQA-24986 | AB63: Sanity, CheckList
A64: b_004 | B64: TC_MAP_0035 | C64: Map | D64: Common | E64: 지도 마커 | F64: 지도 마커 | G64: KR, EU | I64: 4 | J64: 1. 내 차 위치 조회 상태 | L64: 1. Map 탭 진입 2. 노출되는 내 차 위치 마커 외 지도 영역 롱 탭 또는 주기 아이콘 선택 | M64: 1. 내 차 위치 마커 사라지고 해당 POI마커 및 간단 상세 화면 표시된다. | N64: =IF(COUNTIF(P64:W64,"F")>=1,"FAIL",(IF(COUNTIF(P64:W64,"P")>=1,"PASS",(IF(COUNTIF(P64:W64,"N/T")>=1,"N/T",(IF(COUNTIF(P64:W64,"N/A")>=1,"N/A","-"))))))) | O64: =IF(COUNTIF(P64:Q64,"F")>=1,"FAIL",(IF(COUNTIF(P64:Q64,"P")>=1,"PASS",(IF(COUNTIF(P64:Q64,"N/T")>=1,"N/T",(IF(COUNTIF(P64:Q64,"N/A")>=1,"N/A","-"))))))) | P64: P | Q64: P | R64: =IF(COUNTIF(S64:T64,"F")>=1,"FAIL",(IF(COUNTIF(S64:T64,"P")>=1,"PASS",(IF(COUNTIF(S64:T64,"N/T")>=1,"N/T",(IF(COUNTIF(S64:T64,"N/A")>=1,"N/A","-"))))))) | S64: P | T64: P | U64: =IF(COUNTIF(V64:W64,"F")>=1,"FAIL",(IF(COUNTIF(V64:W64,"P")>=1,"PASS",(IF(COUNTIF(V64:W64,"N/T")>=1,"N/T",(IF(COUNTIF(V64:W64,"N/A")>=1,"N/A","-"))))))) | V64: P | W64: P | X64: SPAQA-17429
A65: b_005 | B65: TC_MAP_0036 | C65: Map | D65: Common | E65: 지도 마커 | F65: 지도 마커 | G65: KR, EU | I65: 1 | J65: 1. 프로필 등록 되어 있는 경우 2. 즐겨찾는 등록지 (우리집/ 사무실) 등록되어 있는 경우 | L65: 1. Map 탭 진입 2. 메인 지도 내 우리집/사무실 마커 확인 | M65: 1. 우리집 / 사무실 마커 노출된다. | N65: =IF(COUNTIF(P65:W65,"F")>=1,"FAIL",(IF(COUNTIF(P65:W65,"P")>=1,"PASS",(IF(COUNTIF(P65:W65,"N/T")>=1,"N/T",(IF(COUNTIF(P65:W65,"N/A")>=1,"N/A","-"))))))) | O65: =IF(COUNTIF(P65:Q65,"F")>=1,"FAIL",(IF(COUNTIF(P65:Q65,"P")>=1,"PASS",(IF(COUNTIF(P65:Q65,"N/T")>=1,"N/T",(IF(COUNTIF(P65:Q65,"N/A")>=1,"N/A","-"))))))) | P65: P | Q65: P | R65: =IF(COUNTIF(S65:T65,"F")>=1,"FAIL",(IF(COUNTIF(S65:T65,"P")>=1,"PASS",(IF(COUNTIF(S65:T65,"N/T")>=1,"N/T",(IF(COUNTIF(S65:T65,"N/A")>=1,"N/A","-"))))))) | S65: P | T65: P | U65: =IF(COUNTIF(V65:W65,"F")>=1,"FAIL",(IF(COUNTIF(V65:W65,"P")>=1,"PASS",(IF(COUNTIF(V65:W65,"N/T")>=1,"N/T",(IF(COUNTIF(V65:W65,"N/A")>=1,"N/A","-"))))))) | V65: P | W65: P | X65: SPAQA-22530 SPAQA-22050 | AB65: Sanity, CheckList
A66: b_006 | B66: TC_MAP_0037 | C66: Map | D66: Common | E66: 지도 마커 | F66: 지도 마커 | G66: KR, EU | I66: 1 | J66: 1. 프로필 등록 되어 있는 경우 2. 즐겨찾는 등록지 (즐겨찾기 1~3) 등록 되어 있는 경우 | L66: 1. Map 탭 진입 2. 하단 드로어 영역 즐겨찾기 탭 선택 3. 등록된 즐겨찾는 등록지(즐겨찾기 1~3) 선택 4. 노출되는 지도 확인 | M66: 1. 해당 즐겨찾는 등록지의 일반 POI 속성 및 선택 상태의 마커가 노출된다. 2. 해당 즐겨찾는 등록지의 간단 상세 화면 노출된다. | N66: =IF(COUNTIF(P66:W66,"F")>=1,"FAIL",(IF(COUNTIF(P66:W66,"P")>=1,"PASS",(IF(COUNTIF(P66:W66,"N/T")>=1,"N/T",(IF(COUNTIF(P66:W66,"N/A")>=1,"N/A","-"))))))) | O66: =IF(COUNTIF(P66:Q66,"F")>=1,"FAIL",(IF(COUNTIF(P66:Q66,"P")>=1,"PASS",(IF(COUNTIF(P66:Q66,"N/T")>=1,"N/T",(IF(COUNTIF(P66:Q66,"N/A")>=1,"N/A","-"))))))) | P66: P | Q66: P | R66: =IF(COUNTIF(S66:T66,"F")>=1,"FAIL",(IF(COUNTIF(S66:T66,"P")>=1,"PASS",(IF(COUNTIF(S66:T66,"N/T")>=1,"N/T",(IF(COUNTIF(S66:T66,"N/A")>=1,"N/A","-"))))))) | S66: P | T66: P | U66: =IF(COUNTIF(V66:W66,"F")>=1,"FAIL",(IF(COUNTIF(V66:W66,"P")>=1,"PASS",(IF(COUNTIF(V66:W66,"N/T")>=1,"N/T",(IF(COUNTIF(V66:W66,"N/A")>=1,"N/A","-"))))))) | V66: P | W66: P | X66: SPAQA-17208 SPAQA-18913 SPAQA-19618 | AB66: Sanity, CheckList
A67: b_007 | B67: TC_MAP_0038 | C67: Map | D67: Common | E67: 지도 마커 | F67: 지도 마커 | G67: KR, EU | I67: 1 | J67: 1. 등록지 등록 되어 있는 경우 | L67: 1. Map 탭 진입 2. 하단 드로어 영역 즐겨찾기 탭 선택 3. 등록된 등록지 선택 4. 노출되는 지도 확인 | M67: 1. 해당 등록지의 일반 POI 속성 및 선택 상태의 마커가 노출된다. 2. 해당 등록지의 간단 상세 화면 노출된다. | N67: =IF(COUNTIF(P67:W67,"F")>=1,"FAIL",(IF(COUNTIF(P67:W67,"P")>=1,"PASS",(IF(COUNTIF(P67:W67,"N/T")>=1,"N/T",(IF(COUNTIF(P67:W67,"N/A")>=1,"N/A","-"))))))) | O67: =IF(COUNTIF(P67:Q67,"F")>=1,"FAIL",(IF(COUNTIF(P67:Q67,"P")>=1,"PASS",(IF(COUNTIF(P67:Q67,"N/T")>=1,"N/T",(IF(COUNTIF(P67:Q67,"N/A")>=1,"N/A","-"))))))) | P67: P | Q67: P | R67: =IF(COUNTIF(S67:T67,"F")>=1,"FAIL",(IF(COUNTIF(S67:T67,"P")>=1,"PASS",(IF(COUNTIF(S67:T67,"N/T")>=1,"N/T",(IF(COUNTIF(S67:T67,"N/A")>=1,"N/A","-"))))))) | S67: P | T67: P | U67: =IF(COUNTIF(V67:W67,"F")>=1,"FAIL",(IF(COUNTIF(V67:W67,"P")>=1,"PASS",(IF(COUNTIF(V67:W67,"N/T")>=1,"N/T",(IF(COUNTIF(V67:W67,"N/A")>=1,"N/A","-"))))))) | V67: P | W67: P | X67: SPAQA-18913 SPAQA-20516 SPAQA-17647 SPAQA-20386 | AB67: Sanity, CheckList
A68: b_008 | B68: TC_MAP_0039 | C68: Map | D68: Common | E68: 지도 마커 | F68: 지도 마커 | G68: KR, EU | I68: 1 | K68: 1. EV 차량 | L68: 1. Map 탭 진입 2. 상단 주변 검색 chip 중 전기차 충전소 선택 3. 노출되는 검색 결과 페이지 확인 | M68: 1. 미선택 상태의 충전소 POI마커 노출된다. 충전소 POI 마커 - 사용 가능 (급속/완속) - 사용 중 (급속/완속) - 불가능 - 모름 | N68: =IF(COUNTIF(P68:W68,"F")>=1,"FAIL",(IF(COUNTIF(P68:W68,"P")>=1,"PASS",(IF(COUNTIF(P68:W68,"N/T")>=1,"N/T",(IF(COUNTIF(P68:W68,"N/A")>=1,"N/A","-"))))))) | O68: =IF(COUNTIF(P68:Q68,"F")>=1,"FAIL",(IF(COUNTIF(P68:Q68,"P")>=1,"PASS",(IF(COUNTIF(P68:Q68,"N/T")>=1,"N/T",(IF(COUNTIF(P68:Q68,"N/A")>=1,"N/A","-"))))))) | P68: P | Q68: P | R68: =IF(COUNTIF(S68:T68,"F")>=1,"FAIL",(IF(COUNTIF(S68:T68,"P")>=1,"PASS",(IF(COUNTIF(S68:T68,"N/T")>=1,"N/T",(IF(COUNTIF(S68:T68,"N/A")>=1,"N/A","-"))))))) | S68: P | T68: P | U68: =IF(COUNTIF(V68:W68,"F")>=1,"FAIL",(IF(COUNTIF(V68:W68,"P")>=1,"PASS",(IF(COUNTIF(V68:W68,"N/T")>=1,"N/T",(IF(COUNTIF(V68:W68,"N/A")>=1,"N/A","-"))))))) | V68: P | W68: P | X68: SPAQA-16702 SPAQA-16477 SPAQA-17406 SPAQA-17421 SPAQA-14718 SPAQA-19890 | AB68: Sanity, CheckList
A69: b_009 | B69: TC_MAP_0040 | C69: Map | D69: Common | E69: 지도 마커 | F69: 지도 마커 | G69: KR, EU | I69: 1 | K69: 1. EV 차량 | L69: 1. Map 탭 진입 2. 상단 주변 검색 chip 중 전기차 충전소 선택 3. 노출되는 검색 결과 페이지 내 마커 선택 시 확인 | M69: 1. 선택 상태의 충전소 POI마커 노출된다. 충전소 POI 마커 - 사용 가능 (급속/완속) 아이콘 (n/10) - 사용 중 (급속/완속) 아이콘 (n/10) - 불가능 아이콘(충전 불가) - 모름 아이콘(알 수 없음) | N69: =IF(COUNTIF(P69:W69,"F")>=1,"FAIL",(IF(COUNTIF(P69:W69,"P")>=1,"PASS",(IF(COUNTIF(P69:W69,"N/T")>=1,"N/T",(IF(COUNTIF(P69:W69,"N/A")>=1,"N/A","-"))))))) | O69: =IF(COUNTIF(P69:Q69,"F")>=1,"FAIL",(IF(COUNTIF(P69:Q69,"P")>=1,"PASS",(IF(COUNTIF(P69:Q69,"N/T")>=1,"N/T",(IF(COUNTIF(P69:Q69,"N/A")>=1,"N/A","-"))))))) | P69: P | Q69: P | R69: =IF(COUNTIF(S69:T69,"F")>=1,"FAIL",(IF(COUNTIF(S69:T69,"P")>=1,"PASS",(IF(COUNTIF(S69:T69,"N/T")>=1,"N/T",(IF(COUNTIF(S69:T69,"N/A")>=1,"N/A","-"))))))) | S69: P | T69: P | U69: =IF(COUNTIF(V69:W69,"F")>=1,"FAIL",(IF(COUNTIF(V69:W69,"P")>=1,"PASS",(IF(COUNTIF(V69:W69,"N/T")>=1,"N/T",(IF(COUNTIF(V69:W69,"N/A")>=1,"N/A","-"))))))) | V69: P | W69: P | X69: SPAQA-1658 SPAQA-19890 | AB69: Sanity, CheckList
A70: b_010 | B70: TC_MAP_0041 | C70: Map | D70: Common | E70: 지도 마커 | F70: 지도 마커 | G70: KR, EU | I70: 1 | L70: 1. Map 진입 2. 장소/주소 검색 입력창 선택 3. 임의의 장소/주소 검색 4. 결과 화면 확인 | M70: 1. 일반 속성의 마커 표출 | N70: =IF(COUNTIF(P70:W70,"F")>=1,"FAIL",(IF(COUNTIF(P70:W70,"P")>=1,"PASS",(IF(COUNTIF(P70:W70,"N/T")>=1,"N/T",(IF(COUNTIF(P70:W70,"N/A")>=1,"N/A","-"))))))) | O70: =IF(COUNTIF(P70:Q70,"F")>=1,"FAIL",(IF(COUNTIF(P70:Q70,"P")>=1,"PASS",(IF(COUNTIF(P70:Q70,"N/T")>=1,"N/T",(IF(COUNTIF(P70:Q70,"N/A")>=1,"N/A","-"))))))) | P70: P | Q70: P | R70: =IF(COUNTIF(S70:T70,"F")>=1,"FAIL",(IF(COUNTIF(S70:T70,"P")>=1,"PASS",(IF(COUNTIF(S70:T70,"N/T")>=1,"N/T",(IF(COUNTIF(S70:T70,"N/A")>=1,"N/A","-"))))))) | S70: P | T70: P | U70: =IF(COUNTIF(V70:W70,"F")>=1,"FAIL",(IF(COUNTIF(V70:W70,"P")>=1,"PASS",(IF(COUNTIF(V70:W70,"N/T")>=1,"N/T",(IF(COUNTIF(V70:W70,"N/A")>=1,"N/A","-"))))))) | V70: P | W70: P | X70: SPAQA-15934 | AB70: Sanity, CheckList
A71: b_011 | B71: TC_MAP_0042 | C71: Map | D71: Common | E71: 지도 마커 | F71: 지도 마커 | G71: KR, EU | I71: 1 | L71: 1. Map 진입 2. 장소/주소 검색 입력창 선택 3. 임의의 장소/주소 검색 4. 결과 화면 확인 5. 지도상의 임의의 마커 선택 | M71: 1. 선택 상태의 일반 속성 마커가 지도 중심에 표출 | N71: =IF(COUNTIF(P71:W71,"F")>=1,"FAIL",(IF(COUNTIF(P71:W71,"P")>=1,"PASS",(IF(COUNTIF(P71:W71,"N/T")>=1,"N/T",(IF(COUNTIF(P71:W71,"N/A")>=1,"N/A","-"))))))) | O71: =IF(COUNTIF(P71:Q71,"F")>=1,"FAIL",(IF(COUNTIF(P71:Q71,"P")>=1,"PASS",(IF(COUNTIF(P71:Q71,"N/T")>=1,"N/T",(IF(COUNTIF(P71:Q71,"N/A")>=1,"N/A","-"))))))) | P71: P | Q71: P | R71: =IF(COUNTIF(S71:T71,"F")>=1,"FAIL",(IF(COUNTIF(S71:T71,"P")>=1,"PASS",(IF(COUNTIF(S71:T71,"N/T")>=1,"N/T",(IF(COUNTIF(S71:T71,"N/A")>=1,"N/A","-"))))))) | S71: P | T71: P | U71: =IF(COUNTIF(V71:W71,"F")>=1,"FAIL",(IF(COUNTIF(V71:W71,"P")>=1,"PASS",(IF(COUNTIF(V71:W71,"N/T")>=1,"N/T",(IF(COUNTIF(V71:W71,"N/A")>=1,"N/A","-"))))))) | V71: P | W71: P | AB71: Sanity, CheckList, 개인화
A72: b_014 | B72: TC_MAP_0043 | C72: Map | D72: Common | E72: 지도 마커 | F72: 지도 마커 | G72: KR, EU | I72: 1 | K72: 1. EV 차량 | L72: 1. Map 진입 2. 주변 검색 충전소 선택 3. 검색 결과 화면 확인 | M72: 1. 충전소 POI 마커 표출 : 가용 대수 미포함 상태 표출 | N72: =IF(COUNTIF(P72:W72,"F")>=1,"FAIL",(IF(COUNTIF(P72:W72,"P")>=1,"PASS",(IF(COUNTIF(P72:W72,"N/T")>=1,"N/T",(IF(COUNTIF(P72:W72,"N/A")>=1,"N/A","-"))))))) | O72: =IF(COUNTIF(P72:Q72,"F")>=1,"FAIL",(IF(COUNTIF(P72:Q72,"P")>=1,"PASS",(IF(COUNTIF(P72:Q72,"N/T")>=1,"N/T",(IF(COUNTIF(P72:Q72,"N/A")>=1,"N/A","-"))))))) | P72: P | Q72: P | R72: =IF(COUNTIF(S72:T72,"F")>=1,"FAIL",(IF(COUNTIF(S72:T72,"P")>=1,"PASS",(IF(COUNTIF(S72:T72,"N/T")>=1,"N/T",(IF(COUNTIF(S72:T72,"N/A")>=1,"N/A","-"))))))) | S72: P | T72: P | U72: =IF(COUNTIF(V72:W72,"F")>=1,"FAIL",(IF(COUNTIF(V72:W72,"P")>=1,"PASS",(IF(COUNTIF(V72:W72,"N/T")>=1,"N/T",(IF(COUNTIF(V72:W72,"N/A")>=1,"N/A","-"))))))) | V72: P | W72: P | AB72: Sanity, CheckList
A73: b_015 | B73: TC_MAP_0044 | C73: Map | D73: Common | E73: 지도 마커 | F73: 지도 마커 | G73: KR, EU | I73: 1 | K73: 1. EV 차량 | L73: 1. Map 진입 2. 주변 검색 충전소 선택 3. 검색 결과 화면 확인 4. 지도상의 임의의 마커 선택 | M73: 1. 충전소 POI 마커 지도 중심에 표출 : 가용 대수 포함 상태 표출 | N73: =IF(COUNTIF(P73:W73,"F")>=1,"FAIL",(IF(COUNTIF(P73:W73,"P")>=1,"PASS",(IF(COUNTIF(P73:W73,"N/T")>=1,"N/T",(IF(COUNTIF(P73:W73,"N/A")>=1,"N/A","-"))))))) | O73: =IF(COUNTIF(P73:Q73,"F")>=1,"FAIL",(IF(COUNTIF(P73:Q73,"P")>=1,"PASS",(IF(COUNTIF(P73:Q73,"N/T")>=1,"N/T",(IF(COUNTIF(P73:Q73,"N/A")>=1,"N/A","-"))))))) | P73: P | Q73: P | R73: =IF(COUNTIF(S73:T73,"F")>=1,"FAIL",(IF(COUNTIF(S73:T73,"P")>=1,"PASS",(IF(COUNTIF(S73:T73,"N/T")>=1,"N/T",(IF(COUNTIF(S73:T73,"N/A")>=1,"N/A","-"))))))) | S73: P | T73: P | U73: =IF(COUNTIF(V73:W73,"F")>=1,"FAIL",(IF(COUNTIF(V73:W73,"P")>=1,"PASS",(IF(COUNTIF(V73:W73,"N/T")>=1,"N/T",(IF(COUNTIF(V73:W73,"N/A")>=1,"N/A","-"))))))) | V73: P | W73: P | AB73: Sanity, CheckList
A74: b_016 | B74: TC_MAP_0045 | C74: Map | D74: Common | E74: 지도 마커 | F74: 지도 마커 | G74: KR, EU | I74: 1 | L74: 1. Map 진입 2. 주변 검색 주유소 선택 3. 검색 결과 화면 확인 | M74: 1. 주유소 POI 마커 표출 | N74: =IF(COUNTIF(P74:W74,"F")>=1,"FAIL",(IF(COUNTIF(P74:W74,"P")>=1,"PASS",(IF(COUNTIF(P74:W74,"N/T")>=1,"N/T",(IF(COUNTIF(P74:W74,"N/A")>=1,"N/A","-"))))))) | O74: =IF(COUNTIF(P74:Q74,"F")>=1,"FAIL",(IF(COUNTIF(P74:Q74,"P")>=1,"PASS",(IF(COUNTIF(P74:Q74,"N/T")>=1,"N/T",(IF(COUNTIF(P74:Q74,"N/A")>=1,"N/A","-"))))))) | P74: P | Q74: P | R74: =IF(COUNTIF(S74:T74,"F")>=1,"FAIL",(IF(COUNTIF(S74:T74,"P")>=1,"PASS",(IF(COUNTIF(S74:T74,"N/T")>=1,"N/T",(IF(COUNTIF(S74:T74,"N/A")>=1,"N/A","-"))))))) | S74: P | T74: P | U74: =IF(COUNTIF(V74:W74,"F")>=1,"FAIL",(IF(COUNTIF(V74:W74,"P")>=1,"PASS",(IF(COUNTIF(V74:W74,"N/T")>=1,"N/T",(IF(COUNTIF(V74:W74,"N/A")>=1,"N/A","-"))))))) | V74: N/T | W74: N/T | Z74: G: 내연 차량 필요(N/T) | AA74: N/T : 차량/디바이스 필요(조건) | AB74: Sanity, CheckList
A75: b_017 | B75: TC_MAP_0046 | C75: Map | D75: Common | E75: 지도 마커 | F75: 지도 마커 | G75: KR, EU | I75: 1 | L75: 1. Map 진입 2. 주변 검색 주유소 선택 3. 검색 결과 화면 확인 4. 지도상의 임의의 마커 선택 | M75: 1. 선택 상태의 주유소 마커가 지도 중심에 표출 됨 | N75: =IF(COUNTIF(P75:W75,"F")>=1,"FAIL",(IF(COUNTIF(P75:W75,"P")>=1,"PASS",(IF(COUNTIF(P75:W75,"N/T")>=1,"N/T",(IF(COUNTIF(P75:W75,"N/A")>=1,"N/A","-"))))))) | O75: =IF(COUNTIF(P75:Q75,"F")>=1,"FAIL",(IF(COUNTIF(P75:Q75,"P")>=1,"PASS",(IF(COUNTIF(P75:Q75,"N/T")>=1,"N/T",(IF(COUNTIF(P75:Q75,"N/A")>=1,"N/A","-"))))))) | P75: P | Q75: P | R75: =IF(COUNTIF(S75:T75,"F")>=1,"FAIL",(IF(COUNTIF(S75:T75,"P")>=1,"PASS",(IF(COUNTIF(S75:T75,"N/T")>=1,"N/T",(IF(COUNTIF(S75:T75,"N/A")>=1,"N/A","-"))))))) | S75: P | T75: P | U75: =IF(COUNTIF(V75:W75,"F")>=1,"FAIL",(IF(COUNTIF(V75:W75,"P")>=1,"PASS",(IF(COUNTIF(V75:W75,"N/T")>=1,"N/T",(IF(COUNTIF(V75:W75,"N/A")>=1,"N/A","-"))))))) | V75: N/T | W75: N/T | Z75: G: 내연 차량 필요(N/T) | AA75: N/T : 차량/디바이스 필요(조건) | AB75: Sanity, CheckList
A76: b_018 | B76: TC_MAP_0047 | C76: Map | D76: Common | E76: 지도 마커 | F76: 지도 마커 | G76: KR, EU | I76: 1 | L76: 1. Map 진입 2. 주변 검색 주차장 선택 3. 검색 결과 화면 확인 | M76: 1. 주차장 POI 마커 표출 | N76: =IF(COUNTIF(P76:W76,"F")>=1,"FAIL",(IF(COUNTIF(P76:W76,"P")>=1,"PASS",(IF(COUNTIF(P76:W76,"N/T")>=1,"N/T",(IF(COUNTIF(P76:W76,"N/A")>=1,"N/A","-"))))))) | O76: =IF(COUNTIF(P76:Q76,"F")>=1,"FAIL",(IF(COUNTIF(P76:Q76,"P")>=1,"PASS",(IF(COUNTIF(P76:Q76,"N/T")>=1,"N/T",(IF(COUNTIF(P76:Q76,"N/A")>=1,"N/A","-"))))))) | P76: P | Q76: P | R76: =IF(COUNTIF(S76:T76,"F")>=1,"FAIL",(IF(COUNTIF(S76:T76,"P")>=1,"PASS",(IF(COUNTIF(S76:T76,"N/T")>=1,"N/T",(IF(COUNTIF(S76:T76,"N/A")>=1,"N/A","-"))))))) | S76: P | T76: P | U76: =IF(COUNTIF(V76:W76,"F")>=1,"FAIL",(IF(COUNTIF(V76:W76,"P")>=1,"PASS",(IF(COUNTIF(V76:W76,"N/T")>=1,"N/T",(IF(COUNTIF(V76:W76,"N/A")>=1,"N/A","-"))))))) | V76: P | W76: P | AB76: Sanity, CheckList
A77: b_019 | B77: TC_MAP_0048 | C77: Map | D77: Common | E77: 지도 마커 | F77: 지도 마커 | G77: KR, EU | I77: 1 | L77: 1. Map 진입 2. 주변 검색 주차장 선택 3. 검색 결과 화면 확인 4. 지도상의 임의의 마커 선택 | M77: 1. 선택 상태의 주차장 마커가 지도 중심에 표출 됨 | N77: =IF(COUNTIF(P77:W77,"F")>=1,"FAIL",(IF(COUNTIF(P77:W77,"P")>=1,"PASS",(IF(COUNTIF(P77:W77,"N/T")>=1,"N/T",(IF(COUNTIF(P77:W77,"N/A")>=1,"N/A","-"))))))) | O77: =IF(COUNTIF(P77:Q77,"F")>=1,"FAIL",(IF(COUNTIF(P77:Q77,"P")>=1,"PASS",(IF(COUNTIF(P77:Q77,"N/T")>=1,"N/T",(IF(COUNTIF(P77:Q77,"N/A")>=1,"N/A","-"))))))) | P77: P | Q77: P | R77: =IF(COUNTIF(S77:T77,"F")>=1,"FAIL",(IF(COUNTIF(S77:T77,"P")>=1,"PASS",(IF(COUNTIF(S77:T77,"N/T")>=1,"N/T",(IF(COUNTIF(S77:T77,"N/A")>=1,"N/A","-"))))))) | S77: P | T77: P | U77: =IF(COUNTIF(V77:W77,"F")>=1,"FAIL",(IF(COUNTIF(V77:W77,"P")>=1,"PASS",(IF(COUNTIF(V77:W77,"N/T")>=1,"N/T",(IF(COUNTIF(V77:W77,"N/A")>=1,"N/A","-"))))))) | V77: P | W77: P | AB77: Sanity, CheckList
A78: b_020 | B78: TC_MAP_0049 | C78: Map | D78: Common | E78: 지도 마커 | F78: 지도 마커 | G78: KR, EU | I78: 1 | L78: 1. Map 진입 2. 주변 검색 세차장 선택 3. 검색 결과 화면 확인 | M78: 1. 세차장 POI 마커 표출 | N78: =IF(COUNTIF(P78:W78,"F")>=1,"FAIL",(IF(COUNTIF(P78:W78,"P")>=1,"PASS",(IF(COUNTIF(P78:W78,"N/T")>=1,"N/T",(IF(COUNTIF(P78:W78,"N/A")>=1,"N/A","-"))))))) | O78: =IF(COUNTIF(P78:Q78,"F")>=1,"FAIL",(IF(COUNTIF(P78:Q78,"P")>=1,"PASS",(IF(COUNTIF(P78:Q78,"N/T")>=1,"N/T",(IF(COUNTIF(P78:Q78,"N/A")>=1,"N/A","-"))))))) | P78: P | Q78: P | R78: =IF(COUNTIF(S78:T78,"F")>=1,"FAIL",(IF(COUNTIF(S78:T78,"P")>=1,"PASS",(IF(COUNTIF(S78:T78,"N/T")>=1,"N/T",(IF(COUNTIF(S78:T78,"N/A")>=1,"N/A","-"))))))) | S78: P | T78: P | U78: =IF(COUNTIF(V78:W78,"F")>=1,"FAIL",(IF(COUNTIF(V78:W78,"P")>=1,"PASS",(IF(COUNTIF(V78:W78,"N/T")>=1,"N/T",(IF(COUNTIF(V78:W78,"N/A")>=1,"N/A","-"))))))) | V78: P | W78: P | AB78: Sanity, CheckList
A79: b_021 | B79: TC_MAP_0050 | C79: Map | D79: Common | E79: 지도 마커 | F79: 지도 마커 | G79: KR, EU | I79: 1 | L79: 1. Map 진입 2. 주변 검색 세차장 선택 3. 검색 결과 화면 확인 4. 지도상의 임의의 마커 선택 | M79: 1. 선택 상태의 세차장 마커가 지도 중심에 표출 됨 | N79: =IF(COUNTIF(P79:W79,"F")>=1,"FAIL",(IF(COUNTIF(P79:W79,"P")>=1,"PASS",(IF(COUNTIF(P79:W79,"N/T")>=1,"N/T",(IF(COUNTIF(P79:W79,"N/A")>=1,"N/A","-"))))))) | O79: =IF(COUNTIF(P79:Q79,"F")>=1,"FAIL",(IF(COUNTIF(P79:Q79,"P")>=1,"PASS",(IF(COUNTIF(P79:Q79,"N/T")>=1,"N/T",(IF(COUNTIF(P79:Q79,"N/A")>=1,"N/A","-"))))))) | P79: P | Q79: P | R79: =IF(COUNTIF(S79:T79,"F")>=1,"FAIL",(IF(COUNTIF(S79:T79,"P")>=1,"PASS",(IF(COUNTIF(S79:T79,"N/T")>=1,"N/T",(IF(COUNTIF(S79:T79,"N/A")>=1,"N/A","-"))))))) | S79: P | T79: P | U79: =IF(COUNTIF(V79:W79,"F")>=1,"FAIL",(IF(COUNTIF(V79:W79,"P")>=1,"PASS",(IF(COUNTIF(V79:W79,"N/T")>=1,"N/T",(IF(COUNTIF(V79:W79,"N/A")>=1,"N/A","-"))))))) | V79: P | W79: P | AB79: Sanity, CheckList
A80: b_022 | B80: TC_MAP_0051 | C80: Map | D80: Common | E80: 지도 마커 | F80: 지도 마커 | G80: KR, EU | I80: 1 | J80: 1. 프로필 등록 2. 즐겨찾기에 우리집, 사무실, 즐겨찾기 1,2,3 저장 | K80: 1. 프로필 연동 상태 | L80: 1. Map 진입 2. 메인 지도 화면 확인 | M80: 1. 마커 표시 - 우리집 마커 표시 - 사무실 마커 표시 - 즐겨찾는 등록지 마커 표시(일반 POI 마커) | N80: =IF(COUNTIF(P80:W80,"F")>=1,"FAIL",(IF(COUNTIF(P80:W80,"P")>=1,"PASS",(IF(COUNTIF(P80:W80,"N/T")>=1,"N/T",(IF(COUNTIF(P80:W80,"N/A")>=1,"N/A","-"))))))) | O80: =IF(COUNTIF(P80:Q80,"F")>=1,"FAIL",(IF(COUNTIF(P80:Q80,"P")>=1,"PASS",(IF(COUNTIF(P80:Q80,"N/T")>=1,"N/T",(IF(COUNTIF(P80:Q80,"N/A")>=1,"N/A","-"))))))) | P80: P | Q80: P | R80: =IF(COUNTIF(S80:T80,"F")>=1,"FAIL",(IF(COUNTIF(S80:T80,"P")>=1,"PASS",(IF(COUNTIF(S80:T80,"N/T")>=1,"N/T",(IF(COUNTIF(S80:T80,"N/A")>=1,"N/A","-"))))))) | S80: P | T80: P | U80: =IF(COUNTIF(V80:W80,"F")>=1,"FAIL",(IF(COUNTIF(V80:W80,"P")>=1,"PASS",(IF(COUNTIF(V80:W80,"N/T")>=1,"N/T",(IF(COUNTIF(V80:W80,"N/A")>=1,"N/A","-"))))))) | V80: P | W80: P | X80: SPAQA-24441 SPAQA-24595 SPAQA-24473 | AB80: CheckList
A81: b_023 | B81: TC_MAP_0052 | C81: Map | D81: Common | E81: 지도 마커 | F81: 지도 마커 | G81: KR, EU | I81: 1 | J81: 1. 우리집 저장 상태 | K81: 1. 프로필 연동 상태 | L81: 1. Map 진입 2. 메인 지도 화면 확인 3. 우리집 마커 선택 | M81: 1. 선택 상태의 우리집 마커 표출 2. 우리집 중심으로 지도 이동 | N81: =IF(COUNTIF(P81:W81,"F")>=1,"FAIL",(IF(COUNTIF(P81:W81,"P")>=1,"PASS",(IF(COUNTIF(P81:W81,"N/T")>=1,"N/T",(IF(COUNTIF(P81:W81,"N/A")>=1,"N/A","-"))))))) | O81: =IF(COUNTIF(P81:Q81,"F")>=1,"FAIL",(IF(COUNTIF(P81:Q81,"P")>=1,"PASS",(IF(COUNTIF(P81:Q81,"N/T")>=1,"N/T",(IF(COUNTIF(P81:Q81,"N/A")>=1,"N/A","-"))))))) | P81: P | Q81: P | R81: =IF(COUNTIF(S81:T81,"F")>=1,"FAIL",(IF(COUNTIF(S81:T81,"P")>=1,"PASS",(IF(COUNTIF(S81:T81,"N/T")>=1,"N/T",(IF(COUNTIF(S81:T81,"N/A")>=1,"N/A","-"))))))) | S81: P | T81: P | U81: =IF(COUNTIF(V81:W81,"F")>=1,"FAIL",(IF(COUNTIF(V81:W81,"P")>=1,"PASS",(IF(COUNTIF(V81:W81,"N/T")>=1,"N/T",(IF(COUNTIF(V81:W81,"N/A")>=1,"N/A","-"))))))) | V81: P | W81: P | X81: SPAQA-16177 | AB81: CheckList
A82: b_024 | B82: TC_MAP_0053 | C82: Map | D82: Common | E82: 지도 마커 | F82: 지도 마커 | G82: KR, EU | I82: 1 | J82: 1. 사무실 저장 상태 | K82: 1. 프로필 연동 상태 | L82: 1. Map 진입 2. 메인 지도 화면 확인 3. 사무실 마커 선택 | M82: 1. 선택 상태의 사무실 마커 표출 2. 사무실 중심으로 지도 이동 | N82: =IF(COUNTIF(P82:W82,"F")>=1,"FAIL",(IF(COUNTIF(P82:W82,"P")>=1,"PASS",(IF(COUNTIF(P82:W82,"N/T")>=1,"N/T",(IF(COUNTIF(P82:W82,"N/A")>=1,"N/A","-"))))))) | O82: =IF(COUNTIF(P82:Q82,"F")>=1,"FAIL",(IF(COUNTIF(P82:Q82,"P")>=1,"PASS",(IF(COUNTIF(P82:Q82,"N/T")>=1,"N/T",(IF(COUNTIF(P82:Q82,"N/A")>=1,"N/A","-"))))))) | P82: P | Q82: P | R82: =IF(COUNTIF(S82:T82,"F")>=1,"FAIL",(IF(COUNTIF(S82:T82,"P")>=1,"PASS",(IF(COUNTIF(S82:T82,"N/T")>=1,"N/T",(IF(COUNTIF(S82:T82,"N/A")>=1,"N/A","-"))))))) | S82: P | T82: P | U82: =IF(COUNTIF(V82:W82,"F")>=1,"FAIL",(IF(COUNTIF(V82:W82,"P")>=1,"PASS",(IF(COUNTIF(V82:W82,"N/T")>=1,"N/T",(IF(COUNTIF(V82:W82,"N/A")>=1,"N/A","-"))))))) | V82: P | W82: P | X82: SPAQA-16177 | AB82: CheckList
A83: b_025 | B83: TC_MAP_0054 | C83: Map | D83: Common | E83: 지도 마커 | F83: 지도 마커 | G83: KR, EU | I83: 1 | J83: 1. 즐겨찾기 1,2,3 저장 상태 | K83: 1. 프로필 연동 상태 | L83: 1. Map 진입 2. 메인 지도 화면 확인 3. 즐겨찾기 1,2,3 마커 선택 | M83: 1. 선택 상태의 일반 POI 마커 표출 | N83: =IF(COUNTIF(P83:W83,"F")>=1,"FAIL",(IF(COUNTIF(P83:W83,"P")>=1,"PASS",(IF(COUNTIF(P83:W83,"N/T")>=1,"N/T",(IF(COUNTIF(P83:W83,"N/A")>=1,"N/A","-"))))))) | O83: =IF(COUNTIF(P83:Q83,"F")>=1,"FAIL",(IF(COUNTIF(P83:Q83,"P")>=1,"PASS",(IF(COUNTIF(P83:Q83,"N/T")>=1,"N/T",(IF(COUNTIF(P83:Q83,"N/A")>=1,"N/A","-"))))))) | P83: P | Q83: P | R83: =IF(COUNTIF(S83:T83,"F")>=1,"FAIL",(IF(COUNTIF(S83:T83,"P")>=1,"PASS",(IF(COUNTIF(S83:T83,"N/T")>=1,"N/T",(IF(COUNTIF(S83:T83,"N/A")>=1,"N/A","-"))))))) | S83: P | T83: P | U83: =IF(COUNTIF(V83:W83,"F")>=1,"FAIL",(IF(COUNTIF(V83:W83,"P")>=1,"PASS",(IF(COUNTIF(V83:W83,"N/T")>=1,"N/T",(IF(COUNTIF(V83:W83,"N/A")>=1,"N/A","-"))))))) | V83: P | W83: P | X83: SPAQA-19364 SPAQA-19358 SPAQA-19350 SPAQA-22165 | AB83: CheckList
A84: b_026 | B84: TC_MAP_0055 | C84: Map | D84: Common | E84: 지도 마커 | F84: 지도 마커 | G84: KR, EU | I84: 1 | L84: 1. Map 진입 2. 경로 탐색 진입 3. 임의의 출발지 도착지 입력 후 경로 탐색 실행 4. 결과 화면 확인 | M84: 1. 경로 탐색 결과 화면의 마커 표시 - 출발지 마커 - 도착지 마커 | N84: =IF(COUNTIF(P84:W84,"F")>=1,"FAIL",(IF(COUNTIF(P84:W84,"P")>=1,"PASS",(IF(COUNTIF(P84:W84,"N/T")>=1,"N/T",(IF(COUNTIF(P84:W84,"N/A")>=1,"N/A","-"))))))) | O84: =IF(COUNTIF(P84:Q84,"F")>=1,"FAIL",(IF(COUNTIF(P84:Q84,"P")>=1,"PASS",(IF(COUNTIF(P84:Q84,"N/T")>=1,"N/T",(IF(COUNTIF(P84:Q84,"N/A")>=1,"N/A","-"))))))) | P84: P | Q84: P | R84: =IF(COUNTIF(S84:T84,"F")>=1,"FAIL",(IF(COUNTIF(S84:T84,"P")>=1,"PASS",(IF(COUNTIF(S84:T84,"N/T")>=1,"N/T",(IF(COUNTIF(S84:T84,"N/A")>=1,"N/A","-"))))))) | S84: P | T84: P | U84: =IF(COUNTIF(V84:W84,"F")>=1,"FAIL",(IF(COUNTIF(V84:W84,"P")>=1,"PASS",(IF(COUNTIF(V84:W84,"N/T")>=1,"N/T",(IF(COUNTIF(V84:W84,"N/A")>=1,"N/A","-"))))))) | V84: P | W84: P | X84: SPAQA-17226 SPAQA-19856 | AB84: CheckList
A85: b_027 | B85: TC_MAP_0056 | C85: Map | D85: Common | E85: 지도 마커 | F85: 지도 마커 | G85: KR, EU | I85: 1 | L85: 1. Map 진입 2. 경로 탐색 진입 (DTE 벗어나지 않게) 3. 임의의 출발지 도착지, 경유지 입력 후 경로 탐색 실행 4. 결과 화면 확인 | M85: 1. 경로 탐색 결과 화면의 마커 표시 - 출발지 마커 - 경유지 마커 - 도착지 마커 | N85: =IF(COUNTIF(P85:W85,"F")>=1,"FAIL",(IF(COUNTIF(P85:W85,"P")>=1,"PASS",(IF(COUNTIF(P85:W85,"N/T")>=1,"N/T",(IF(COUNTIF(P85:W85,"N/A")>=1,"N/A","-"))))))) | O85: =IF(COUNTIF(P85:Q85,"F")>=1,"FAIL",(IF(COUNTIF(P85:Q85,"P")>=1,"PASS",(IF(COUNTIF(P85:Q85,"N/T")>=1,"N/T",(IF(COUNTIF(P85:Q85,"N/A")>=1,"N/A","-"))))))) | P85: P | Q85: P | R85: =IF(COUNTIF(S85:T85,"F")>=1,"FAIL",(IF(COUNTIF(S85:T85,"P")>=1,"PASS",(IF(COUNTIF(S85:T85,"N/T")>=1,"N/T",(IF(COUNTIF(S85:T85,"N/A")>=1,"N/A","-"))))))) | S85: P | T85: P | U85: =IF(COUNTIF(V85:W85,"F")>=1,"FAIL",(IF(COUNTIF(V85:W85,"P")>=1,"PASS",(IF(COUNTIF(V85:W85,"N/T")>=1,"N/T",(IF(COUNTIF(V85:W85,"N/A")>=1,"N/A","-"))))))) | V85: P | W85: P | X85: SPAQA-20714 SPAQA-22322 SPAQA-20713 SPAQA-23937 | AB85: CheckList
A86: b_028 | B86: TC_MAP_0057 | C86: Map | D86: Common | E86: 지도 마커 | F86: 지도 마커 | G86: KR, EU | I86: 1 | K86: 1. EV 차량 | L86: 1. Map 진입 2. 경로 탐색 진입 3. DTE를 벗어나는 거리의 임의의 경유지 추가 4. 도착지 입력 후 경로 탐색 실행 5. 결과 화면 확인 | M86: 1. 경로 탐색 결과 화면의 마커 표시 - 출발지 마커 - 경유지 마커 - 추천 충전소 마커 - 도착지 마커 | N86: =IF(COUNTIF(P86:W86,"F")>=1,"FAIL",(IF(COUNTIF(P86:W86,"P")>=1,"PASS",(IF(COUNTIF(P86:W86,"N/T")>=1,"N/T",(IF(COUNTIF(P86:W86,"N/A")>=1,"N/A","-"))))))) | O86: =IF(COUNTIF(P86:Q86,"F")>=1,"FAIL",(IF(COUNTIF(P86:Q86,"P")>=1,"PASS",(IF(COUNTIF(P86:Q86,"N/T")>=1,"N/T",(IF(COUNTIF(P86:Q86,"N/A")>=1,"N/A","-"))))))) | P86: P | Q86: P | R86: =IF(COUNTIF(S86:T86,"F")>=1,"FAIL",(IF(COUNTIF(S86:T86,"P")>=1,"PASS",(IF(COUNTIF(S86:T86,"N/T")>=1,"N/T",(IF(COUNTIF(S86:T86,"N/A")>=1,"N/A","-"))))))) | S86: P | T86: P | U86: =IF(COUNTIF(V86:W86,"F")>=1,"FAIL",(IF(COUNTIF(V86:W86,"P")>=1,"PASS",(IF(COUNTIF(V86:W86,"N/T")>=1,"N/T",(IF(COUNTIF(V86:W86,"N/A")>=1,"N/A","-"))))))) | V86: P | W86: P | X86: SPAQA-16137 SPAQA-2071 SPAQA-22548 SPAQA-22899 SPAQA-15930 SPAQA-25355 | AB86: CheckList
B87: TC_MAP_0058 | C87: Map | D87: Common | E87: 지도 마커 | F87: 지도 마커 | G87: KR, EU | I87: 3 | L87: 1. 최종 목적지 알림 푸시 수신 후 앱에서 선택 2. 최종 목적지 안내 화면 표출 | M87: 1. 최종 목적지 안내 화면에서 마커 표출 - 내 위치 마커 - 내 차 위치 마커 - 최종 목적지 마커 | N87: =IF(COUNTIF(P87:W87,"F")>=1,"FAIL",(IF(COUNTIF(P87:W87,"P")>=1,"PASS",(IF(COUNTIF(P87:W87,"N/T")>=1,"N/T",(IF(COUNTIF(P87:W87,"N/A")>=1,"N/A","-"))))))) | O87: =IF(COUNTIF(P87:Q87,"F")>=1,"FAIL",(IF(COUNTIF(P87:Q87,"P")>=1,"PASS",(IF(COUNTIF(P87:Q87,"N/T")>=1,"N/T",(IF(COUNTIF(P87:Q87,"N/A")>=1,"N/A","-"))))))) | P87: F | Q87: P | R87: =IF(COUNTIF(S87:T87,"F")>=1,"FAIL",(IF(COUNTIF(S87:T87,"P")>=1,"PASS",(IF(COUNTIF(S87:T87,"N/T")>=1,"N/T",(IF(COUNTIF(S87:T87,"N/A")>=1,"N/A","-"))))))) | S87: F | T87: P | U87: =IF(COUNTIF(V87:W87,"F")>=1,"FAIL",(IF(COUNTIF(V87:W87,"P")>=1,"PASS",(IF(COUNTIF(V87:W87,"N/T")>=1,"N/T",(IF(COUNTIF(V87:W87,"N/A")>=1,"N/A","-"))))))) | V87: F | W87: P | X87: SPAQA-16755 SPAQA-17040 | Y87: SPAQA-26632 | AB87: 실차
A88: X_019 | B88: TC_MAP_0059 | C88: Map | D88: Common | E88: 지도 마커 | F88: 지도 마커 | G88: KR, EU | I88: 5 | L88: 1. 발레모드 실행 후, 발레모드 지도 화면 확인 | M88: 1. 발레모드 화면에서 마커 표출 - 발렛 차량 인도(시작) 마커 표출(발레모드 2단계) - 발렛 차량 주차 마커(첫번째 주차 후 차량 주차 시 표출) - 발레 차량 마커(발레모드 켜고 차량 주행) | N88: =IF(COUNTIF(P88:W88,"F")>=1,"FAIL",(IF(COUNTIF(P88:W88,"P")>=1,"PASS",(IF(COUNTIF(P88:W88,"N/T")>=1,"N/T",(IF(COUNTIF(P88:W88,"N/A")>=1,"N/A","-"))))))) | O88: =IF(COUNTIF(P88:Q88,"F")>=1,"FAIL",(IF(COUNTIF(P88:Q88,"P")>=1,"PASS",(IF(COUNTIF(P88:Q88,"N/T")>=1,"N/T",(IF(COUNTIF(P88:Q88,"N/A")>=1,"N/A","-"))))))) | P88: N/T | Q88: N/T | R88: =IF(COUNTIF(S88:T88,"F")>=1,"FAIL",(IF(COUNTIF(S88:T88,"P")>=1,"PASS",(IF(COUNTIF(S88:T88,"N/T")>=1,"N/T",(IF(COUNTIF(S88:T88,"N/A")>=1,"N/A","-"))))))) | S88: N/T | T88: N/T | U88: =IF(COUNTIF(V88:W88,"F")>=1,"FAIL",(IF(COUNTIF(V88:W88,"P")>=1,"PASS",(IF(COUNTIF(V88:W88,"N/T")>=1,"N/T",(IF(COUNTIF(V88:W88,"N/A")>=1,"N/A","-"))))))) | V88: N/T | W88: N/T | Z88: (공통) 차량 위치 유럽 고정 표출로 확인 불가(N/T) | AA88: N/T : 외부 환경 필요(환경) | AB88: 실차
A89: b_029 | B89: TC_MAP_0060 | C89: Map | D89: Common | E89: 지도 마커 | F89: 지도 마커 | G89: KR, EU | I89: 1 | J89: 1. 즐겨찾기1,2,3에 충전소 POI 등록 상태 | K89: 1. 차량 계정 연동 상태 | L89: 1. Map 진입 2. 즐겨찾기 탭 선택 3. 즐겨찾기 1,2,3 中 택 1 4. 지도 영역 내 마커 확인 | M89: 1. 선택 상태의 일반 POI 마커 표시 | N89: =IF(COUNTIF(P89:W89,"F")>=1,"FAIL",(IF(COUNTIF(P89:W89,"P")>=1,"PASS",(IF(COUNTIF(P89:W89,"N/T")>=1,"N/T",(IF(COUNTIF(P89:W89,"N/A")>=1,"N/A","-"))))))) | O89: =IF(COUNTIF(P89:Q89,"F")>=1,"FAIL",(IF(COUNTIF(P89:Q89,"P")>=1,"PASS",(IF(COUNTIF(P89:Q89,"N/T")>=1,"N/T",(IF(COUNTIF(P89:Q89,"N/A")>=1,"N/A","-"))))))) | P89: P | Q89: P | R89: =IF(COUNTIF(S89:T89,"F")>=1,"FAIL",(IF(COUNTIF(S89:T89,"P")>=1,"PASS",(IF(COUNTIF(S89:T89,"N/T")>=1,"N/T",(IF(COUNTIF(S89:T89,"N/A")>=1,"N/A","-"))))))) | S89: P | T89: P | U89: =IF(COUNTIF(V89:W89,"F")>=1,"FAIL",(IF(COUNTIF(V89:W89,"P")>=1,"PASS",(IF(COUNTIF(V89:W89,"N/T")>=1,"N/T",(IF(COUNTIF(V89:W89,"N/A")>=1,"N/A","-"))))))) | V89: P | W89: P | X89: SPAQA-16956(TASK) SPAQA-22083 | AB89: CheckList, TASK, 개인화
A90: b_030 | B90: TC_MAP_0061 | C90: Map | D90: Common | E90: 지도 마커 | F90: 지도 마커 | G90: KR, EU | I90: 1 | J90: 1. 등록지에 충전소 POI 등록 상태 | K90: 1. EV | L90: 1. Map 진입 2. 즐겨찾기 탭 선택 3. 등록지 목록 내 충전소 선택 4. 지도 영역 내 마커 확인 | M90: 1. 선택 상태의 일반 POI 마커 표시 | N90: =IF(COUNTIF(P90:W90,"F")>=1,"FAIL",(IF(COUNTIF(P90:W90,"P")>=1,"PASS",(IF(COUNTIF(P90:W90,"N/T")>=1,"N/T",(IF(COUNTIF(P90:W90,"N/A")>=1,"N/A","-"))))))) | O90: =IF(COUNTIF(P90:Q90,"F")>=1,"FAIL",(IF(COUNTIF(P90:Q90,"P")>=1,"PASS",(IF(COUNTIF(P90:Q90,"N/T")>=1,"N/T",(IF(COUNTIF(P90:Q90,"N/A")>=1,"N/A","-"))))))) | P90: P | Q90: P | R90: =IF(COUNTIF(S90:T90,"F")>=1,"FAIL",(IF(COUNTIF(S90:T90,"P")>=1,"PASS",(IF(COUNTIF(S90:T90,"N/T")>=1,"N/T",(IF(COUNTIF(S90:T90,"N/A")>=1,"N/A","-"))))))) | S90: P | T90: P | U90: =IF(COUNTIF(V90:W90,"F")>=1,"FAIL",(IF(COUNTIF(V90:W90,"P")>=1,"PASS",(IF(COUNTIF(V90:W90,"N/T")>=1,"N/T",(IF(COUNTIF(V90:W90,"N/A")>=1,"N/A","-"))))))) | V90: P | W90: P | X90: SPAQA-16956(TASK) SPAQA-18887 SPAQA-23711 | AB90: CheckList, TASK
A91: b_031 | B91: TC_MAP_0062 | C91: Map | D91: Common | E91: 지도 마커 | F91: 지도 마커 | G91: KR, EU | I91: 3 | J91: 1. 최근 검색에 충전소 있는 경우 | K91: 1. EV | L91: 1. Map 진입 2. 최근 검색 탭 선택 3. 최근 검색 목록 내 충전소 선택 4. 지도 영역 내 마커 확인 | M91: 1. 충전소 POI 마커 표출 | N91: =IF(COUNTIF(P91:W91,"F")>=1,"FAIL",(IF(COUNTIF(P91:W91,"P")>=1,"PASS",(IF(COUNTIF(P91:W91,"N/T")>=1,"N/T",(IF(COUNTIF(P91:W91,"N/A")>=1,"N/A","-"))))))) | O91: =IF(COUNTIF(P91:Q91,"F")>=1,"FAIL",(IF(COUNTIF(P91:Q91,"P")>=1,"PASS",(IF(COUNTIF(P91:Q91,"N/T")>=1,"N/T",(IF(COUNTIF(P91:Q91,"N/A")>=1,"N/A","-"))))))) | P91: P | Q91: P | R91: =IF(COUNTIF(S91:T91,"F")>=1,"FAIL",(IF(COUNTIF(S91:T91,"P")>=1,"PASS",(IF(COUNTIF(S91:T91,"N/T")>=1,"N/T",(IF(COUNTIF(S91:T91,"N/A")>=1,"N/A","-"))))))) | S91: N/T | T91: N/T | U91: =IF(COUNTIF(V91:W91,"F")>=1,"FAIL",(IF(COUNTIF(V91:W91,"P")>=1,"PASS",(IF(COUNTIF(V91:W91,"N/T")>=1,"N/T",(IF(COUNTIF(V91:W91,"N/A")>=1,"N/A","-"))))))) | V91: N/T | W91: N/T | X91: SPAQA-16956(TASK) SPAQA-23265 (iOS Block) SPAQA-26093 | Z91: (공통) evs2Support: 0으로 최근 검색에 쌓이지 않음(N/T) | AA91: N/T : 차량/디바이스 필요(조건) | AB91: TASK, Proxy
A92: b_032 | B92: TC_MAP_0063 | C92: Map | D92: Common | E92: 지도 마커 | F92: 지도 마커 | G92: KR, EU | I92: 3 | J92: 1. 즐겨찾는 충전소 등록 상태 | K92: 1. 차량 계정 연동 상태 2. EV 차량 | L92: 1. Map 진입 2. 즐겨찾기 탭 선택 3. 충전소 탭 선택 4. 충전소 목록 선택 5. 지도 영역 내 마커 확인 | M92: 1. 충전소 POI 마커 표출 | N92: =IF(COUNTIF(P92:W92,"F")>=1,"FAIL",(IF(COUNTIF(P92:W92,"P")>=1,"PASS",(IF(COUNTIF(P92:W92,"N/T")>=1,"N/T",(IF(COUNTIF(P92:W92,"N/A")>=1,"N/A","-"))))))) | O92: =IF(COUNTIF(P92:Q92,"F")>=1,"FAIL",(IF(COUNTIF(P92:Q92,"P")>=1,"PASS",(IF(COUNTIF(P92:Q92,"N/T")>=1,"N/T",(IF(COUNTIF(P92:Q92,"N/A")>=1,"N/A","-"))))))) | P92: N/T | Q92: N/T | R92: =IF(COUNTIF(S92:T92,"F")>=1,"FAIL",(IF(COUNTIF(S92:T92,"P")>=1,"PASS",(IF(COUNTIF(S92:T92,"N/T")>=1,"N/T",(IF(COUNTIF(S92:T92,"N/A")>=1,"N/A","-"))))))) | S92: P | T92: P | U92: =IF(COUNTIF(V92:W92,"F")>=1,"FAIL",(IF(COUNTIF(V92:W92,"P")>=1,"PASS",(IF(COUNTIF(V92:W92,"N/T")>=1,"N/T",(IF(COUNTIF(V92:W92,"N/A")>=1,"N/A","-"))))))) | V92: P | W92: P | X92: SPAQA-22037 SPAQA-21638 SPAQA-20783 SPAQA-16956(TASK) SPAQA-18363(TASK) SPAQA-18364(TASK) SPAQA-24269 | Z92: K: 즐겨찾는 충전소 등록 차량 없음 | AA92: N/T : 차량/디바이스 필요(조건) | AB92: TASK, 실차
A93: b_033 | B93: TC_MAP_0064 | C93: Map | D93: Common | E93: 드로어 축소/확장 : 간단 상세 | F93: 드로어 축소/확장 : 간단 상세 | G93: KR, EU, NA | I93: 4 | L93: 1. Map 진입 2. 임의의 POI 검색 3. 검색 결과 지도 내 임의의 POI 선택 4. 간단 상세 화면의 드로어를 위로 Flick 또는 Drag&Drop | M93: 1. 전체 상세 화면으로 전환 | N93: =IF(COUNTIF(P93:W93,"F")>=1,"FAIL",(IF(COUNTIF(P93:W93,"P")>=1,"PASS",(IF(COUNTIF(P93:W93,"N/T")>=1,"N/T",(IF(COUNTIF(P93:W93,"N/A")>=1,"N/A","-"))))))) | O93: =IF(COUNTIF(P93:Q93,"F")>=1,"FAIL",(IF(COUNTIF(P93:Q93,"P")>=1,"PASS",(IF(COUNTIF(P93:Q93,"N/T")>=1,"N/T",(IF(COUNTIF(P93:Q93,"N/A")>=1,"N/A","-"))))))) | P93: P | Q93: P | R93: =IF(COUNTIF(S93:T93,"F")>=1,"FAIL",(IF(COUNTIF(S93:T93,"P")>=1,"PASS",(IF(COUNTIF(S93:T93,"N/T")>=1,"N/T",(IF(COUNTIF(S93:T93,"N/A")>=1,"N/A","-"))))))) | S93: P | T93: P | U93: =IF(COUNTIF(V93:W93,"F")>=1,"FAIL",(IF(COUNTIF(V93:W93,"P")>=1,"PASS",(IF(COUNTIF(V93:W93,"N/T")>=1,"N/T",(IF(COUNTIF(V93:W93,"N/A")>=1,"N/A","-"))))))) | V93: P | W93: P | X93: SPAQA-20145 SPAQA-24045 SPAQA-24270
A94: b_034 | B94: TC_MAP_0065 | C94: Map | D94: Common | E94: 드로어 축소/확장 : 간단 상세 | F94: 드로어 축소/확장 : 간단 상세 | G94: KR, EU, NA | I94: 4 | L94: 1. Map 진입 2. 임의의 POI 검색 3. 검색 결과 지도 내 임의의 POI 선택 4. 간단 상세 화면의 드로어를 위로 Drag한 상태에서 Drop(Release) 하지 않고 유지 | M94: 1. Drag 중에는 간단 상세 UI 유지 | N94: =IF(COUNTIF(P94:W94,"F")>=1,"FAIL",(IF(COUNTIF(P94:W94,"P")>=1,"PASS",(IF(COUNTIF(P94:W94,"N/T")>=1,"N/T",(IF(COUNTIF(P94:W94,"N/A")>=1,"N/A","-"))))))) | O94: =IF(COUNTIF(P94:Q94,"F")>=1,"FAIL",(IF(COUNTIF(P94:Q94,"P")>=1,"PASS",(IF(COUNTIF(P94:Q94,"N/T")>=1,"N/T",(IF(COUNTIF(P94:Q94,"N/A")>=1,"N/A","-"))))))) | P94: P | Q94: P | R94: =IF(COUNTIF(S94:T94,"F")>=1,"FAIL",(IF(COUNTIF(S94:T94,"P")>=1,"PASS",(IF(COUNTIF(S94:T94,"N/T")>=1,"N/T",(IF(COUNTIF(S94:T94,"N/A")>=1,"N/A","-"))))))) | S94: P | T94: P | U94: =IF(COUNTIF(V94:W94,"F")>=1,"FAIL",(IF(COUNTIF(V94:W94,"P")>=1,"PASS",(IF(COUNTIF(V94:W94,"N/T")>=1,"N/T",(IF(COUNTIF(V94:W94,"N/A")>=1,"N/A","-"))))))) | V94: P | W94: P
B95: TC_Map_1557 | C95: Map | D95: Common | E95: 딥링크 (Deep Link) | F95: 내 차로 전송 : 딥링크 | G95: KR, EU, NA | I95: 6 | L95: 1. 딥링크로 내 차로 전송 2. 앱 진입 | M95: 1. [내 차로 전송] 팝업 표출 | N95: =IF(COUNTIF(P95:W95,"F")>=1,"FAIL",(IF(COUNTIF(P95:W95,"P")>=1,"PASS",(IF(COUNTIF(P95:W95,"N/T")>=1,"N/T",(IF(COUNTIF(P95:W95,"N/A")>=1,"N/A","-"))))))) | O95: =IF(COUNTIF(P95:Q95,"F")>=1,"FAIL",(IF(COUNTIF(P95:Q95,"P")>=1,"PASS",(IF(COUNTIF(P95:Q95,"N/T")>=1,"N/T",(IF(COUNTIF(P95:Q95,"N/A")>=1,"N/A","-"))))))) | P95: P | Q95: P | R95: =IF(COUNTIF(S95:T95,"F")>=1,"FAIL",(IF(COUNTIF(S95:T95,"P")>=1,"PASS",(IF(COUNTIF(S95:T95,"N/T")>=1,"N/T",(IF(COUNTIF(S95:T95,"N/A")>=1,"N/A","-"))))))) | S95: P | T95: P | U95: =IF(COUNTIF(V95:W95,"F")>=1,"FAIL",(IF(COUNTIF(V95:W95,"P")>=1,"PASS",(IF(COUNTIF(V95:W95,"N/T")>=1,"N/T",(IF(COUNTIF(V95:W95,"N/A")>=1,"N/A","-"))))))) | V95: P | W95: P | X95: SPAQA-15852(TASK) SPAQA-25656 SPAQA-25660 SPAQA-25683 SPAQA-25654 | AB95: TASK
B96: TC_Map_1558 | C96: Map | D96: Common | E96: 딥링크 (Deep Link) | F96: 내 차로 전송 : 딥링크 | G96: KR, EU, NA | I96: 6 | L96: 1. 딥링크로 내 차로 전송 2. 앱 진입 3. [X] 버튼 선택 | M96: 1. 팝업 닫히고 홈 탭으로 이동 | N96: =IF(COUNTIF(P96:W96,"F")>=1,"FAIL",(IF(COUNTIF(P96:W96,"P")>=1,"PASS",(IF(COUNTIF(P96:W96,"N/T")>=1,"N/T",(IF(COUNTIF(P96:W96,"N/A")>=1,"N/A","-"))))))) | O96: =IF(COUNTIF(P96:Q96,"F")>=1,"FAIL",(IF(COUNTIF(P96:Q96,"P")>=1,"PASS",(IF(COUNTIF(P96:Q96,"N/T")>=1,"N/T",(IF(COUNTIF(P96:Q96,"N/A")>=1,"N/A","-"))))))) | P96: P | Q96: P | R96: =IF(COUNTIF(S96:T96,"F")>=1,"FAIL",(IF(COUNTIF(S96:T96,"P")>=1,"PASS",(IF(COUNTIF(S96:T96,"N/T")>=1,"N/T",(IF(COUNTIF(S96:T96,"N/A")>=1,"N/A","-"))))))) | S96: P | T96: P | U96: =IF(COUNTIF(V96:W96,"F")>=1,"FAIL",(IF(COUNTIF(V96:W96,"P")>=1,"PASS",(IF(COUNTIF(V96:W96,"N/T")>=1,"N/T",(IF(COUNTIF(V96:W96,"N/A")>=1,"N/A","-"))))))) | V96: P | W96: P | X96: SPAQA-15852(TASK) | AB96: TASK
B97: TC_MAP_0066 | C97: Map | D97: Common (폴리엇 기준) | E97: 검색 결과 | F97: 간단 상세(검색 결과 1개) | G97: KR, EU | I97: 1 | J97: 1. 검색 결과가 1개인 상태 - Type 1,2 통합 검색 - 홈탭 가까운 주유소/충전소 선택 - 지도 롱 탭 | L97: 1. Map 진입 2. 동작 조건에 맞는 화면 진입 3. 화면의 하단 드로어 확인 | M97: 1. 하단 드로어가 간단 상세 화면 형태로 표출 poi명 직선 거리, 주소 [경로 탐색] [내 차로 전송] [저장] [공유] * 직선 거리는 위치 권한 On일 경우 표출 | N97: =IF(COUNTIF(P97:W97,"F")>=1,"FAIL",(IF(COUNTIF(P97:W97,"P")>=1,"PASS",(IF(COUNTIF(P97:W97,"N/T")>=1,"N/T",(IF(COUNTIF(P97:W97,"N/A")>=1,"N/A","-"))))))) | O97: =IF(COUNTIF(P97:Q97,"F")>=1,"FAIL",(IF(COUNTIF(P97:Q97,"P")>=1,"PASS",(IF(COUNTIF(P97:Q97,"N/T")>=1,"N/T",(IF(COUNTIF(P97:Q97,"N/A")>=1,"N/A","-"))))))) | P97: P | Q97: P | R97: =IF(COUNTIF(S97:T97,"F")>=1,"FAIL",(IF(COUNTIF(S97:T97,"P")>=1,"PASS",(IF(COUNTIF(S97:T97,"N/T")>=1,"N/T",(IF(COUNTIF(S97:T97,"N/A")>=1,"N/A","-"))))))) | S97: P | T97: P | U97: =IF(COUNTIF(V97:W97,"F")>=1,"FAIL",(IF(COUNTIF(V97:W97,"P")>=1,"PASS",(IF(COUNTIF(V97:W97,"N/T")>=1,"N/T",(IF(COUNTIF(V97:W97,"N/A")>=1,"N/A","-"))))))) | V97: P | W97: P | X97: SPAQA-15769(TASK) SPAQA-16635 SPAQA-21746 SPAQA-21741 SPAQA-23934 | AB97: CheckList, TASK
B98: TC_MAP_0067 | C98: Map | D98: Common (폴리엇 기준) | E98: 검색 결과 | F98: 간단 상세(검색 결과 1개) | G98: KR, EU | I98: 4 | J98: 1. 검색 결과가 1개인 상태 - Type 1,2 통합 검색 - 즐겨찾는 충전소 추가 - 홈탭 가까운 주유소/충전소 선택 - 지도 롱 탭 | L98: 1. Map 진입 2. 동작 조건에 맞는 화면 진입 3. poi명과 주소가 동일한 장소 검색 ex) berlin 4. 검색 결과 화면의 하단 드로어 확인 | M98: 1. POI 간단 상세 내용 중 주소 미표출 poi명 직선 거리 [경로 탐색] [내 차로 전송] [저장] [공유] * 직선 거리는 위치 권한 On일 경우 표출 | N98: =IF(COUNTIF(P98:W98,"F")>=1,"FAIL",(IF(COUNTIF(P98:W98,"P")>=1,"PASS",(IF(COUNTIF(P98:W98,"N/T")>=1,"N/T",(IF(COUNTIF(P98:W98,"N/A")>=1,"N/A","-"))))))) | O98: =IF(COUNTIF(P98:Q98,"F")>=1,"FAIL",(IF(COUNTIF(P98:Q98,"P")>=1,"PASS",(IF(COUNTIF(P98:Q98,"N/T")>=1,"N/T",(IF(COUNTIF(P98:Q98,"N/A")>=1,"N/A","-"))))))) | P98: P | Q98: P | R98: =IF(COUNTIF(S98:T98,"F")>=1,"FAIL",(IF(COUNTIF(S98:T98,"P")>=1,"PASS",(IF(COUNTIF(S98:T98,"N/T")>=1,"N/T",(IF(COUNTIF(S98:T98,"N/A")>=1,"N/A","-"))))))) | S98: P | T98: P | U98: =IF(COUNTIF(V98:W98,"F")>=1,"FAIL",(IF(COUNTIF(V98:W98,"P")>=1,"PASS",(IF(COUNTIF(V98:W98,"N/T")>=1,"N/T",(IF(COUNTIF(V98:W98,"N/A")>=1,"N/A","-"))))))) | V98: P | W98: P | X98: SPAQA-23287 SPAQA-23806
B99: TC_MAP_0068 | C99: Map | D99: Common (폴리엇 기준) | E99: 검색 결과 | F99: 간단 상세(검색 결과 1개) | G99: KR, EU | I99: 1 | J99: 1. 검색 결과가 1개인 상태 - Type 1,2 통합 검색 - 홈탭 가까운 주유소/충전소 선택 - 지도 롱 탭 | L99: 1. Map 진입 2. 동작 조건에 맞는 화면 진입 3. 검색 결과 화면의 지도 확인 | M99: 1. POI 마커가 선택 상태로 1개 표출 | N99: =IF(COUNTIF(P99:W99,"F")>=1,"FAIL",(IF(COUNTIF(P99:W99,"P")>=1,"PASS",(IF(COUNTIF(P99:W99,"N/T")>=1,"N/T",(IF(COUNTIF(P99:W99,"N/A")>=1,"N/A","-"))))))) | O99: =IF(COUNTIF(P99:Q99,"F")>=1,"FAIL",(IF(COUNTIF(P99:Q99,"P")>=1,"PASS",(IF(COUNTIF(P99:Q99,"N/T")>=1,"N/T",(IF(COUNTIF(P99:Q99,"N/A")>=1,"N/A","-"))))))) | P99: P | Q99: P | R99: =IF(COUNTIF(S99:T99,"F")>=1,"FAIL",(IF(COUNTIF(S99:T99,"P")>=1,"PASS",(IF(COUNTIF(S99:T99,"N/T")>=1,"N/T",(IF(COUNTIF(S99:T99,"N/A")>=1,"N/A","-"))))))) | S99: P | T99: P | U99: =IF(COUNTIF(V99:W99,"F")>=1,"FAIL",(IF(COUNTIF(V99:W99,"P")>=1,"PASS",(IF(COUNTIF(V99:W99,"N/T")>=1,"N/T",(IF(COUNTIF(V99:W99,"N/A")>=1,"N/A","-"))))))) | V99: P | W99: P | X99: SPAQA-20197 SPAQA-22262 SPAQA-23950 | AB99: CheckList
B100: TC_MAP_0069 | C100: Map | D100: Common (폴리엇 기준) | E100: 검색 결과 | F100: 간단 상세(검색 결과 1개) | G100: KR, EU | I100: 1 | J100: 1. 검색 결과가 1개인 상태 - Type 1,2 통합 검색 - 홈탭 가까운 주유소/충전소 선택 | L100: 1. Map 진입 2. 동작 조건에 맞는 화면 진입 3. 검색 결과 화면에서 입력 필드 선택 | M100: 1. 입력 필드 포커스 상태 및 키패드 노출 2. 검색어에 대한 추천 검색어 표시 | N100: =IF(COUNTIF(P100:W100,"F")>=1,"FAIL",(IF(COUNTIF(P100:W100,"P")>=1,"PASS",(IF(COUNTIF(P100:W100,"N/T")>=1,"N/T",(IF(COUNTIF(P100:W100,"N/A")>=1,"N/A","-"))))))) | O100: =IF(COUNTIF(P100:Q100,"F")>=1,"FAIL",(IF(COUNTIF(P100:Q100,"P")>=1,"PASS",(IF(COUNTIF(P100:Q100,"N/T")>=1,"N/T",(IF(COUNTIF(P100:Q100,"N/A")>=1,"N/A","-"))))))) | P100: P | Q100: P | R100: =IF(COUNTIF(S100:T100,"F")>=1,"FAIL",(IF(COUNTIF(S100:T100,"P")>=1,"PASS",(IF(COUNTIF(S100:T100,"N/T")>=1,"N/T",(IF(COUNTIF(S100:T100,"N/A")>=1,"N/A","-"))))))) | S100: P | T100: P | U100: =IF(COUNTIF(V100:W100,"F")>=1,"FAIL",(IF(COUNTIF(V100:W100,"P")>=1,"PASS",(IF(COUNTIF(V100:W100,"N/T")>=1,"N/T",(IF(COUNTIF(V100:W100,"N/A")>=1,"N/A","-"))))))) | V100: P | W100: P | X100: SPAQA-20111 SPAQA-22871 | AB100: CheckList
B101: TC_MAP_0070 | C101: Map | D101: Common (폴리엇 기준) | E101: 검색 결과 | F101: 간단 상세(검색 결과 1개) | G101: KR, EU | I101: 1 | J101: 1. 검색 결과가 1개인 상태 - Type 1,2 통합 검색 - 홈탭 가까운 주유소/충전소 선택 | L101: 1. Map 진입 2. 동작 조건에 맞는 화면 진입 3. 검색 결과 화면에서 [<] 버튼 선택 | M101: 1. 이전 화면 이동 | N101: =IF(COUNTIF(P101:W101,"F")>=1,"FAIL",(IF(COUNTIF(P101:W101,"P")>=1,"PASS",(IF(COUNTIF(P101:W101,"N/T")>=1,"N/T",(IF(COUNTIF(P101:W101,"N/A")>=1,"N/A","-"))))))) | O101: =IF(COUNTIF(P101:Q101,"F")>=1,"FAIL",(IF(COUNTIF(P101:Q101,"P")>=1,"PASS",(IF(COUNTIF(P101:Q101,"N/T")>=1,"N/T",(IF(COUNTIF(P101:Q101,"N/A")>=1,"N/A","-"))))))) | P101: P | Q101: P | R101: =IF(COUNTIF(S101:T101,"F")>=1,"FAIL",(IF(COUNTIF(S101:T101,"P")>=1,"PASS",(IF(COUNTIF(S101:T101,"N/T")>=1,"N/T",(IF(COUNTIF(S101:T101,"N/A")>=1,"N/A","-"))))))) | S101: P | T101: P | U101: =IF(COUNTIF(V101:W101,"F")>=1,"FAIL",(IF(COUNTIF(V101:W101,"P")>=1,"PASS",(IF(COUNTIF(V101:W101,"N/T")>=1,"N/T",(IF(COUNTIF(V101:W101,"N/A")>=1,"N/A","-"))))))) | V101: P | W101: P | X101: SPAQA-18882 SPAQA-18905 SPAQA-25366 | AB101: CheckList
A102: a_001 | B102: TC_MAP_0071 | C102: Map | D102: Common (폴리엇 기준) | E102: 검색 결과 | F102: 간단 상세(검색 결과 1개) | G102: KR, EU | I102: 1 | J102: 1. 검색 결과가 1개인 상태 - Type 1,2 통합 검색 - 홈탭 가까운 주유소/충전소 선택 | L102: 1. Map 진입 2. 동작 조건에 맞는 화면 진입 3. 검색 결과 화면에서 [X] 버튼 선택 | M102: 1. 메인 지도 이동 | N102: =IF(COUNTIF(P102:W102,"F")>=1,"FAIL",(IF(COUNTIF(P102:W102,"P")>=1,"PASS",(IF(COUNTIF(P102:W102,"N/T")>=1,"N/T",(IF(COUNTIF(P102:W102,"N/A")>=1,"N/A","-"))))))) | O102: =IF(COUNTIF(P102:Q102,"F")>=1,"FAIL",(IF(COUNTIF(P102:Q102,"P")>=1,"PASS",(IF(COUNTIF(P102:Q102,"N/T")>=1,"N/T",(IF(COUNTIF(P102:Q102,"N/A")>=1,"N/A","-"))))))) | P102: P | Q102: P | R102: =IF(COUNTIF(S102:T102,"F")>=1,"FAIL",(IF(COUNTIF(S102:T102,"P")>=1,"PASS",(IF(COUNTIF(S102:T102,"N/T")>=1,"N/T",(IF(COUNTIF(S102:T102,"N/A")>=1,"N/A","-"))))))) | S102: P | T102: P | U102: =IF(COUNTIF(V102:W102,"F")>=1,"FAIL",(IF(COUNTIF(V102:W102,"P")>=1,"PASS",(IF(COUNTIF(V102:W102,"N/T")>=1,"N/T",(IF(COUNTIF(V102:W102,"N/A")>=1,"N/A","-"))))))) | V102: P | W102: P | AB102: CheckList
...

Sheet My Car
A1: ㄴ | C1: TC 추가 NO : | D1: =IFERROR(__xludf.DUMMYFUNCTION("""TC_""&""MyCar""&""_""&TEXT(ARRAYFORMULA(MAX(IFERROR(VALUE(REGEXEXTRACT(B28:B1694, ""\d+"")))))+1,""0000"")"),"TC_MyCar_0560")
B2: CCI One App | E2: EU FullTC | L2: =Control!L2 | M2: =IF(COUNTIF(N2:O2,"F")>=1,"FAIL",(IF(COUNTIF(N2:O2,"P")>=1,"PASS",(IF(COUNTIF(N2:O2,"N/T")>=1,"N/T",(IF(COUNTIF(N2:O2,"N/A")>=1,"N/A","-"))))))) | O2: 추가 | P2: 수정 | Q2: 삭제
E3: Project | H3: UID ver. | L3: =Control!L3 | M3: =IF(COUNTIF(N3:O3,"F")>=1,"FAIL",(IF(COUNTIF(N3:O3,"P")>=1,"PASS",(IF(COUNTIF(N3:O3,"N/T")>=1,"N/T",(IF(COUNTIF(N3:O3,"N/A")>=1,"N/A","-"))))))) | O3: =COUNTIFS($AB:$AB,"*"&O2&"*") | P3: =COUNTIFS($AB:$AB,"*"&P2&"*") | Q3: =COUNTIFS($AB:$AB,"*"&Q2&"*")
E4: 담당자 | H4: 작성일자 | L4: =Control!L4 | M4: =IF(COUNTIF(N4:O4,"F")>=1,"FAIL",(IF(COUNTIF(N4:O4,"P")>=1,"PASS",(IF(COUNTIF(N4:O4,"N/T")>=1,"N/T",(IF(COUNTIF(N4:O4,"N/A")>=1,"N/A","-")))))))
L5: =Control!L5 | M5: =IF(COUNTIF(N5:O5,"F")>=1,"FAIL",(IF(COUNTIF(N5:O5,"P")>=1,"PASS",(IF(COUNTIF(N5:O5,"N/T")>=1,"N/T",(IF(COUNTIF(N5:O5,"N/A")>=1,"N/A","-"))))))) | N5: ← 색깔 업뎃 시 직접 색 지정하지 말고, 이거 복붙해 주세요(누가 처리 했는지 히스토리 보관용)
B6: 테스트 환경
B7: Tester
B9: Test Target | D9: Total TC | E9: RunRate | F9: PassRate | G9: PASS | H9: FAIL | I9: N/A | J9: N/T | N9: Brand | O9: KOA | R9: HOA | U9: GOA
B10: Total | D10: =SUM(D11:D18) | E10: =IFERROR(SUM($G10:J10)/$D10,"-") | F10: =IFERROR($G10/(SUM(G10:H10)),"-") | G10: =SUM(G11:G18) | H10: =SUM(H11:H18) | I10: =SUM(I11:I18) | J10: =SUM(J11:J18) | N10: OS 별 결과 | O10: Total | P10: Android | Q10: iOS | R10: Total | S10: Android | T10: iOS | U10: Total
B11: My Car | C11: Common | D11: =COUNTIF($D$22:$D$8766,$C11) | E11: =IFERROR(SUM($G11:J11)/$D11,"-") | F11: =IFERROR($G11/(SUM(G11:H11)),"-") | G11: =COUNTIFS($D:$D,$C11,$N:$N,G$9) | H11: =COUNTIFS($D:$D,$C11,$N:$N,H$9) | I11: =COUNTIFS($D:$D,$C11,$N:$N,I$9) | J11: =COUNTIFS($D:$D,$C11,$N:$N,J$9) | N11: Total | O11: =SUM(O12:O15) | P11: =SUM(P12:P15) | Q11: =SUM(Q12:Q15) | R11: =SUM(R12:R15) | S11: =SUM(S12:S15) | T11: =SUM(T12:T15) | U11: =SUM(U12:U15)
C12: CCS 가입 정보 | D12: =COUNTIF($D$22:$D$8766,$C12) | E12: =IFERROR(SUM($G12:J12)/$D12,"-") | F12: =IFERROR($G12/(SUM(G12:H12)),"-") | G12: =COUNTIFS($D:$D,$C12,$N:$N,G$9) | H12: =COUNTIFS($D:$D,$C12,$N:$N,H$9) | I12: =COUNTIFS($D:$D,$C12,$N:$N,I$9) | J12: =COUNTIFS($D:$D,$C12,$N:$N,J$9) | N12: PASS | O12: =COUNTIFS(O$22:O$10136,$N12) | P12: =COUNTIFS(P$22:P$10136,"P") | Q12: =COUNTIFS(Q$22:Q$10136,"P") | R12: =COUNTIFS(R$22:R$10136,$N12) | S12: =COUNTIFS(S$22:S$10136,"P") | T12: =COUNTIFS(T$22:T$10136,"P") | U12: =COUNTIFS(U$22:U$10136,$N12)
C13: 차량 공유 및 프로필 | D13: =COUNTIF($D$22:$D$8766,$C13) | E13: =IFERROR(SUM($G13:J13)/$D13,"-") | F13: =IFERROR($G13/(SUM(G13:H13)),"-") | G13: =COUNTIFS($D:$D,$C13,$N:$N,G$9) | H13: =COUNTIFS($D:$D,$C13,$N:$N,H$9) | I13: =COUNTIFS($D:$D,$C13,$N:$N,I$9) | J13: =COUNTIFS($D:$D,$C13,$N:$N,J$9) | N13: FAIL | O13: =COUNTIFS(O$22:O$10136,$N13) | P13: =COUNTIFS(P$22:P$10136,"F") | Q13: =COUNTIFS(Q$22:Q$10136,"F") | R13: =COUNTIFS(R$22:R$10136,$N13) | S13: =COUNTIFS(S$22:S$10136,"F") | T13: =COUNTIFS(T$22:T$10136,"F") | U13: =COUNTIFS(U$22:U$10136,$N13)
C14: 디지털 키 | D14: =COUNTIF($D$22:$D$8766,$C14) | E14: =IFERROR(SUM($G14:J14)/$D14,"-") | F14: =IFERROR($G14/(SUM(G14:H14)),"-") | G14: =COUNTIFS($D:$D,$C14,$N:$N,G$9) | H14: =COUNTIFS($D:$D,$C14,$N:$N,H$9) | I14: =COUNTIFS($D:$D,$C14,$N:$N,I$9) | J14: =COUNTIFS($D:$D,$C14,$N:$N,J$9) | N14: N/A | O14: =COUNTIFS(O$22:O$10136,$N14) | P14: =COUNTIFS(P$22:P$10136,$N14) | Q14: =COUNTIFS(Q$22:Q$10136,$N14) | R14: =COUNTIFS(R$22:R$10136,$N14) | S14: =COUNTIFS(S$22:S$10136,$N14) | T14: =COUNTIFS(T$22:T$10136,$N14) | U14: =COUNTIFS(U$22:U$10136,$N14)
C15: 연동 서비스 | D15: =COUNTIF($D$22:$D$8766,$C15) | E15: =IFERROR(SUM($G15:J15)/$D15,"-") | F15: =IFERROR($G15/(SUM(G15:H15)),"-") | G15: =COUNTIFS($D:$D,$C15,$N:$N,G$9) | H15: =COUNTIFS($D:$D,$C15,$N:$N,H$9) | I15: =COUNTIFS($D:$D,$C15,$N:$N,I$9) | J15: =COUNTIFS($D:$D,$C15,$N:$N,J$9) | N15: N/T | O15: =COUNTIFS(O$22:O$10136,$N15) | P15: =COUNTIFS(P$22:P$10136,$N15) | Q15: =COUNTIFS(Q$22:Q$10136,$N15) | R15: =COUNTIFS(R$22:R$10136,$N15) | S15: =COUNTIFS(S$22:S$10136,$N15) | T15: =COUNTIFS(T$22:T$10136,$N15) | U15: =COUNTIFS(U$22:U$10136,$N15)
C16: 그 외 | D16: =COUNTIF($D$20:$D$8764,$C16) | E16: =IFERROR(SUM($G16:J16)/$D16,"-") | F16: =IFERROR($G16/(SUM(G16:H16)),"-") | G16: =COUNTIFS($D:$D,$C16,$N:$N,G$9) | H16: =COUNTIFS($D:$D,$C16,$N:$N,H$9) | I16: =COUNTIFS($D:$D,$C16,$N:$N,I$9) | J16: =COUNTIFS($D:$D,$C16,$N:$N,J$9)
C17: 라이팅 패턴 설정 | D17: =COUNTIF($D$20:$D$8764,$C17) | E17: =IFERROR(SUM($G17:J17)/$D17,"-") | F17: =IFERROR($G17/(SUM(G17:H17)),"-") | G17: =COUNTIFS($D:$D,$C17,$N:$N,G$9) | H17: =COUNTIFS($D:$D,$C17,$N:$N,H$9) | I17: =COUNTIFS($D:$D,$C17,$N:$N,I$9) | J17: =COUNTIFS($D:$D,$C17,$N:$N,J$9)
C18: 차량 소프트웨어 버전 | D18: =COUNTIF($D$20:$D$8764,$C18) | E18: =IFERROR(SUM($G18:J18)/$D18,"-") | F18: =IFERROR($G18/(SUM(G18:H18)),"-") | G18: =COUNTIFS($D:$D,$C18,$N:$N,G$9) | H18: =COUNTIFS($D:$D,$C18,$N:$N,H$9) | I18: =COUNTIFS($D:$D,$C18,$N:$N,I$9) | J18: =COUNTIFS($D:$D,$C18,$N:$N,J$9)
B20: TC ID | C20: 카테고리 | D20: 대분류 | E20: 중분류 | F20: 소분류 | G20: 향지 | H20: 브랜드 | I20: 우선순위 | J20: Pre-condition | L20: TC procedure | M20: Expected result | N20: Result | O20: KOA Result | P20: KOA | R20: HOA Result | S20: HOA | U20: GOA Result | V20: GOA | X20: Closed 지라 NO | Y20: 지라 NO. | Z20: NT/NA 상세 사유 | AA20: N/A N/T 필터 | AB20: LABEL
J21: App 동작 조건 | K21: 차량 동작 조건 | M21: 1. 팝업 표출 Please grant user profile permissions to use the service Please ask the vehicle's main user for permission to add a new profile. [Close] (*Close 선택 시 팝업 닫힘) | P21: Android | Q21: iOS | S21: Android | T21: iOS | V21: Android | W21: iOS
B22: TC_MyCar_0001 | C22: My Car | D22: Common | E22: Common | F22: 개인화 4단계 프로필 연동 상태 안내 | G22: EU | I22: 4 | J22: 1. 프로필 미등록 2. 주사용자 | K22: 1. 프로필 미등록 2. 주사용자 | L22: 1. My Car 진입 2. 차량 관리 메뉴 진입 3. 연동 서비스 메뉴 진입 - 캘린더 서비스 - 스트리밍 서비스 | M22: 1. 팝업 표출 Please grant user profile permissions to use the service. Please register your profile in the profile settings. [Register profile] [Close] (*Close 선택 시 팝업 닫힘) | N22: =IF(COUNTIF(P22:W22,"F")>=1,"FAIL",(IF(COUNTIF(P22:W22,"P")>=1,"PASS",(IF(COUNTIF(P22:W22,"N/T")>=1,"N/T",(IF(COUNTIF(P22:W22,"N/A")>=1,"N/A","-"))))))) | O22: =IF(COUNTIF(P22:Q22,"F")>=1,"FAIL",(IF(COUNTIF(P22:Q22,"P")>=1,"PASS",(IF(COUNTIF(P22:Q22,"N/T")>=1,"N/T",(IF(COUNTIF(P22:Q22,"N/A")>=1,"N/A","-"))))))) | P22: N/T | Q22: N/T | R22: =IF(COUNTIF(S22:T22,"F")>=1,"FAIL",(IF(COUNTIF(S22:T22,"P")>=1,"PASS",(IF(COUNTIF(S22:T22,"N/T")>=1,"N/T",(IF(COUNTIF(S22:T22,"N/A")>=1,"N/A","-"))))))) | S22: P | T22: P | U22: =IF(COUNTIF(V22:W22,"F")>=1,"FAIL",(IF(COUNTIF(V22:W22,"P")>=1,"PASS",(IF(COUNTIF(V22:W22,"N/T")>=1,"N/T",(IF(COUNTIF(V22:W22,"N/A")>=1,"N/A","-"))))))) | V22: P | W22: P | Z22: K : MV원격사용불가(방전) (N/T) | AB22: 개인화, 실차
B23: TC_MyCar_0002 | C23: My Car | D23: Common | E23: Common | F23: 개인화 4단계 프로필 연동 상태 안내 | G23: EU | I23: 4 | J23: 1. 프로필 미등록 2. 주사용자 | K23: 1. 개인화 4단계 차량 또는 지역 | L23: 1. My Car 진입 2. 차량 관리 메뉴 진입 3. 연동 서비스 메뉴 진입 - 캘린더 서비스 - 스트리밍 서비스 4. [Register profile] 버튼 선택 | M23: 1. Manage Profile 이동 | N23: =IF(COUNTIF(P23:W23,"F")>=1,"FAIL",(IF(COUNTIF(P23:W23,"P")>=1,"PASS",(IF(COUNTIF(P23:W23,"N/T")>=1,"N/T",(IF(COUNTIF(P23:W23,"N/A")>=1,"N/A","-"))))))) | O23: =IF(COUNTIF(P23:Q23,"F")>=1,"FAIL",(IF(COUNTIF(P23:Q23,"P")>=1,"PASS",(IF(COUNTIF(P23:Q23,"N/T")>=1,"N/T",(IF(COUNTIF(P23:Q23,"N/A")>=1,"N/A","-"))))))) | P23: N/T | Q23: N/T | R23: =IF(COUNTIF(S23:T23,"F")>=1,"FAIL",(IF(COUNTIF(S23:T23,"P")>=1,"PASS",(IF(COUNTIF(S23:T23,"N/T")>=1,"N/T",(IF(COUNTIF(S23:T23,"N/A")>=1,"N/A","-"))))))) | S23: P | T23: P | U23: =IF(COUNTIF(V23:W23,"F")>=1,"FAIL",(IF(COUNTIF(V23:W23,"P")>=1,"PASS",(IF(COUNTIF(V23:W23,"N/T")>=1,"N/T",(IF(COUNTIF(V23:W23,"N/A")>=1,"N/A","-"))))))) | V23: P | W23: P | Z23: K : MV원격사용불가(방전) (N/T) | AB23: 개인화, 실차
B24: TC_MyCar_0003 | C24: My Car | D24: Common | E24: Common | F24: 개인화 4단계 프로필 연동 상태 안내 | G24: EU | I24: 4 | J24: 1. 프로필 미등록 2. 피공유자 | K24: 1. 개인화 4단계 차량 또는 지역 | L24: 1. My Car 진입 2. 차량 관리 메뉴 진입 3. 연동 서비스 메뉴 진입 - 캘린더 서비스 - 스트리밍 서비스 | M24: 1. 팝업 표출 Please grant user profile permissions to use the service Please ask the vehicle's main user for permission to add a new profile. [Close] (*Close 선택 시 팝업 닫힘) | N24: =IF(COUNTIF(P24:W24,"F")>=1,"FAIL",(IF(COUNTIF(P24:W24,"P")>=1,"PASS",(IF(COUNTIF(P24:W24,"N/T")>=1,"N/T",(IF(COUNTIF(P24:W24,"N/A")>=1,"N/A","-"))))))) | O24: =IF(COUNTIF(P24:Q24,"F")>=1,"FAIL",(IF(COUNTIF(P24:Q24,"P")>=1,"PASS",(IF(COUNTIF(P24:Q24,"N/T")>=1,"N/T",(IF(COUNTIF(P24:Q24,"N/A")>=1,"N/A","-"))))))) | P24: P | Q24: P | R24: =IF(COUNTIF(S24:T24,"F")>=1,"FAIL",(IF(COUNTIF(S24:T24,"P")>=1,"PASS",(IF(COUNTIF(S24:T24,"N/T")>=1,"N/T",(IF(COUNTIF(S24:T24,"N/A")>=1,"N/A","-"))))))) | S24: P | T24: P | U24: =IF(COUNTIF(V24:W24,"F")>=1,"FAIL",(IF(COUNTIF(V24:W24,"P")>=1,"PASS",(IF(COUNTIF(V24:W24,"N/T")>=1,"N/T",(IF(COUNTIF(V24:W24,"N/A")>=1,"N/A","-"))))))) | V24: P | W24: P | X24: SPAQA-12319 | Z24: K : wbkong@poliot.co.kr 계정으로 확인 | AB24: 개인화, 실차
B25: TC_MyCar_0004 | C25: My Car | D25: Common | E25: Common | F25: 개인화 4단계 프로필 연동 상태 안내 | G25: EU | I25: 4 | J25: 1. 프로필 미연동 | K25: 1. 개인화 4단계 차량 또는 지역 | L25: 1. My Car 진입 2. 차량 관리 메뉴 진입 3. 연동 서비스 메뉴 진입 - 캘린더 서비스 - 스트리밍 서비스 | M25: 1. 팝업 표출 Profile sync has not been completed. Please complete setting up your user profile in the vehicle. ※ If the Problem persists, please contact the Customer Centre. [Customer centre] [Close] (*Close 선택 시 팝업 닫힘) | N25: =IF(COUNTIF(P25:W25,"F")>=1,"FAIL",(IF(COUNTIF(P25:W25,"P")>=1,"PASS",(IF(COUNTIF(P25:W25,"N/T")>=1,"N/T",(IF(COUNTIF(P25:W25,"N/A")>=1,"N/A","-"))))))) | O25: =IF(COUNTIF(P25:Q25,"F")>=1,"FAIL",(IF(COUNTIF(P25:Q25,"P")>=1,"PASS",(IF(COUNTIF(P25:Q25,"N/T")>=1,"N/T",(IF(COUNTIF(P25:Q25,"N/A")>=1,"N/A","-"))))))) | P25: P | Q25: P | R25: =IF(COUNTIF(S25:T25,"F")>=1,"FAIL",(IF(COUNTIF(S25:T25,"P")>=1,"PASS",(IF(COUNTIF(S25:T25,"N/T")>=1,"N/T",(IF(COUNTIF(S25:T25,"N/A")>=1,"N/A","-"))))))) | S25: P | T25: P | U25: =IF(COUNTIF(V25:W25,"F")>=1,"FAIL",(IF(COUNTIF(V25:W25,"P")>=1,"PASS",(IF(COUNTIF(V25:W25,"N/T")>=1,"N/T",(IF(COUNTIF(V25:W25,"N/A")>=1,"N/A","-"))))))) | V25: P | W25: P | X25: SPAQA-14472 SPAQA-14482 SPAQA-15337 SPAQA-19199 SPAQA-15136 | AB25: 개인화, 실차
B26: TC_MyCar_0005 | C26: My Car | D26: Common | E26: Common | F26: 개인화 4단계 프로필 연동 상태 안내 | G26: EU | I26: 4 | J26: 1. 프로필 미연동 | K26: 1. 개인화 4단계 차량 또는 지역 | L26: 1. My Car 진입 2. 차량 관리 메뉴 진입 3. 연동 서비스 메뉴 진입 - 캘린더 서비스 - 스트리밍 서비스 4. [Customer centre] 버튼 선택 | M26: 1. 고객센터 홈페이지 이동 | N26: =IF(COUNTIF(P26:W26,"F")>=1,"FAIL",(IF(COUNTIF(P26:W26,"P")>=1,"PASS",(IF(COUNTIF(P26:W26,"N/T")>=1,"N/T",(IF(COUNTIF(P26:W26,"N/A")>=1,"N/A","-"))))))) | O26: =IF(COUNTIF(P26:Q26,"F")>=1,"FAIL",(IF(COUNTIF(P26:Q26,"P")>=1,"PASS",(IF(COUNTIF(P26:Q26,"N/T")>=1,"N/T",(IF(COUNTIF(P26:Q26,"N/A")>=1,"N/A","-"))))))) | P26: P | Q26: P | R26: =IF(COUNTIF(S26:T26,"F")>=1,"FAIL",(IF(COUNTIF(S26:T26,"P")>=1,"PASS",(IF(COUNTIF(S26:T26,"N/T")>=1,"N/T",(IF(COUNTIF(S26:T26,"N/A")>=1,"N/A","-"))))))) | S26: P | T26: P | U26: =IF(COUNTIF(V26:W26,"F")>=1,"FAIL",(IF(COUNTIF(V26:W26,"P")>=1,"PASS",(IF(COUNTIF(V26:W26,"N/T")>=1,"N/T",(IF(COUNTIF(V26:W26,"N/A")>=1,"N/A","-"))))))) | V26: P | W26: P | X26: SPAQA-12012 SPAQA-12319 SPAQA-13136 SPAQA-13101 SPAQA-13440 SPAQA-20927 SPAQA-14502 | AB26: 개인화, 실차
B27: TC_MyCar_0007 | C27: My Car | D27: Common | E27: Common | F27: 서비스 리스트 OFF시 표시 정책 | G27: EU | J27: 1. Service List Off | K27: 1. ePrivacy 지원 차량 | L27: 1. MyCar 진입 2. Digital Key Management, External Services, Alert Services, User profile backup 진입 | M27: 1. 해당 탭 진입 시 Service List off 안내 배너 노출 된다. - The service is restricted or unavailable. Check [Privacy Settings] under {AVN_SERVICE_NAME}menu in the vehicle's navigation system. ※ Service List 화면 미제공 | N27: =IF(COUNTIF(P27:W27,"F")>=1,"FAIL",(IF(COUNTIF(P27:W27,"P")>=1,"PASS",(IF(COUNTIF(P27:W27,"N/T")>=1,"N/T",(IF(COUNTIF(P27:W27,"N/A")>=1,"N/A","-"))))))) | O27: =IF(COUNTIF(P27:Q27,"F")>=1,"FAIL",(IF(COUNTIF(P27:Q27,"P")>=1,"PASS",(IF(COUNTIF(P27:Q27,"N/T")>=1,"N/T",(IF(COUNTIF(P27:Q27,"N/A")>=1,"N/A","-"))))))) | P27: N/A | Q27: N/A | R27: =IF(COUNTIF(S27:T27,"F")>=1,"FAIL",(IF(COUNTIF(S27:T27,"P")>=1,"PASS",(IF(COUNTIF(S27:T27,"N/T")>=1,"N/T",(IF(COUNTIF(S27:T27,"N/A")>=1,"N/A","-"))))))) | S27: N/A | T27: N/A | U27: =IF(COUNTIF(V27:W27,"F")>=1,"FAIL",(IF(COUNTIF(V27:W27,"P")>=1,"PASS",(IF(COUNTIF(V27:W27,"N/T")>=1,"N/T",(IF(COUNTIF(V27:W27,"N/A")>=1,"N/A","-"))))))) | V27: N/A | W27: N/A | X27: SPAQA-17223 SPAQA-17224 SPAQA-17500 SPAQA-17298 SPAQA-17293 SPAQA-17203 | Z27: 중복 : TC_MyCar_0245 | AA27: 사양 아님(N/A) | AB27: 실차, 삭제
B28: TC_MyCar_0008 | C28: My Car | D28: Common | E28: Common | F28: 연동 서비스 진입 시 오류 팝업 | G28: KR, EU | I28: 5 | K28: 1. 대표 차량의 스트리밍 서비스 미지원 | L28: 1. MyCar 진입 2. 차량 관리 진입 3. 연동 서비스 진입 | M28: 1. 오류 팝업 표출 The main vehicle does not support this function. Please change the main vehicle and try again. [Close] * close 버튼 선택 시, 팝업 닫히고 현재 화면 유지 | N28: =IF(COUNTIF(P28:W28,"F")>=1,"FAIL",(IF(COUNTIF(P28:W28,"P")>=1,"PASS",(IF(COUNTIF(P28:W28,"N/T")>=1,"N/T",(IF(COUNTIF(P28:W28,"N/A")>=1,"N/A","-"))))))) | O28: =IF(COUNTIF(P28:Q28,"F")>=1,"FAIL",(IF(COUNTIF(P28:Q28,"P")>=1,"PASS",(IF(COUNTIF(P28:Q28,"N/T")>=1,"N/T",(IF(COUNTIF(P28:Q28,"N/A")>=1,"N/A","-"))))))) | P28: N/T | Q28: N/T | R28: =IF(COUNTIF(S28:T28,"F")>=1,"FAIL",(IF(COUNTIF(S28:T28,"P")>=1,"PASS",(IF(COUNTIF(S28:T28,"N/T")>=1,"N/T",(IF(COUNTIF(S28:T28,"N/A")>=1,"N/A","-"))))))) | S28: N/T | T28: N/T | U28: =IF(COUNTIF(V28:W28,"F")>=1,"FAIL",(IF(COUNTIF(V28:W28,"P")>=1,"PASS",(IF(COUNTIF(V28:W28,"N/T")>=1,"N/T",(IF(COUNTIF(V28:W28,"N/A")>=1,"N/A","-"))))))) | V28: N/T | W28: N/T | Z28: (공통) 스트리밍 서비스 미지원 차량 필요 | AA28: N/T : 차량/디바이스 필요(조건)
B29: TC_MyCar_0552 | C29: My Car | D29: CCS 가입 정보 | E29: CCS 가입 정보 | F29: CCS 가입 정보 | G29: KR, EU, NA, MX | H29: KOA, HOA | I29: 1 | J29: 1. 미로그인 | L29: 1. MyCar 진입 | M29: 1. 차량 관리 메뉴 미표출 2. 로그인 버튼 표출 | N29: =IF(COUNTIF(P29:W29,"F")>=1,"FAIL",(IF(COUNTIF(P29:W29,"P")>=1,"PASS",(IF(COUNTIF(P29:W29,"N/T")>=1,"N/T",(IF(COUNTIF(P29:W29,"N/A")>=1,"N/A","-"))))))) | O29: =IF(COUNTIF(P29:Q29,"F")>=1,"FAIL",(IF(COUNTIF(P29:Q29,"P")>=1,"PASS",(IF(COUNTIF(P29:Q29,"N/T")>=1,"N/T",(IF(COUNTIF(P29:Q29,"N/A")>=1,"N/A","-"))))))) | P29: P | Q29: P | R29: =IF(COUNTIF(S29:T29,"F")>=1,"FAIL",(IF(COUNTIF(S29:T29,"P")>=1,"PASS",(IF(COUNTIF(S29:T29,"N/T")>=1,"N/T",(IF(COUNTIF(S29:T29,"N/A")>=1,"N/A","-"))))))) | S29: P | T29: P | U29: =IF(COUNTIF(V29:W29,"F")>=1,"FAIL",(IF(COUNTIF(V29:W29,"P")>=1,"PASS",(IF(COUNTIF(V29:W29,"N/T")>=1,"N/T",(IF(COUNTIF(V29:W29,"N/A")>=1,"N/A","-"))))))) | V29: N/A | W29: N/A | Z29: G : 미로그인 시 마이카 진입 불가(N/A) | AA29: 사양 아님(N/A) | AB29: Sanity
B30: TC_MyCar_0553 | C30: My Car | D30: CCS 가입 정보 | E30: CCS 가입 정보 | F30: CCS 가입 정보 | G30: KR, EU, NA, MX | H30: KOA, HOA | I30: 1 | J30: 1. 미로그인 | L30: 1. MyCar 진입 2. 로그인 버튼 선택 | M30: 1. 로그인 화면 표출 | N30: =IF(COUNTIF(P30:W30,"F")>=1,"FAIL",(IF(COUNTIF(P30:W30,"P")>=1,"PASS",(IF(COUNTIF(P30:W30,"N/T")>=1,"N/T",(IF(COUNTIF(P30:W30,"N/A")>=1,"N/A","-"))))))) | O30: =IF(COUNTIF(P30:Q30,"F")>=1,"FAIL",(IF(COUNTIF(P30:Q30,"P")>=1,"PASS",(IF(COUNTIF(P30:Q30,"N/T")>=1,"N/T",(IF(COUNTIF(P30:Q30,"N/A")>=1,"N/A","-"))))))) | P30: P | Q30: P | R30: =IF(COUNTIF(S30:T30,"F")>=1,"FAIL",(IF(COUNTIF(S30:T30,"P")>=1,"PASS",(IF(COUNTIF(S30:T30,"N/T")>=1,"N/T",(IF(COUNTIF(S30:T30,"N/A")>=1,"N/A","-"))))))) | S30: P | T30: P | U30: =IF(COUNTIF(V30:W30,"F")>=1,"FAIL",(IF(COUNTIF(V30:W30,"P")>=1,"PASS",(IF(COUNTIF(V30:W30,"N/T")>=1,"N/T",(IF(COUNTIF(V30:W30,"N/A")>=1,"N/A","-"))))))) | V30: N/A | W30: N/A | Z30: G : 미로그인 시 마이카 진입 불가(N/A) | AA30: 사양 아님(N/A) | AB30: Sanity
B31: TC_MyCar_0009 | C31: My Car | D31: CCS 가입 정보 | E31: CCS 가입 정보 | F31: CCS 가입 정보 | G31: KR, EU | I31: 3 | J31: 1. CCS 미가입 상태 2. 차주인 경우 | L31: 1. My Car 진입 2. 차량 관리 진입 3. {CCS_SERVICE} 선택 | M31: 1. CCS 가입 화면 표출된다. | N31: =IF(COUNTIF(P31:W31,"F")>=1,"FAIL",(IF(COUNTIF(P31:W31,"P")>=1,"PASS",(IF(COUNTIF(P31:W31,"N/T")>=1,"N/T",(IF(COUNTIF(P31:W31,"N/A")>=1,"N/A","-"))))))) | O31: =IF(COUNTIF(P31:Q31,"F")>=1,"FAIL",(IF(COUNTIF(P31:Q31,"P")>=1,"PASS",(IF(COUNTIF(P31:Q31,"N/T")>=1,"N/T",(IF(COUNTIF(P31:Q31,"N/A")>=1,"N/A","-"))))))) | P31: P | Q31: P | R31: =IF(COUNTIF(S31:T31,"F")>=1,"FAIL",(IF(COUNTIF(S31:T31,"P")>=1,"PASS",(IF(COUNTIF(S31:T31,"N/T")>=1,"N/T",(IF(COUNTIF(S31:T31,"N/A")>=1,"N/A","-"))))))) | S31: P | T31: P | U31: =IF(COUNTIF(V31:W31,"F")>=1,"FAIL",(IF(COUNTIF(V31:W31,"P")>=1,"PASS",(IF(COUNTIF(V31:W31,"N/T")>=1,"N/T",(IF(COUNTIF(V31:W31,"N/A")>=1,"N/A","-"))))))) | V31: P | W31: P | X31: SPAQA-16856(TASK) SPAQA-19379 SPAQA-19136 SPAQA-25008 SPAQA-25722 | AB31: TASK, 실차
B32: TC_MyCar_0010 | C32: My Car | D32: CCS 가입 정보 | E32: CCS 가입 정보 | F32: CCS 가입 정보 | G32: KR, EU | I32: 1 | J32: 1. CCS 이용 불가 2. 차주인 경우 | K32: 1. 차량 Offline Mode OFF | L32: 1. My Car 진입 2. 차량 관리 진입 3. {CCS_SERVICE} 선택 | M32: 1. 가입일 , 만료일, 차대번호 표출 - Subscription date - Expiration date - Vin | N32: =IF(COUNTIF(P32:W32,"F")>=1,"FAIL",(IF(COUNTIF(P32:W32,"P")>=1,"PASS",(IF(COUNTIF(P32:W32,"N/T")>=1,"N/T",(IF(COUNTIF(P32:W32,"N/A")>=1,"N/A","-"))))))) | O32: =IF(COUNTIF(P32:Q32,"F")>=1,"FAIL",(IF(COUNTIF(P32:Q32,"P")>=1,"PASS",(IF(COUNTIF(P32:Q32,"N/T")>=1,"N/T",(IF(COUNTIF(P32:Q32,"N/A")>=1,"N/A","-"))))))) | P32: P | Q32: P | R32: =IF(COUNTIF(S32:T32,"F")>=1,"FAIL",(IF(COUNTIF(S32:T32,"P")>=1,"PASS",(IF(COUNTIF(S32:T32,"N/T")>=1,"N/T",(IF(COUNTIF(S32:T32,"N/A")>=1,"N/A","-"))))))) | S32: P | T32: P | U32: =IF(COUNTIF(V32:W32,"F")>=1,"FAIL",(IF(COUNTIF(V32:W32,"P")>=1,"PASS",(IF(COUNTIF(V32:W32,"N/T")>=1,"N/T",(IF(COUNTIF(V32:W32,"N/A")>=1,"N/A","-"))))))) | V32: P | W32: P | X32: SPAQA-16856(TASK) | AB32: CheckList, 실차, TASK
B33: TC_MyCar_0049 | C33: My Car | D33: 차량 공유 및 프로필 | E33: 프로필 관리 | F33: 프로필 연동 | G33: EU | I33: 1 | K33: 1. 차량 프로필 연동 시도 | L33: 1. 프로필 연동 PUSH 팝업 확인 2. 개인화 4단계 차량 | M33: 1. 팝업 표출된다. - Self-authentication - Taday 00:00 - EV9 A self-authentication request has been sent from your vehicle. - Do you want to allow this authentication request? - [Accept] - [Cancel] | N33: =IF(COUNTIF(P33:W33,"F")>=1,"FAIL",(IF(COUNTIF(P33:W33,"P")>=1,"PASS",(IF(COUNTIF(P33:W33,"N/T")>=1,"N/T",(IF(COUNTIF(P33:W33,"N/A")>=1,"N/A","-"))))))) | O33: =IF(COUNTIF(P33:Q33,"F")>=1,"FAIL",(IF(COUNTIF(P33:Q33,"P")>=1,"PASS",(IF(COUNTIF(P33:Q33,"N/T")>=1,"N/T",(IF(COUNTIF(P33:Q33,"N/A")>=1,"N/A","-"))))))) | P33: N/T | Q33: N/T | R33: =IF(COUNTIF(S33:T33,"F")>=1,"FAIL",(IF(COUNTIF(S33:T33,"P")>=1,"PASS",(IF(COUNTIF(S33:T33,"N/T")>=1,"N/T",(IF(COUNTIF(S33:T33,"N/A")>=1,"N/A","-"))))))) | S33: F | T33: F | U33: =IF(COUNTIF(V33:W33,"F")>=1,"FAIL",(IF(COUNTIF(V33:W33,"P")>=1,"PASS",(IF(COUNTIF(V33:W33,"N/T")>=1,"N/T",(IF(COUNTIF(V33:W33,"N/A")>=1,"N/A","-"))))))) | V33: F | W33: F | X33: spaqa-17026(TASK) | Y33: SPAQA-22949 SPAQA-25282 SPAQA-25088 | Z33: K : MV원격사용불가(방전) (N/T) | AB33: CheckList, 실차, TASK
B34: TC_MyCar_0011 | C34: My Car | D34: CCS 가입 정보 | E34: CCS 가입 정보 | F34: CCS 가입 정보 | G34: KR, EU | I34: 3 | J34: 1. CCS 이용 불가 2. 차주인 경우 | K34: 1. 차량 Deactivation | L34: 1. My Car 진입 2. 차량 관리 진입 3. {CCS_SERVICE} 선택 | M34: 1. This vehicle is not subscribed to Kia Connect. Subscribe to use a variety of remote control services. 2. [Active ] 버튼 표출 | N34: =IF(COUNTIF(P34:W34,"F")>=1,"FAIL",(IF(COUNTIF(P34:W34,"P")>=1,"PASS",(IF(COUNTIF(P34:W34,"N/T")>=1,"N/T",(IF(COUNTIF(P34:W34,"N/A")>=1,"N/A","-"))))))) | O34: =IF(COUNTIF(P34:Q34,"F")>=1,"FAIL",(IF(COUNTIF(P34:Q34,"P")>=1,"PASS",(IF(COUNTIF(P34:Q34,"N/T")>=1,"N/T",(IF(COUNTIF(P34:Q34,"N/A")>=1,"N/A","-"))))))) | P34: P | Q34: P | R34: =IF(COUNTIF(S34:T34,"F")>=1,"FAIL",(IF(COUNTIF(S34:T34,"P")>=1,"PASS",(IF(COUNTIF(S34:T34,"N/T")>=1,"N/T",(IF(COUNTIF(S34:T34,"N/A")>=1,"N/A","-"))))))) | S34: P | T34: P | U34: =IF(COUNTIF(V34:W34,"F")>=1,"FAIL",(IF(COUNTIF(V34:W34,"P")>=1,"PASS",(IF(COUNTIF(V34:W34,"N/T")>=1,"N/T",(IF(COUNTIF(V34:W34,"N/A")>=1,"N/A","-"))))))) | V34: P | W34: P | X34: SPAQA-16856(TASK) SPAQA-26399(TASK) | AB34: TASK, 실차, 수정
B35: TC_MyCar_0012 | C35: My Car | D35: CCS 가입 정보 | E35: CCS 가입 정보 | F35: CCS 가입 정보 | G35: KR, EU | I35: 5 | J35: 1. CCS 이용 불가 2. 차주인 경우 | K35: 1. 차량 안전 모드 상태 | L35: 1. My Car 진입 2. 차량 관리 진입 3. {CCS_SERVICE} 선택 | M35: 1. 진입불가 팝업 표출 Service temporarily restricted due to unstable vehicle connection. Full service functionality will be available when the connection improves. ※ You may not receive push notifications in the current condition [Close] | N35: =IF(COUNTIF(P35:W35,"F")>=1,"FAIL",(IF(COUNTIF(P35:W35,"P")>=1,"PASS",(IF(COUNTIF(P35:W35,"N/T")>=1,"N/T",(IF(COUNTIF(P35:W35,"N/A")>=1,"N/A","-"))))))) | O35: =IF(COUNTIF(P35:Q35,"F")>=1,"FAIL",(IF(COUNTIF(P35:Q35,"P")>=1,"PASS",(IF(COUNTIF(P35:Q35,"N/T")>=1,"N/T",(IF(COUNTIF(P35:Q35,"N/A")>=1,"N/A","-"))))))) | P35: P | Q35: P | R35: =IF(COUNTIF(S35:T35,"F")>=1,"FAIL",(IF(COUNTIF(S35:T35,"P")>=1,"PASS",(IF(COUNTIF(S35:T35,"N/T")>=1,"N/T",(IF(COUNTIF(S35:T35,"N/A")>=1,"N/A","-"))))))) | S35: P | T35: P | U35: =IF(COUNTIF(V35:W35,"F")>=1,"FAIL",(IF(COUNTIF(V35:W35,"P")>=1,"PASS",(IF(COUNTIF(V35:W35,"N/T")>=1,"N/T",(IF(COUNTIF(V35:W35,"N/A")>=1,"N/A","-"))))))) | V35: P | W35: P | X35: SPAQA-16856(TASK) SPAQA-19632 SPAQA-19633 SPAQA-19162 | Z35: (공통) 안전모드 강제 설정으로 확인 가능 | AB35: TASK, 실차
B36: TC_MyCar_0013 | C36: My Car | D36: CCS 가입 정보 | E36: CCS 가입 정보 | F36: CCS 가입 정보 | G36: KR, EU | I36: 4 | J36: 1. CCS 이용 불가 2. 피공유자인 경우 | K36: 1. 차량 Offline Mode OFF | L36: 1. My Car 진입 2. 차량 관리 진입 3. {CCS_SERVICE} 선택 | M36: 1. 가입일 , 만료일, 차대번호 표출 - Subscription date - Expiration date - Vin | N36: =IF(COUNTIF(P36:W36,"F")>=1,"FAIL",(IF(COUNTIF(P36:W36,"P")>=1,"PASS",(IF(COUNTIF(P36:W36,"N/T")>=1,"N/T",(IF(COUNTIF(P36:W36,"N/A")>=1,"N/A","-"))))))) | O36: =IF(COUNTIF(P36:Q36,"F")>=1,"FAIL",(IF(COUNTIF(P36:Q36,"P")>=1,"PASS",(IF(COUNTIF(P36:Q36,"N/T")>=1,"N/T",(IF(COUNTIF(P36:Q36,"N/A")>=1,"N/A","-"))))))) | P36: P | Q36: P | R36: =IF(COUNTIF(S36:T36,"F")>=1,"FAIL",(IF(COUNTIF(S36:T36,"P")>=1,"PASS",(IF(COUNTIF(S36:T36,"N/T")>=1,"N/T",(IF(COUNTIF(S36:T36,"N/A")>=1,"N/A","-"))))))) | S36: P | T36: P | U36: =IF(COUNTIF(V36:W36,"F")>=1,"FAIL",(IF(COUNTIF(V36:W36,"P")>=1,"PASS",(IF(COUNTIF(V36:W36,"N/T")>=1,"N/T",(IF(COUNTIF(V36:W36,"N/A")>=1,"N/A","-"))))))) | V36: P | W36: P | X36: SPAQA-16856(TASK) | AB36: TASK, 실차
B37: TC_MyCar_0014 | C37: My Car | D37: CCS 가입 정보 | E37: CCS 가입 정보 | F37: CCS 가입 정보 | G37: KR, EU | I37: 3 | J37: 1. CCS 이용 불가 2. 피공유자인 경우 | K37: 1. 차량 Deactivation | L37: 1. My Car 진입 2. 차량 관리 진입 3. {CCS_SERVICE} 선택 | M37: 1. 진입 불가 안내 팝업 표출 - Please obtain {CCS Service Name} permission from the main user first [Close] | N37: =IF(COUNTIF(P37:W37,"F")>=1,"FAIL",(IF(COUNTIF(P37:W37,"P")>=1,"PASS",(IF(COUNTIF(P37:W37,"N/T")>=1,"N/T",(IF(COUNTIF(P37:W37,"N/A")>=1,"N/A","-"))))))) | O37: =IF(COUNTIF(P37:Q37,"F")>=1,"FAIL",(IF(COUNTIF(P37:Q37,"P")>=1,"PASS",(IF(COUNTIF(P37:Q37,"N/T")>=1,"N/T",(IF(COUNTIF(P37:Q37,"N/A")>=1,"N/A","-"))))))) | P37: P | Q37: P | R37: =IF(COUNTIF(S37:T37,"F")>=1,"FAIL",(IF(COUNTIF(S37:T37,"P")>=1,"PASS",(IF(COUNTIF(S37:T37,"N/T")>=1,"N/T",(IF(COUNTIF(S37:T37,"N/A")>=1,"N/A","-"))))))) | S37: P | T37: P | U37: =IF(COUNTIF(V37:W37,"F")>=1,"FAIL",(IF(COUNTIF(V37:W37,"P")>=1,"PASS",(IF(COUNTIF(V37:W37,"N/T")>=1,"N/T",(IF(COUNTIF(V37:W37,"N/A")>=1,"N/A","-"))))))) | V37: P | W37: P | X37: SPAQA-16856(TASK) | Z37: H : 차량 디액티브 시 피공유자 Bluelink 진입 불가 (Flow) | AB37: TASK, 실차
B38: TC_MyCar_0015 | C38: My Car | D38: CCS 가입 정보 | E38: CCS 가입 정보 | F38: CCS 가입 정보 | G38: KR, EU | I38: 5 | J38: 1. CCS 이용 불가 2. 피공유자인 경우 | K38: 1. 차량 안전 모드 상태 | L38: 1. My Car 진입 2. 차량 관리 진입 3. {CCS_SERVICE} 선택 | M38: 1. 진입불가 팝업 표출 Service temporarily restricted due to unstable vehicle connection. Full service functionality will be available when the connection improves. ※ You may not receive push notifications in the current condition [Close] | N38: =IF(COUNTIF(P38:W38,"F")>=1,"FAIL",(IF(COUNTIF(P38:W38,"P")>=1,"PASS",(IF(COUNTIF(P38:W38,"N/T")>=1,"N/T",(IF(COUNTIF(P38:W38,"N/A")>=1,"N/A","-"))))))) | O38: =IF(COUNTIF(P38:Q38,"F")>=1,"FAIL",(IF(COUNTIF(P38:Q38,"P")>=1,"PASS",(IF(COUNTIF(P38:Q38,"N/T")>=1,"N/T",(IF(COUNTIF(P38:Q38,"N/A")>=1,"N/A","-"))))))) | P38: P | Q38: P | R38: =IF(COUNTIF(S38:T38,"F")>=1,"FAIL",(IF(COUNTIF(S38:T38,"P")>=1,"PASS",(IF(COUNTIF(S38:T38,"N/T")>=1,"N/T",(IF(COUNTIF(S38:T38,"N/A")>=1,"N/A","-"))))))) | S38: P | T38: P | U38: =IF(COUNTIF(V38:W38,"F")>=1,"FAIL",(IF(COUNTIF(V38:W38,"P")>=1,"PASS",(IF(COUNTIF(V38:W38,"N/T")>=1,"N/T",(IF(COUNTIF(V38:W38,"N/A")>=1,"N/A","-"))))))) | V38: P | W38: P | X38: SPAQA-16856(TASK) | Z38: K : debug mode | AB38: TASK, 실차
B39: TC_MyCar_0016 | C39: My Car | D39: CCS 가입 정보 | E39: CCS 가입 정보 | F39: CCS 가입 정보 | G39: KR, EU | I39: 1 | L39: 1. My Car 진입 2. 차량 관리 선택 3. {CCS_SERVICE} 메뉴 확인 | M39: 1. CCS_SERVICE 메뉴 확인한다. - 브랜드 별 서비스 명 표시 - H : Bluelink / K : {CCS_SERVICE} / G : GENESIS Connected Services | N39: =IF(COUNTIF(P39:W39,"F")>=1,"FAIL",(IF(COUNTIF(P39:W39,"P")>=1,"PASS",(IF(COUNTIF(P39:W39,"N/T")>=1,"N/T",(IF(COUNTIF(P39:W39,"N/A")>=1,"N/A","-"))))))) | O39: =IF(COUNTIF(P39:Q39,"F")>=1,"FAIL",(IF(COUNTIF(P39:Q39,"P")>=1,"PASS",(IF(COUNTIF(P39:Q39,"N/T")>=1,"N/T",(IF(COUNTIF(P39:Q39,"N/A")>=1,"N/A","-"))))))) | P39: P | Q39: P | R39: =IF(COUNTIF(S39:T39,"F")>=1,"FAIL",(IF(COUNTIF(S39:T39,"P")>=1,"PASS",(IF(COUNTIF(S39:T39,"N/T")>=1,"N/T",(IF(COUNTIF(S39:T39,"N/A")>=1,"N/A","-"))))))) | S39: P | T39: P | U39: =IF(COUNTIF(V39:W39,"F")>=1,"FAIL",(IF(COUNTIF(V39:W39,"P")>=1,"PASS",(IF(COUNTIF(V39:W39,"N/T")>=1,"N/T",(IF(COUNTIF(V39:W39,"N/A")>=1,"N/A","-"))))))) | V39: P | W39: P | X39: SPAQA-9896 SPAQA-14576 | AB39: Sanity
B40: TC_MyCar_0017 | C40: My Car | D40: CCS 가입 정보 | E40: CCS 가입 정보 | F40: CCS 가입 정보 | G40: KR, EU | I40: 1 | L40: 1. My Car 진입 2. 차량 관리 선택 3. {CCS_SERVICE} 선택 | M40: 1. CCS_SERVICE 진입 확인한다. | N40: =IF(COUNTIF(P40:W40,"F")>=1,"FAIL",(IF(COUNTIF(P40:W40,"P")>=1,"PASS",(IF(COUNTIF(P40:W40,"N/T")>=1,"N/T",(IF(COUNTIF(P40:W40,"N/A")>=1,"N/A","-"))))))) | O40: =IF(COUNTIF(P40:Q40,"F")>=1,"FAIL",(IF(COUNTIF(P40:Q40,"P")>=1,"PASS",(IF(COUNTIF(P40:Q40,"N/T")>=1,"N/T",(IF(COUNTIF(P40:Q40,"N/A")>=1,"N/A","-"))))))) | P40: P | Q40: P | R40: =IF(COUNTIF(S40:T40,"F")>=1,"FAIL",(IF(COUNTIF(S40:T40,"P")>=1,"PASS",(IF(COUNTIF(S40:T40,"N/T")>=1,"N/T",(IF(COUNTIF(S40:T40,"N/A")>=1,"N/A","-"))))))) | S40: P | T40: P | U40: =IF(COUNTIF(V40:W40,"F")>=1,"FAIL",(IF(COUNTIF(V40:W40,"P")>=1,"PASS",(IF(COUNTIF(V40:W40,"N/T")>=1,"N/T",(IF(COUNTIF(V40:W40,"N/A")>=1,"N/A","-"))))))) | V40: P | W40: P | X40: SPAQA-14593 | AB40: Sanity
B41: TC_MyCar_0018 | C41: My Car | D41: CCS 가입 정보 | E41: CCS 가입 정보 | F41: CCS 가입 정보 | G41: KR, EU | I41: 1 | L41: 1. My Car 탭 진입 2. 차량 관리 선택 3. {CCS_SERVICE} 진입 | M41: 1. 가입일, 만료일(EU Only), 차대번호 표출 2. 단말 번호 미표출 | N41: =IF(COUNTIF(P41:W41,"F")>=1,"FAIL",(IF(COUNTIF(P41:W41,"P")>=1,"PASS",(IF(COUNTIF(P41:W41,"N/T")>=1,"N/T",(IF(COUNTIF(P41:W41,"N/A")>=1,"N/A","-"))))))) | O41: =IF(COUNTIF(P41:Q41,"F")>=1,"FAIL",(IF(COUNTIF(P41:Q41,"P")>=1,"PASS",(IF(COUNTIF(P41:Q41,"N/T")>=1,"N/T",(IF(COUNTIF(P41:Q41,"N/A")>=1,"N/A","-"))))))) | P41: P | Q41: P | R41: =IF(COUNTIF(S41:T41,"F")>=1,"FAIL",(IF(COUNTIF(S41:T41,"P")>=1,"PASS",(IF(COUNTIF(S41:T41,"N/T")>=1,"N/T",(IF(COUNTIF(S41:T41,"N/A")>=1,"N/A","-"))))))) | S41: P | T41: P | U41: =IF(COUNTIF(V41:W41,"F")>=1,"FAIL",(IF(COUNTIF(V41:W41,"P")>=1,"PASS",(IF(COUNTIF(V41:W41,"N/T")>=1,"N/T",(IF(COUNTIF(V41:W41,"N/A")>=1,"N/A","-"))))))) | V41: P | W41: P | X41: SPAQA-14947 SPAQA-16269 SPAQA-16915 SPAQA-22867 | AB41: Sanity, TASK
B42: TC_MyCar_0554 | C42: My Car | D42: CCS 가입 정보 | E42: CCS 가입 정보 | F42: CCS 가입 정보 | G42: EU | H42: HOA, KOA | I42: 4 | J42: 1. 요금제 가입 상태 | K42: 1. 요금제 상관 없음 | L42: 1. My Car 진입 2. 차량 관리 선택 3. {CCS SERVICE}진입 4. 요금제 정보 카드 확인 | M42: 1. 요금제 명 표출 확인 ex) PRO, LITE.. | N42: =IF(COUNTIF(P42:W42,"F")>=1,"FAIL",(IF(COUNTIF(P42:W42,"P")>=1,"PASS",(IF(COUNTIF(P42:W42,"N/T")>=1,"N/T",(IF(COUNTIF(P42:W42,"N/A")>=1,"N/A","-"))))))) | O42: =IF(COUNTIF(P42:Q42,"F")>=1,"FAIL",(IF(COUNTIF(P42:Q42,"P")>=1,"PASS",(IF(COUNTIF(P42:Q42,"N/T")>=1,"N/T",(IF(COUNTIF(P42:Q42,"N/A")>=1,"N/A","-"))))))) | P42: P | Q42: P | R42: =IF(COUNTIF(S42:T42,"F")>=1,"FAIL",(IF(COUNTIF(S42:T42,"P")>=1,"PASS",(IF(COUNTIF(S42:T42,"N/T")>=1,"N/T",(IF(COUNTIF(S42:T42,"N/A")>=1,"N/A","-"))))))) | S42: P | T42: P | U42: =IF(COUNTIF(V42:W42,"F")>=1,"FAIL",(IF(COUNTIF(V42:W42,"P")>=1,"PASS",(IF(COUNTIF(V42:W42,"N/T")>=1,"N/T",(IF(COUNTIF(V42:W42,"N/A")>=1,"N/A","-"))))))) | V42: N/A | W42: N/A | X42: SPAQA-25812(TASK) | Z42: G : 비대상 브랜드 (N/A) | AA42: 비대상 차종(N/A) | AB42: TASK
B43: TC_MyCar_0019 | C43: My Car | D43: CCS 가입 정보 | E43: CCS 가입 정보 | F43: CCS 가입 정보 | G43: EU | H43: HOA, KOA | I43: 4 | J43: 1. 차주 계정 | K43: 1. 무료 요금제 | L43: 1. My Car 탭 진입 2. 차량 관리 선택 3. {CCS SERVICE}진입 4. 요금제 정보 카드 확인 | M43: 1. 무료기간 만료일자 표출 - Expires date : {dd mm yy} 표출 ex) Expiration date: 18 Mar 2034 | N43: =IF(COUNTIF(P43:W43,"F")>=1,"FAIL",(IF(COUNTIF(P43:W43,"P")>=1,"PASS",(IF(COUNTIF(P43:W43,"N/T")>=1,"N/T",(IF(COUNTIF(P43:W43,"N/A")>=1,"N/A","-"))))))) | O43: =IF(COUNTIF(P43:Q43,"F")>=1,"FAIL",(IF(COUNTIF(P43:Q43,"P")>=1,"PASS",(IF(COUNTIF(P43:Q43,"N/T")>=1,"N/T",(IF(COUNTIF(P43:Q43,"N/A")>=1,"N/A","-"))))))) | P43: P | Q43: P | R43: =IF(COUNTIF(S43:T43,"F")>=1,"FAIL",(IF(COUNTIF(S43:T43,"P")>=1,"PASS",(IF(COUNTIF(S43:T43,"N/T")>=1,"N/T",(IF(COUNTIF(S43:T43,"N/A")>=1,"N/A","-"))))))) | S43: P | T43: P | U43: =IF(COUNTIF(V43:W43,"F")>=1,"FAIL",(IF(COUNTIF(V43:W43,"P")>=1,"PASS",(IF(COUNTIF(V43:W43,"N/T")>=1,"N/T",(IF(COUNTIF(V43:W43,"N/A")>=1,"N/A","-"))))))) | V43: N/A | W43: N/A | X43: SPAQA-25812(TASK) | Z43: G : 비대상 브랜드 (N/A) | AA43: 사양 아님(N/A) | AB43: TASK
B44: TC_MyCar_0020 | C44: My Car | D44: CCS 가입 정보 | E44: CCS 가입 정보 | F44: CCS 가입 정보 | G44: EU | H44: HOA, KOA | I44: 4 | J44: 1. 차주 계정 | K44: 1. 무료 요금제 2. 만료일 30일 이내 | L44: 1. My Car 탭 진입 2. 차량 관리 선택 3. {CCS SERVICE}진입 4. 요금제 정보 카드 확인 | M44: 1. 라이트 요금제 남은 기간 정보 표출 {CCS_SERVICE_NAME} Lite will be available for %s years, %s months from subscription date. ※ 개월 수가 0일 경우, %s months 미표시 ※ CLDR 적용 in %s day(s) - CLDR 적용 (당일일 경우 ‘in 1 day’, 이외 ‘in n days’) | N44: =IF(COUNTIF(P44:W44,"F")>=1,"FAIL",(IF(COUNTIF(P44:W44,"P")>=1,"PASS",(IF(COUNTIF(P44:W44,"N/T")>=1,"N/T",(IF(COUNTIF(P44:W44,"N/A")>=1,"N/A","-"))))))) | O44: =IF(COUNTIF(P44:Q44,"F")>=1,"FAIL",(IF(COUNTIF(P44:Q44,"P")>=1,"PASS",(IF(COUNTIF(P44:Q44,"N/T")>=1,"N/T",(IF(COUNTIF(P44:Q44,"N/A")>=1,"N/A","-"))))))) | P44: P | Q44: P | R44: =IF(COUNTIF(S44:T44,"F")>=1,"FAIL",(IF(COUNTIF(S44:T44,"P")>=1,"PASS",(IF(COUNTIF(S44:T44,"N/T")>=1,"N/T",(IF(COUNTIF(S44:T44,"N/A")>=1,"N/A","-"))))))) | S44: P | T44: P | U44: =IF(COUNTIF(V44:W44,"F")>=1,"FAIL",(IF(COUNTIF(V44:W44,"P")>=1,"PASS",(IF(COUNTIF(V44:W44,"N/T")>=1,"N/T",(IF(COUNTIF(V44:W44,"N/A")>=1,"N/A","-"))))))) | V44: N/A | W44: N/A | X44: SPAQA-23479(TASK) SPAQA-25812(TASK) | Z44: G : 비대상 브랜드 (N/A) | AA44: 사양 아님(N/A) | AB44: TASK
B45: TC_MyCar_0555 | C45: My Car | D45: CCS 가입 정보 | E45: CCS 가입 정보 | F45: CCS 가입 정보 | G45: EU | H45: HOA, KOA | I45: 4 | J45: 1. 무료 기간 상태(만료일 정보 Y + 금액 정보 Y) 1. 차주 계정 | K45: 1. 무료 요금제 | L45: 1. My Car 탭 진입 2. 차량 관리 선택 3. {CCS SERVICE}진입 4. 요금제 정보 카드 확인 | M45: 1. 'Free trial' 문구 정상 표출 확인 | N45: =IF(COUNTIF(P45:W45,"F")>=1,"FAIL",(IF(COUNTIF(P45:W45,"P")>=1,"PASS",(IF(COUNTIF(P45:W45,"N/T")>=1,"N/T",(IF(COUNTIF(P45:W45,"N/A")>=1,"N/A","-"))))))) | O45: =IF(COUNTIF(P45:Q45,"F")>=1,"FAIL",(IF(COUNTIF(P45:Q45,"P")>=1,"PASS",(IF(COUNTIF(P45:Q45,"N/T")>=1,"N/T",(IF(COUNTIF(P45:Q45,"N/A")>=1,"N/A","-"))))))) | P45: P | Q45: P | R45: =IF(COUNTIF(S45:T45,"F")>=1,"FAIL",(IF(COUNTIF(S45:T45,"P")>=1,"PASS",(IF(COUNTIF(S45:T45,"N/T")>=1,"N/T",(IF(COUNTIF(S45:T45,"N/A")>=1,"N/A","-"))))))) | S45: P | T45: P | U45: =IF(COUNTIF(V45:W45,"F")>=1,"FAIL",(IF(COUNTIF(V45:W45,"P")>=1,"PASS",(IF(COUNTIF(V45:W45,"N/T")>=1,"N/T",(IF(COUNTIF(V45:W45,"N/A")>=1,"N/A","-"))))))) | V45: N/A | W45: N/A | X45: SPAQA-25812(TASK) | Z45: G : 비대상 브랜드 (N/A) | AA45: 사양 아님(N/A) | AB45: TASK
B46: TC_MyCar_0021 | C46: My Car | D46: CCS 가입 정보 | E46: CCS 가입 정보 | F46: CCS 가입 정보 | G46: EU | H46: HOA, KOA | I46: 4 | J46: 1. 차주 계정 | K46: 1. 유료 요금제 | L46: 1. My Car 탭 진입 2. 차량 관리 선택 3. {CCS SERVICE}진입 4. 요금제 정보 카드 확인 | M46: 1. Active 문구 표출 확인 | N46: =IF(COUNTIF(P46:W46,"F")>=1,"FAIL",(IF(COUNTIF(P46:W46,"P")>=1,"PASS",(IF(COUNTIF(P46:W46,"N/T")>=1,"N/T",(IF(COUNTIF(P46:W46,"N/A")>=1,"N/A","-"))))))) | O46: =IF(COUNTIF(P46:Q46,"F")>=1,"FAIL",(IF(COUNTIF(P46:Q46,"P")>=1,"PASS",(IF(COUNTIF(P46:Q46,"N/T")>=1,"N/T",(IF(COUNTIF(P46:Q46,"N/A")>=1,"N/A","-"))))))) | P46: P | Q46: P | R46: =IF(COUNTIF(S46:T46,"F")>=1,"FAIL",(IF(COUNTIF(S46:T46,"P")>=1,"PASS",(IF(COUNTIF(S46:T46,"N/T")>=1,"N/T",(IF(COUNTIF(S46:T46,"N/A")>=1,"N/A","-"))))))) | S46: P | T46: P | U46: =IF(COUNTIF(V46:W46,"F")>=1,"FAIL",(IF(COUNTIF(V46:W46,"P")>=1,"PASS",(IF(COUNTIF(V46:W46,"N/T")>=1,"N/T",(IF(COUNTIF(V46:W46,"N/A")>=1,"N/A","-"))))))) | V46: N/A | W46: N/A | X46: SPAQA-23659 SPAQA-23479(TASK) SPAQA-25812(TASK) | Z46: G : 비대상 브랜드 (N/A) | AA46: 사양 아님(N/A) | AB46: TASK
B47: TC_MyCar_0441 | C47: My Car | D47: CCS 가입 정보 | E47: CCS 가입 정보 | F47: CCS 가입 정보 | G47: EU | H47: HOA, KOA | I47: 4 | J47: 1. CCS 실 사용자 2. 차주 계정 | K47: 1. 요금제 상관 없음 | L47: 1. My Car 탭 진입 2. 차량 관리 선택 3. {CCS SERVICE}진입 5. 스토어 안내 카드 확인 | M47: 1. Explore a variety of plans in {BRAND FoD} 문구 표출 2. Store 버튼 표출 | N47: =IF(COUNTIF(P47:W47,"F")>=1,"FAIL",(IF(COUNTIF(P47:W47,"P")>=1,"PASS",(IF(COUNTIF(P47:W47,"N/T")>=1,"N/T",(IF(COUNTIF(P47:W47,"N/A")>=1,"N/A","-"))))))) | O47: =IF(COUNTIF(P47:Q47,"F")>=1,"FAIL",(IF(COUNTIF(P47:Q47,"P")>=1,"PASS",(IF(COUNTIF(P47:Q47,"N/T")>=1,"N/T",(IF(COUNTIF(P47:Q47,"N/A")>=1,"N/A","-"))))))) | P47: P | Q47: P | R47: =IF(COUNTIF(S47:T47,"F")>=1,"FAIL",(IF(COUNTIF(S47:T47,"P")>=1,"PASS",(IF(COUNTIF(S47:T47,"N/T")>=1,"N/T",(IF(COUNTIF(S47:T47,"N/A")>=1,"N/A","-"))))))) | S47: P | T47: P | U47: =IF(COUNTIF(V47:W47,"F")>=1,"FAIL",(IF(COUNTIF(V47:W47,"P")>=1,"PASS",(IF(COUNTIF(V47:W47,"N/T")>=1,"N/T",(IF(COUNTIF(V47:W47,"N/A")>=1,"N/A","-"))))))) | V47: N/A | W47: N/A | X47: SPAQA-25148 SPAQA-25812(TASK) | Z47: G : 비대상 브랜드 (N/A) | AA47: 사양 아님(N/A) | AB47: TASK
B48: TC_MyCar_0442 | C48: My Car | D48: CCS 가입 정보 | E48: CCS 가입 정보 | F48: CCS 가입 정보 | G48: EU | H48: HOA, KOA | I48: 4 | J48: 1. 피공유자 | K48: 1. 무료 요금제 | L48: 1. My Car 탭 진입 2. 이용 가능한 차량 선택 3. 차량 관리 선택 4. {CCS SERVICE}진입 | M48: 1. 아래와 같이 노출 {Plan name} Expires on: {25 December 2030} in %s day(s) Free Trial | N48: =IF(COUNTIF(P48:W48,"F")>=1,"FAIL",(IF(COUNTIF(P48:W48,"P")>=1,"PASS",(IF(COUNTIF(P48:W48,"N/T")>=1,"N/T",(IF(COUNTIF(P48:W48,"N/A")>=1,"N/A","-"))))))) | O48: =IF(COUNTIF(P48:Q48,"F")>=1,"FAIL",(IF(COUNTIF(P48:Q48,"P")>=1,"PASS",(IF(COUNTIF(P48:Q48,"N/T")>=1,"N/T",(IF(COUNTIF(P48:Q48,"N/A")>=1,"N/A","-"))))))) | P48: P | Q48: P | R48: =IF(COUNTIF(S48:T48,"F")>=1,"FAIL",(IF(COUNTIF(S48:T48,"P")>=1,"PASS",(IF(COUNTIF(S48:T48,"N/T")>=1,"N/T",(IF(COUNTIF(S48:T48,"N/A")>=1,"N/A","-"))))))) | S48: P | T48: P | U48: =IF(COUNTIF(V48:W48,"F")>=1,"FAIL",(IF(COUNTIF(V48:W48,"P")>=1,"PASS",(IF(COUNTIF(V48:W48,"N/T")>=1,"N/T",(IF(COUNTIF(V48:W48,"N/A")>=1,"N/A","-"))))))) | V48: N/A | W48: N/A | X48: SPAQA-25148 SPAQA-25812(TASK) | Z48: G : 비대상 브랜드 (N/A) | AA48: 사양 아님(N/A) | AB48: TASK
B49: TC_MyCar_0460 | C49: My Car | D49: CCS 가입 정보 | E49: CCS 가입 정보 | F49: CCS 가입 정보 | G49: EU | H49: HOA, KOA | I49: 4 | J49: 1. CCS 실 사용자 2. 차주 계정 | K49: 1. 무료 요금제 | L49: 1. My Car 탭 진입 2. 차량 관리 선택 3. {CCS SERVICE}진입 4. (Store) 버튼 선택 | M49: 1. FoD 웹 뷰 페이지로 이동 해당 앱 언어로 FoD 페이지 언어 표출 - 앱 언어와 FoD 페이지 언어 동일 | N49: =IF(COUNTIF(P49:W49,"F")>=1,"FAIL",(IF(COUNTIF(P49:W49,"P")>=1,"PASS",(IF(COUNTIF(P49:W49,"N/T")>=1,"N/T",(IF(COUNTIF(P49:W49,"N/A")>=1,"N/A","-"))))))) | O49: =IF(COUNTIF(P49:Q49,"F")>=1,"FAIL",(IF(COUNTIF(P49:Q49,"P")>=1,"PASS",(IF(COUNTIF(P49:Q49,"N/T")>=1,"N/T",(IF(COUNTIF(P49:Q49,"N/A")>=1,"N/A","-"))))))) | P49: P | Q49: P | R49: =IF(COUNTIF(S49:T49,"F")>=1,"FAIL",(IF(COUNTIF(S49:T49,"P")>=1,"PASS",(IF(COUNTIF(S49:T49,"N/T")>=1,"N/T",(IF(COUNTIF(S49:T49,"N/A")>=1,"N/A","-"))))))) | S49: P | T49: P | U49: =IF(COUNTIF(V49:W49,"F")>=1,"FAIL",(IF(COUNTIF(V49:W49,"P")>=1,"PASS",(IF(COUNTIF(V49:W49,"N/T")>=1,"N/T",(IF(COUNTIF(V49:W49,"N/A")>=1,"N/A","-"))))))) | V49: N/A | W49: N/A | X49: SPAQA-25505(TASK) SPAQA-25216 SPAQA-25552 SPAQA-25284 SPAQA-25634 SPAQA-25812(TASK) | Z49: G : 비대상 브랜드 (N/A) | AA49: 사양 아님(N/A) | AB49: TASK
B50: TC_MyCar_0556 | C50: My Car | D50: CCS 가입 정보 | E50: CCS 가입 정보 | F50: CCS 가입 정보 | G50: EU | H50: HOA, KOA | I50: 5 | J50: 1. 유료 상위 요금제 사용자가 기간이 만료 되어 하위 요금제로 변경 진행 시, 배치 실패로 요금제 정보를 불러오지 못할 경우 | K50: 1. 차량 CCS 가입 해제 중 | L50: 1. MyCar 탭 진입 2. 차량 관리 선택 3. {CCS SERVICE}진입 4. 요금제 정보 카드 확인 | M50: 1. CCS 요금제 정보 확인 실패 시 문구 표출 - Checking plan information. - Please check again later. | N50: =IF(COUNTIF(P50:W50,"F")>=1,"FAIL",(IF(COUNTIF(P50:W50,"P")>=1,"PASS",(IF(COUNTIF(P50:W50,"N/T")>=1,"N/T",(IF(COUNTIF(P50:W50,"N/A")>=1,"N/A","-"))))))) | O50: =IF(COUNTIF(P50:Q50,"F")>=1,"FAIL",(IF(COUNTIF(P50:Q50,"P")>=1,"PASS",(IF(COUNTIF(P50:Q50,"N/T")>=1,"N/T",(IF(COUNTIF(P50:Q50,"N/A")>=1,"N/A","-"))))))) | P50: N/T | Q50: N/T | R50: =IF(COUNTIF(S50:T50,"F")>=1,"FAIL",(IF(COUNTIF(S50:T50,"P")>=1,"PASS",(IF(COUNTIF(S50:T50,"N/T")>=1,"N/T",(IF(COUNTIF(S50:T50,"N/A")>=1,"N/A","-"))))))) | S50: N/T | T50: N/T | U50: =IF(COUNTIF(V50:W50,"F")>=1,"FAIL",(IF(COUNTIF(V50:W50,"P")>=1,"PASS",(IF(COUNTIF(V50:W50,"N/T")>=1,"N/T",(IF(COUNTIF(V50:W50,"N/A")>=1,"N/A","-"))))))) | V50: N/A | W50: N/A | X50: SPAQA-25812(TASK) | Z50: K/H : CCS 요금제 정보 확인 실패 상태 필요 G : 비대상 브랜드 (N/A) | AA50: N/T : 특수상황/실패 조건 필요(조건) | AB50: TASK
B51: TC_MyCar_0557 | C51: My Car | D51: CCS 가입 정보 | E51: CCS 가입 정보 | F51: CCS 가입 정보 | G51: EU | H51: HOA, KOA | I51: 4 | J51: 1. 피공유자 | K51: 1. 무료 요금제 | L51: 1. My Car 탭 진입 2. 차량 관리 선택 3. {CCS SERVICE}진입 4. 요금제 정보 카드 확인 | M51: 1. FoD 영역 미노출 | N51: =IF(COUNTIF(P51:W51,"F")>=1,"FAIL",(IF(COUNTIF(P51:W51,"P")>=1,"PASS",(IF(COUNTIF(P51:W51,"N/T")>=1,"N/T",(IF(COUNTIF(P51:W51,"N/A")>=1,"N/A","-"))))))) | O51: =IF(COUNTIF(P51:Q51,"F")>=1,"FAIL",(IF(COUNTIF(P51:Q51,"P")>=1,"PASS",(IF(COUNTIF(P51:Q51,"N/T")>=1,"N/T",(IF(COUNTIF(P51:Q51,"N/A")>=1,"N/A","-"))))))) | P51: P | Q51: P | R51: =IF(COUNTIF(S51:T51,"F")>=1,"FAIL",(IF(COUNTIF(S51:T51,"P")>=1,"PASS",(IF(COUNTIF(S51:T51,"N/T")>=1,"N/T",(IF(COUNTIF(S51:T51,"N/A")>=1,"N/A","-"))))))) | S51: P | T51: P | U51: =IF(COUNTIF(V51:W51,"F")>=1,"FAIL",(IF(COUNTIF(V51:W51,"P")>=1,"PASS",(IF(COUNTIF(V51:W51,"N/T")>=1,"N/T",(IF(COUNTIF(V51:W51,"N/A")>=1,"N/A","-"))))))) | V51: N/A | W51: N/A | X51: SPAQA-25812(TASK) | Z51: G : 비대상 브랜드 (N/A) | AB51: TASK
B52: TC_MyCar_0558 | C52: My Car | D52: CCS 가입 정보 | E52: CCS 가입 정보 | F52: CCS 가입 정보 | G52: EU | H52: HOA, KOA | I52: 4 | J52: 1. 피공유자 | K52: 1. 유료 요금제 | L52: 1. My Car 탭 진입 2. 차량 관리 선택 3. {CCS SERVICE}진입 4. 요금제 정보 카드 확인 | M52: 1. FoD 영역 미노출 | N52: =IF(COUNTIF(P52:W52,"F")>=1,"FAIL",(IF(COUNTIF(P52:W52,"P")>=1,"PASS",(IF(COUNTIF(P52:W52,"N/T")>=1,"N/T",(IF(COUNTIF(P52:W52,"N/A")>=1,"N/A","-"))))))) | O52: =IF(COUNTIF(P52:Q52,"F")>=1,"FAIL",(IF(COUNTIF(P52:Q52,"P")>=1,"PASS",(IF(COUNTIF(P52:Q52,"N/T")>=1,"N/T",(IF(COUNTIF(P52:Q52,"N/A")>=1,"N/A","-"))))))) | P52: P | Q52: P | R52: =IF(COUNTIF(S52:T52,"F")>=1,"FAIL",(IF(COUNTIF(S52:T52,"P")>=1,"PASS",(IF(COUNTIF(S52:T52,"N/T")>=1,"N/T",(IF(COUNTIF(S52:T52,"N/A")>=1,"N/A","-"))))))) | S52: P | T52: P | U52: =IF(COUNTIF(V52:W52,"F")>=1,"FAIL",(IF(COUNTIF(V52:W52,"P")>=1,"PASS",(IF(COUNTIF(V52:W52,"N/T")>=1,"N/T",(IF(COUNTIF(V52:W52,"N/A")>=1,"N/A","-"))))))) | V52: N/A | W52: N/A | X52: SPAQA-25812(TASK) | Z52: G : 비대상 브랜드 (N/A) | AB52: TASK
B53: TC_MyCar_0559 | C53: My Car | D53: CCS 가입 정보 | E53: CCS 가입 정보 | F53: CCS 가입 정보 | G53: EU | H53: HOA, KOA | I53: 4 | J53: 1. 피공유자 | K53: 1. 유료 요금제 | L53: 1. My Car 탭 진입 2. 차량 관리 선택 3. {CCS SERVICE}진입 4. 요금제 정보 카드 확인 | M53: 1. 아래와 같이 노출 {Plan name} Active | N53: =IF(COUNTIF(P53:W53,"F")>=1,"FAIL",(IF(COUNTIF(P53:W53,"P")>=1,"PASS",(IF(COUNTIF(P53:W53,"N/T")>=1,"N/T",(IF(COUNTIF(P53:W53,"N/A")>=1,"N/A","-"))))))) | O53: =IF(COUNTIF(P53:Q53,"F")>=1,"FAIL",(IF(COUNTIF(P53:Q53,"P")>=1,"PASS",(IF(COUNTIF(P53:Q53,"N/T")>=1,"N/T",(IF(COUNTIF(P53:Q53,"N/A")>=1,"N/A","-"))))))) | P53: P | Q53: P | R53: =IF(COUNTIF(S53:T53,"F")>=1,"FAIL",(IF(COUNTIF(S53:T53,"P")>=1,"PASS",(IF(COUNTIF(S53:T53,"N/T")>=1,"N/T",(IF(COUNTIF(S53:T53,"N/A")>=1,"N/A","-"))))))) | S53: P | T53: P | U53: =IF(COUNTIF(V53:W53,"F")>=1,"FAIL",(IF(COUNTIF(V53:W53,"P")>=1,"PASS",(IF(COUNTIF(V53:W53,"N/T")>=1,"N/T",(IF(COUNTIF(V53:W53,"N/A")>=1,"N/A","-"))))))) | V53: N/A | W53: N/A | X53: SPAQA-25812(TASK) | Z53: G : 비대상 브랜드 (N/A) | AB53: TASK
B54: TC_MyCar_0461 | C54: My Car | D54: CCS 가입 정보 | E54: CCS 가입 정보 | F54: CCS 가입 정보 | G54: EU | H54: HOA | I54: 5 | K54: 1. 라이트 요금제 | L54: 1. My Car 탭 진입 2. 이용 가능한 차량 선택 3. 차량 관리 선택 4. {CCS SERVICE}진입 5. 하단 안내 문구 확인 | M54: 1. 라이트 요금제 남은 기간 정보 표출 {CCS_SERVICE_NAME} Lite will be available for %s years, %s months from subscription date. ※ 개월 수가 0일 경우, %s months 미표시 ※ CLDR 적용 in %s day(s) - CLDR 적용 (당일일 경우 ‘in 1 day’, 이외 ‘in n days’) | N54: =IF(COUNTIF(P54:W54,"F")>=1,"FAIL",(IF(COUNTIF(P54:W54,"P")>=1,"PASS",(IF(COUNTIF(P54:W54,"N/T")>=1,"N/T",(IF(COUNTIF(P54:W54,"N/A")>=1,"N/A","-"))))))) | O54: =IF(COUNTIF(P54:Q54,"F")>=1,"FAIL",(IF(COUNTIF(P54:Q54,"P")>=1,"PASS",(IF(COUNTIF(P54:Q54,"N/T")>=1,"N/T",(IF(COUNTIF(P54:Q54,"N/A")>=1,"N/A","-"))))))) | P54: N/A | Q54: N/A | R54: =IF(COUNTIF(S54:T54,"F")>=1,"FAIL",(IF(COUNTIF(S54:T54,"P")>=1,"PASS",(IF(COUNTIF(S54:T54,"N/T")>=1,"N/T",(IF(COUNTIF(S54:T54,"N/A")>=1,"N/A","-"))))))) | S54: P | T54: P | U54: =IF(COUNTIF(V54:W54,"F")>=1,"FAIL",(IF(COUNTIF(V54:W54,"P")>=1,"PASS",(IF(COUNTIF(V54:W54,"N/T")>=1,"N/T",(IF(COUNTIF(V54:W54,"N/A")>=1,"N/A","-"))))))) | V54: N/A | W54: N/A | X54: SPAQA-25686(TASK) SPAQA-25948 SPAQA-25812(TASK) | Z54: K/G : 비대상 브랜드 (N/A) | AA54: 사양 아님(N/A) | AB54: TASK, Proxy
B55: TC_MyCar_0462 | C55: My Car | D55: CCS 가입 정보 | E55: CCS 가입 정보 | F55: CCS 가입 정보 | G55: EU | H55: KOA, GOA | I55: 5 | L55: 1. My Car 진입 2. 차량 관리 진입 3. {CCS_SERVICE} 선택 4. 하단 기간 안내 문구 확인 | M55: 1. 요금제 기간 안내 문구 표출 {CCS_SERVICE_NAME} will be available for %s years, %s months from subscription date. ※ CLDR 적용 in %s day(s) - CLDR 적용 (당일일 경우 ‘in 1 day’, 이외 ‘in n days’) | N55: =IF(COUNTIF(P55:W55,"F")>=1,"FAIL",(IF(COUNTIF(P55:W55,"P")>=1,"PASS",(IF(COUNTIF(P55:W55,"N/T")>=1,"N/T",(IF(COUNTIF(P55:W55,"N/A")>=1,"N/A","-"))))))) | O55: =IF(COUNTIF(P55:Q55,"F")>=1,"FAIL",(IF(COUNTIF(P55:Q55,"P")>=1,"PASS",(IF(COUNTIF(P55:Q55,"N/T")>=1,"N/T",(IF(COUNTIF(P55:Q55,"N/A")>=1,"N/A","-"))))))) | P55: P | Q55: F | R55: =IF(COUNTIF(S55:T55,"F")>=1,"FAIL",(IF(COUNTIF(S55:T55,"P")>=1,"PASS",(IF(COUNTIF(S55:T55,"N/T")>=1,"N/T",(IF(COUNTIF(S55:T55,"N/A")>=1,"N/A","-"))))))) | S55: N/A | T55: N/A | U55: =IF(COUNTIF(V55:W55,"F")>=1,"FAIL",(IF(COUNTIF(V55:W55,"P")>=1,"PASS",(IF(COUNTIF(V55:W55,"N/T")>=1,"N/T",(IF(COUNTIF(V55:W55,"N/A")>=1,"N/A","-"))))))) | V55: P | W55: P | X55: SPAQA-25686(TASK) SPAQA-25752 SPAQA-25774 SPAQA-25948 SPAQA-25812(TASK) | Y55: SPAQA-26260 | Z55: H : 비대상 브랜드 (N/A) | AA55: 사양 아님(N/A) | AB55: TASK, Proxy
B56: TC_MyCar_0022 | C56: My Car | D56: CCS 가입 정보 | E56: CCS 가입 정보 | F56: CCS 가입 정보 | G56: KR, EU | I56: 5 | J56: 1. 신약관 미동의 2. 차주인 경우 | L56: 1. My Car 진입 2. 차량 관리 진입 3. {CCS_SERVICE} 선택 | M56: 1. 신약관 동의 관련 영역 표출 약관 개정 안내 {CCS_SERVICE_NAME} 이용약관에 재동의 후 서비스를 이용해 주세요. [자세히 보기] | N56: =IF(COUNTIF(P56:W56,"F")>=1,"FAIL",(IF(COUNTIF(P56:W56,"P")>=1,"PASS",(IF(COUNTIF(P56:W56,"N/T")>=1,"N/T",(IF(COUNTIF(P56:W56,"N/A")>=1,"N/A","-"))))))) | O56: =IF(COUNTIF(P56:Q56,"F")>=1,"FAIL",(IF(COUNTIF(P56:Q56,"P")>=1,"PASS",(IF(COUNTIF(P56:Q56,"N/T")>=1,"N/T",(IF(COUNTIF(P56:Q56,"N/A")>=1,"N/A","-"))))))) | P56: N/T | Q56: N/T | R56: =IF(COUNTIF(S56:T56,"F")>=1,"FAIL",(IF(COUNTIF(S56:T56,"P")>=1,"PASS",(IF(COUNTIF(S56:T56,"N/T")>=1,"N/T",(IF(COUNTIF(S56:T56,"N/A")>=1,"N/A","-"))))))) | S56: N/T | T56: N/T | U56: =IF(COUNTIF(V56:W56,"F")>=1,"FAIL",(IF(COUNTIF(V56:W56,"P")>=1,"PASS",(IF(COUNTIF(V56:W56,"N/T")>=1,"N/T",(IF(COUNTIF(V56:W56,"N/A")>=1,"N/A","-"))))))) | V56: N/T | W56: N/T | X56: SPAQA-16856(TASK) SPAQA-19001(TASK) | Z56: (공통) 신약관 미동의 환경 필요 (N/T) | AA56: N/T : 특수상황/실패 조건 필요(조건) | AB56: TASK
B57: TC_MyCar_0050 | C57: My Car | D57: 차량 공유 및 프로필 | E57: 프로필 관리 | F57: 프로필 연동 | G57: EU | I57: 1 | K57: 1. 차량 프로필 연동 시도 | L57: 1. 프로필 연동 PUSH 팝업 확인 2. 팝업 내 [Cancel] 선택 | M57: 1. 팝업 닫히며 현재 화면 유지되는지 확인한다. | N57: =IF(COUNTIF(P57:W57,"F")>=1,"FAIL",(IF(COUNTIF(P57:W57,"P")>=1,"PASS",(IF(COUNTIF(P57:W57,"N/T")>=1,"N/T",(IF(COUNTIF(P57:W57,"N/A")>=1,"N/A","-"))))))) | O57: =IF(COUNTIF(P57:Q57,"F")>=1,"FAIL",(IF(COUNTIF(P57:Q57,"P")>=1,"PASS",(IF(COUNTIF(P57:Q57,"N/T")>=1,"N/T",(IF(COUNTIF(P57:Q57,"N/A")>=1,"N/A","-"))))))) | P57: P | Q57: P | R57: =IF(COUNTIF(S57:T57,"F")>=1,"FAIL",(IF(COUNTIF(S57:T57,"P")>=1,"PASS",(IF(COUNTIF(S57:T57,"N/T")>=1,"N/T",(IF(COUNTIF(S57:T57,"N/A")>=1,"N/A","-"))))))) | S57: P | T57: P | U57: =IF(COUNTIF(V57:W57,"F")>=1,"FAIL",(IF(COUNTIF(V57:W57,"P")>=1,"PASS",(IF(COUNTIF(V57:W57,"N/T")>=1,"N/T",(IF(COUNTIF(V57:W57,"N/A")>=1,"N/A","-"))))))) | V57: P | W57: P | X57: spaqa-17026(TASK) | AB57: CheckList, 실차, TASK
B58: TC_MyCar_0024 | C58: My Car | D58: CCS 가입 정보 | E58: CCS 가입 정보 | F58: CCS 가입 정보 | G58: KR, EU | I58: 4 | J58: 1. CCS 미가입 상태 2. 피공유자인 경우 | L58: 1. My Car 진입 2. 차량 관리 진입 3. {CCS_SERVICE} 선택 | M58: 1. 진입 불가 안내 팝업 표출 - Please obtain {CCS_SERVICE} permission from the main user first. - [Close] | N58: =IF(COUNTIF(P58:W58,"F")>=1,"FAIL",(IF(COUNTIF(P58:W58,"P")>=1,"PASS",(IF(COUNTIF(P58:W58,"N/T")>=1,"N/T",(IF(COUNTIF(P58:W58,"N/A")>=1,"N/A","-"))))))) | O58: =IF(COUNTIF(P58:Q58,"F")>=1,"FAIL",(IF(COUNTIF(P58:Q58,"P")>=1,"PASS",(IF(COUNTIF(P58:Q58,"N/T")>=1,"N/T",(IF(COUNTIF(P58:Q58,"N/A")>=1,"N/A","-"))))))) | P58: P | Q58: P | R58: =IF(COUNTIF(S58:T58,"F")>=1,"FAIL",(IF(COUNTIF(S58:T58,"P")>=1,"PASS",(IF(COUNTIF(S58:T58,"N/T")>=1,"N/T",(IF(COUNTIF(S58:T58,"N/A")>=1,"N/A","-"))))))) | S58: P | T58: P | U58: =IF(COUNTIF(V58:W58,"F")>=1,"FAIL",(IF(COUNTIF(V58:W58,"P")>=1,"PASS",(IF(COUNTIF(V58:W58,"N/T")>=1,"N/T",(IF(COUNTIF(V58:W58,"N/A")>=1,"N/A","-"))))))) | V58: P | W58: P | X58: SPAQA-16856(TASK) | Z58: K : wbkong | AB58: TASK
B59: TC_MyCar_0025 | C59: My Car | D59: CCS 가입 정보 | E59: CCS 가입 정보 | F59: CCS 가입 정보 | G59: KR, EU | I59: 5 | J59: 1. 신약관 미동의 2. 피공유자인 경우 | L59: 1. My Car 진입 2. 차량 관리 진입 3. {CCS_SERVICE} 선택 | M59: 1. 신약관 동의 관련 영역 표출 약관 개정 안내 {CCS_SERVICE_NAME} 이용약관에 재동의 후 서비스를 이용해 주세요. [자세히 보기] | N59: =IF(COUNTIF(P59:W59,"F")>=1,"FAIL",(IF(COUNTIF(P59:W59,"P")>=1,"PASS",(IF(COUNTIF(P59:W59,"N/T")>=1,"N/T",(IF(COUNTIF(P59:W59,"N/A")>=1,"N/A","-"))))))) | O59: =IF(COUNTIF(P59:Q59,"F")>=1,"FAIL",(IF(COUNTIF(P59:Q59,"P")>=1,"PASS",(IF(COUNTIF(P59:Q59,"N/T")>=1,"N/T",(IF(COUNTIF(P59:Q59,"N/A")>=1,"N/A","-"))))))) | P59: N/T | Q59: N/T | R59: =IF(COUNTIF(S59:T59,"F")>=1,"FAIL",(IF(COUNTIF(S59:T59,"P")>=1,"PASS",(IF(COUNTIF(S59:T59,"N/T")>=1,"N/T",(IF(COUNTIF(S59:T59,"N/A")>=1,"N/A","-"))))))) | S59: N/T | T59: N/T | U59: =IF(COUNTIF(V59:W59,"F")>=1,"FAIL",(IF(COUNTIF(V59:W59,"P")>=1,"PASS",(IF(COUNTIF(V59:W59,"N/T")>=1,"N/T",(IF(COUNTIF(V59:W59,"N/A")>=1,"N/A","-"))))))) | V59: N/T | W59: N/T | X59: SPAQA-16856(TASK) SPAQA-19336 | Z59: (공통) 신약관 미동의 환경 필요 | AA59: N/T : 특수상황/실패 조건 필요(조건) | AB59: TASK
B60: TC_MyCar_0026 | C60: My Car | D60: CCS 가입 정보 | E60: CCS 가입 정보 | F60: CCS 가입 정보 | G60: KR, EU | I60: 4 | J60: 1. CCS 정상 이용 2. 피공유자인 경우 | L60: 1. My Car 진입 2. 차량 관리 진입 3. {CCS_SERVICE} 선택 | M60: 1. 가입일 , 만료일, 차대번호 표출 - Subscription date - Expiration date - Vin | N60: =IF(COUNTIF(P60:W60,"F")>=1,"FAIL",(IF(COUNTIF(P60:W60,"P")>=1,"PASS",(IF(COUNTIF(P60:W60,"N/T")>=1,"N/T",(IF(COUNTIF(P60:W60,"N/A")>=1,"N/A","-"))))))) | O60: =IF(COUNTIF(P60:Q60,"F")>=1,"FAIL",(IF(COUNTIF(P60:Q60,"P")>=1,"PASS",(IF(COUNTIF(P60:Q60,"N/T")>=1,"N/T",(IF(COUNTIF(P60:Q60,"N/A")>=1,"N/A","-"))))))) | P60: P | Q60: P | R60: =IF(COUNTIF(S60:T60,"F")>=1,"FAIL",(IF(COUNTIF(S60:T60,"P")>=1,"PASS",(IF(COUNTIF(S60:T60,"N/T")>=1,"N/T",(IF(COUNTIF(S60:T60,"N/A")>=1,"N/A","-"))))))) | S60: P | T60: P | U60: =IF(COUNTIF(V60:W60,"F")>=1,"FAIL",(IF(COUNTIF(V60:W60,"P")>=1,"PASS",(IF(COUNTIF(V60:W60,"N/T")>=1,"N/T",(IF(COUNTIF(V60:W60,"N/A")>=1,"N/A","-"))))))) | V60: P | W60: P | X60: SPAQA-16856(TASK) | Z60: hoa.eu01@gmail.com 계정으로 확인 | AB60: TASK
B61: TC_MyCar_0027 | C61: My Car | D61: CCS 가입 정보 | E61: CCS 가입 정보 | F61: CCS 가입 정보 | G61: KR, EU | I61: 5 | J61: 1. 안전모드 상태 | K61: 1. CCS 이용 불가 2. 차주인 경우 | L61: 1. My Car 진입 2. 차량 관리 진입 3. {CCS_SERVICE} 선택 | M61: 1. 가입정보 화면 진입 불가 | N61: =IF(COUNTIF(P61:W61,"F")>=1,"FAIL",(IF(COUNTIF(P61:W61,"P")>=1,"PASS",(IF(COUNTIF(P61:W61,"N/T")>=1,"N/T",(IF(COUNTIF(P61:W61,"N/A")>=1,"N/A","-"))))))) | O61: =IF(COUNTIF(P61:Q61,"F")>=1,"FAIL",(IF(COUNTIF(P61:Q61,"P")>=1,"PASS",(IF(COUNTIF(P61:Q61,"N/T")>=1,"N/T",(IF(COUNTIF(P61:Q61,"N/A")>=1,"N/A","-"))))))) | P61: P | Q61: P | R61: =IF(COUNTIF(S61:T61,"F")>=1,"FAIL",(IF(COUNTIF(S61:T61,"P")>=1,"PASS",(IF(COUNTIF(S61:T61,"N/T")>=1,"N/T",(IF(COUNTIF(S61:T61,"N/A")>=1,"N/A","-"))))))) | S61: P | T61: P | U61: =IF(COUNTIF(V61:W61,"F")>=1,"FAIL",(IF(COUNTIF(V61:W61,"P")>=1,"PASS",(IF(COUNTIF(V61:W61,"N/T")>=1,"N/T",(IF(COUNTIF(V61:W61,"N/A")>=1,"N/A","-"))))))) | V61: P | W61: P | X61: SPAQA-18314(TASK) | AB61: TASK
B62: TC_MyCar_0028 | C62: My Car | D62: CCS 가입 정보 | E62: CCS 가입 정보 | F62: CCS 가입 정보 | G62: KR, EU | I62: 5 | J62: 1. 안전모드 상태 | K62: 1. CCS 이용 불가 2. 차주인 경우 | L62: 1. My Car 진입 2. 차량 관리 진입 3. {CCS_SERVICE} 선택 | M62: 1. 가입정보 화면 진입 불가 팝업 표출 "Service is temporarily restricted due to an unstable vehicle connection. Service will return to normal when the connection improves. ※ You may not receive push notifications in the current state. Close" * close 선택시 팝업 소거 | N62: =IF(COUNTIF(P62:W62,"F")>=1,"FAIL",(IF(COUNTIF(P62:W62,"P")>=1,"PASS",(IF(COUNTIF(P62:W62,"N/T")>=1,"N/T",(IF(COUNTIF(P62:W62,"N/A")>=1,"N/A","-"))))))) | O62: =IF(COUNTIF(P62:Q62,"F")>=1,"FAIL",(IF(COUNTIF(P62:Q62,"P")>=1,"PASS",(IF(COUNTIF(P62:Q62,"N/T")>=1,"N/T",(IF(COUNTIF(P62:Q62,"N/A")>=1,"N/A","-"))))))) | P62: P | Q62: P | R62: =IF(COUNTIF(S62:T62,"F")>=1,"FAIL",(IF(COUNTIF(S62:T62,"P")>=1,"PASS",(IF(COUNTIF(S62:T62,"N/T")>=1,"N/T",(IF(COUNTIF(S62:T62,"N/A")>=1,"N/A","-"))))))) | S62: P | T62: P | U62: =IF(COUNTIF(V62:W62,"F")>=1,"FAIL",(IF(COUNTIF(V62:W62,"P")>=1,"PASS",(IF(COUNTIF(V62:W62,"N/T")>=1,"N/T",(IF(COUNTIF(V62:W62,"N/A")>=1,"N/A","-"))))))) | V62: P | W62: P | X62: SPAQA-18314(TASK) | Z62: 아래 문구 확인 Service temporarily restricted due to unstable vehicle connection. Full service functionaliy will be available when the connection improves. ※ You may not receive push notifications in the current condition | AB62: TASK
B63: TC_MyCar_0029 | C63: My Car | D63: CCS 가입 정보 | E63: CCS 가입 정보 | F63: 신약관 개정 안내 | G63: EU | I63: 5 | J63: 1. 신약관 미동의 | L63: 1. My Car 진입 2. 차량 관리 진입 3. {CCS_SERVICE} 선택 | M63: 1. 신약관 동의 관련 영역 표출 약관 개정 안내 {CCS_SERVICE_NAME} 이용약관에 재동의 후 서비스를 이용해 주세요. [자세히 보기] | N63: =IF(COUNTIF(P63:W63,"F")>=1,"FAIL",(IF(COUNTIF(P63:W63,"P")>=1,"PASS",(IF(COUNTIF(P63:W63,"N/T")>=1,"N/T",(IF(COUNTIF(P63:W63,"N/A")>=1,"N/A","-"))))))) | O63: =IF(COUNTIF(P63:Q63,"F")>=1,"FAIL",(IF(COUNTIF(P63:Q63,"P")>=1,"PASS",(IF(COUNTIF(P63:Q63,"N/T")>=1,"N/T",(IF(COUNTIF(P63:Q63,"N/A")>=1,"N/A","-"))))))) | P63: N/T | Q63: N/T | R63: =IF(COUNTIF(S63:T63,"F")>=1,"FAIL",(IF(COUNTIF(S63:T63,"P")>=1,"PASS",(IF(COUNTIF(S63:T63,"N/T")>=1,"N/T",(IF(COUNTIF(S63:T63,"N/A")>=1,"N/A","-"))))))) | S63: N/T | T63: N/T | U63: =IF(COUNTIF(V63:W63,"F")>=1,"FAIL",(IF(COUNTIF(V63:W63,"P")>=1,"PASS",(IF(COUNTIF(V63:W63,"N/T")>=1,"N/T",(IF(COUNTIF(V63:W63,"N/A")>=1,"N/A","-"))))))) | V63: N/T | W63: N/T | X63: SPAQA-19336 | Z63: (공통) 신약관 미동의 환경 필요 | AA63: N/T : 특수상황/실패 조건 필요(조건)
B64: TC_MyCar_0030 | C64: My Car | D64: CCS 가입 정보 | E64: CCS 가입 정보 | F64: 신약관 개정 안내 | G64: EU | I64: 5 | J64: 1. 신약관 미동의 | L64: 1. My Car 진입 2. 차량 관리 진입 3. {CCS_SERVICE} 선택 4. [자세히 보기] 버튼 선택 | M64: 1. 신약관 이용 동의 화면으로 이동 < {CCS_SERVICE} 이용 약관 {CCS_SERVICE} 이용 약관에 동의해 주세요. □ [필수] 이용약관 제목(서버) > □ 전체 약관에 동의합니다. [동의] * 필수, 선택 약관 여부는 서버에서 수신 * < 버튼 선택 시 이전 화면 이동 | N64: =IF(COUNTIF(P64:W64,"F")>=1,"FAIL",(IF(COUNTIF(P64:W64,"P")>=1,"PASS",(IF(COUNTIF(P64:W64,"N/T")>=1,"N/T",(IF(COUNTIF(P64:W64,"N/A")>=1,"N/A","-"))))))) | O64: =IF(COUNTIF(P64:Q64,"F")>=1,"FAIL",(IF(COUNTIF(P64:Q64,"P")>=1,"PASS",(IF(COUNTIF(P64:Q64,"N/T")>=1,"N/T",(IF(COUNTIF(P64:Q64,"N/A")>=1,"N/A","-"))))))) | P64: N/T | Q64: N/T | R64: =IF(COUNTIF(S64:T64,"F")>=1,"FAIL",(IF(COUNTIF(S64:T64,"P")>=1,"PASS",(IF(COUNTIF(S64:T64,"N/T")>=1,"N/T",(IF(COUNTIF(S64:T64,"N/A")>=1,"N/A","-"))))))) | S64: N/T | T64: N/T | U64: =IF(COUNTIF(V64:W64,"F")>=1,"FAIL",(IF(COUNTIF(V64:W64,"P")>=1,"PASS",(IF(COUNTIF(V64:W64,"N/T")>=1,"N/T",(IF(COUNTIF(V64:W64,"N/A")>=1,"N/A","-"))))))) | V64: N/T | W64: N/T | Z64: (공통) 신약관 미동의 환경 필요 | AA64: N/T : 특수상황/실패 조건 필요(조건)
B65: TC_MyCar_0463 | C65: My Car | D65: CCS 가입 정보 | E65: CCS 가입 정보 | F65: CCS 가입 정보 | G65: EU | I65: 6 | J65: 1. 차량 2대 이상 등록 된 상황 | L65: 1. My Car 진입 2. 이용 가능한 차량 목록 진입 3. 대표 차량 아닌 차량 선택 4. [Set a main vehicle] 버튼 선택 5. 상단 토스트 확인 | M65: 1. 차량 변경시 토스트 팝업 노출 | N65: =IF(COUNTIF(P65:W65,"F")>=1,"FAIL",(IF(COUNTIF(P65:W65,"P")>=1,"PASS",(IF(COUNTIF(P65:W65,"N/T")>=1,"N/T",(IF(COUNTIF(P65:W65,"N/A")>=1,"N/A","-"))))))) | O65: =IF(COUNTIF(P65:Q65,"F")>=1,"FAIL",(IF(COUNTIF(P65:Q65,"P")>=1,"PASS",(IF(COUNTIF(P65:Q65,"N/T")>=1,"N/T",(IF(COUNTIF(P65:Q65,"N/A")>=1,"N/A","-"))))))) | P65: P | Q65: P | R65: =IF(COUNTIF(S65:T65,"F")>=1,"FAIL",(IF(COUNTIF(S65:T65,"P")>=1,"PASS",(IF(COUNTIF(S65:T65,"N/T")>=1,"N/T",(IF(COUNTIF(S65:T65,"N/A")>=1,"N/A","-"))))))) | S65: P | T65: P | U65: =IF(COUNTIF(V65:W65,"F")>=1,"FAIL",(IF(COUNTIF(V65:W65,"P")>=1,"PASS",(IF(COUNTIF(V65:W65,"N/T")>=1,"N/T",(IF(COUNTIF(V65:W65,"N/A")>=1,"N/A","-"))))))) | V65: P | W65: P | X65: SPAQA-25621
B66: TC_MyCar_0031 | C66: My Car | D66: CCS 가입 정보 | E66: CCS 가입 정보 | F66: 신약관 개정 안내 | G66: EU | I66: 5 | J66: 1. 신약관 미동의 | L66: 1. My Car 진입 2. 차량 관리 진입 3. {CCS_SERVICE} 선택 4. [자세히 보기] 버튼 선택 5. 각 약관의 [>] 버튼 선택 | M66: 1. 해당 약관동의 별도 화면이 호출된다. | N66: =IF(COUNTIF(P66:W66,"F")>=1,"FAIL",(IF(COUNTIF(P66:W66,"P")>=1,"PASS",(IF(COUNTIF(P66:W66,"N/T")>=1,"N/T",(IF(COUNTIF(P66:W66,"N/A")>=1,"N/A","-"))))))) | O66: =IF(COUNTIF(P66:Q66,"F")>=1,"FAIL",(IF(COUNTIF(P66:Q66,"P")>=1,"PASS",(IF(COUNTIF(P66:Q66,"N/T")>=1,"N/T",(IF(COUNTIF(P66:Q66,"N/A")>=1,"N/A","-"))))))) | P66: N/A | Q66: N/A | R66: =IF(COUNTIF(S66:T66,"F")>=1,"FAIL",(IF(COUNTIF(S66:T66,"P")>=1,"PASS",(IF(COUNTIF(S66:T66,"N/T")>=1,"N/T",(IF(COUNTIF(S66:T66,"N/A")>=1,"N/A","-"))))))) | S66: N/A | T66: N/A | U66: =IF(COUNTIF(V66:W66,"F")>=1,"FAIL",(IF(COUNTIF(V66:W66,"P")>=1,"PASS",(IF(COUNTIF(V66:W66,"N/T")>=1,"N/T",(IF(COUNTIF(V66:W66,"N/A")>=1,"N/A","-"))))))) | V66: N/A | W66: N/A | Z66: ICT 영역 | AA66: EU 미지원 기능(N/A) | AB66: 삭제
B67: TC_MyCar_0032 | C67: My Car | D67: CCS 가입 정보 | E67: CCS 가입 정보 | F67: 신약관 개정 안내 | G67: EU | I67: 5 | J67: 1. 신약관 미동의 | L67: 1. My Car 진입 2. 차량 관리 진입 3. {CCS_SERVICE} 선택 4. [자세히 보기] 버튼 선택 5. 체크박스 선택/재선택 6. [전체 약관에 동의합니다.] 체크박스 선택 | M67: 1. 선택한 체크박스가 정상적으로 체크된다. 2. 선택한 체크박스를 재선택 시 체크 해제된다. 3. [전체 약관에 동의합니다.] 체크 시 모든 약관의 체크박스가 체크된다. | N67: =IF(COUNTIF(P67:W67,"F")>=1,"FAIL",(IF(COUNTIF(P67:W67,"P")>=1,"PASS",(IF(COUNTIF(P67:W67,"N/T")>=1,"N/T",(IF(COUNTIF(P67:W67,"N/A")>=1,"N/A","-"))))))) | O67: =IF(COUNTIF(P67:Q67,"F")>=1,"FAIL",(IF(COUNTIF(P67:Q67,"P")>=1,"PASS",(IF(COUNTIF(P67:Q67,"N/T")>=1,"N/T",(IF(COUNTIF(P67:Q67,"N/A")>=1,"N/A","-"))))))) | P67: N/A | Q67: N/A | R67: =IF(COUNTIF(S67:T67,"F")>=1,"FAIL",(IF(COUNTIF(S67:T67,"P")>=1,"PASS",(IF(COUNTIF(S67:T67,"N/T")>=1,"N/T",(IF(COUNTIF(S67:T67,"N/A")>=1,"N/A","-"))))))) | S67: N/A | T67: N/A | U67: =IF(COUNTIF(V67:W67,"F")>=1,"FAIL",(IF(COUNTIF(V67:W67,"P")>=1,"PASS",(IF(COUNTIF(V67:W67,"N/T")>=1,"N/T",(IF(COUNTIF(V67:W67,"N/A")>=1,"N/A","-"))))))) | V67: N/A | W67: N/A | Z67: ICT 영역 | AA67: EU 미지원 기능(N/A) | AB67: 삭제
B68: TC_MyCar_0033 | C68: My Car | D68: CCS 가입 정보 | E68: CCS 가입 정보 | F68: 신약관 개정 안내 | G68: EU | I68: 5 | J68: 1. 신약관 미동의 | L68: 1. My Car 진입 2. 차량 관리 진입 3. {CCS_SERVICE} 선택 4. [자세히 보기] 버튼 선택 5. 필수 약관 모두 체크 | M68: 1. [동의] 버튼이 활성화된다. | N68: =IF(COUNTIF(P68:W68,"F")>=1,"FAIL",(IF(COUNTIF(P68:W68,"P")>=1,"PASS",(IF(COUNTIF(P68:W68,"N/T")>=1,"N/T",(IF(COUNTIF(P68:W68,"N/A")>=1,"N/A","-"))))))) | O68: =IF(COUNTIF(P68:Q68,"F")>=1,"FAIL",(IF(COUNTIF(P68:Q68,"P")>=1,"PASS",(IF(COUNTIF(P68:Q68,"N/T")>=1,"N/T",(IF(COUNTIF(P68:Q68,"N/A")>=1,"N/A","-"))))))) | P68: N/A | Q68: N/A | R68: =IF(COUNTIF(S68:T68,"F")>=1,"FAIL",(IF(COUNTIF(S68:T68,"P")>=1,"PASS",(IF(COUNTIF(S68:T68,"N/T")>=1,"N/T",(IF(COUNTIF(S68:T68,"N/A")>=1,"N/A","-"))))))) | S68: N/A | T68: N/A | U68: =IF(COUNTIF(V68:W68,"F")>=1,"FAIL",(IF(COUNTIF(V68:W68,"P")>=1,"PASS",(IF(COUNTIF(V68:W68,"N/T")>=1,"N/T",(IF(COUNTIF(V68:W68,"N/A")>=1,"N/A","-"))))))) | V68: N/A | W68: N/A | Z68: ICT 영역 | AA68: EU 미지원 기능(N/A) | AB68: 삭제
B69: TC_MyCar_0034 | C69: My Car | D69: CCS 가입 정보 | E69: CCS 가입 정보 | F69: 신약관 개정 안내 | G69: EU | I69: 5 | J69: 1. 신약관 미동의 2. 차주로 로그인 했거나, 차주가 동의한 상태에서 피공유자 로그인 | L69: 1. My Car 진입 2. 차량 관리 진입 3. {CCS_SERVICE} 선택 4. [자세히 보기] 버튼 선택 5. 필수 약관 모두 체크 6. [동의] 버튼 선택 | M69: 1. 블록 해제되고, Control 화면 정상 진입 | N69: =IF(COUNTIF(P69:W69,"F")>=1,"FAIL",(IF(COUNTIF(P69:W69,"P")>=1,"PASS",(IF(COUNTIF(P69:W69,"N/T")>=1,"N/T",(IF(COUNTIF(P69:W69,"N/A")>=1,"N/A","-"))))))) | O69: =IF(COUNTIF(P69:Q69,"F")>=1,"FAIL",(IF(COUNTIF(P69:Q69,"P")>=1,"PASS",(IF(COUNTIF(P69:Q69,"N/T")>=1,"N/T",(IF(COUNTIF(P69:Q69,"N/A")>=1,"N/A","-"))))))) | P69: N/A | Q69: N/A | R69: =IF(COUNTIF(S69:T69,"F")>=1,"FAIL",(IF(COUNTIF(S69:T69,"P")>=1,"PASS",(IF(COUNTIF(S69:T69,"N/T")>=1,"N/T",(IF(COUNTIF(S69:T69,"N/A")>=1,"N/A","-"))))))) | S69: N/A | T69: N/A | U69: =IF(COUNTIF(V69:W69,"F")>=1,"FAIL",(IF(COUNTIF(V69:W69,"P")>=1,"PASS",(IF(COUNTIF(V69:W69,"N/T")>=1,"N/T",(IF(COUNTIF(V69:W69,"N/A")>=1,"N/A","-"))))))) | V69: N/A | W69: N/A | Z69: ICT 영역 | AA69: EU 미지원 기능(N/A) | AB69: 삭제
